Workbook

Sheet Dashboard
A1: MT5 Position Studio — Mentorship Report
A2: Account 3214929 · SarmayeGozareBartar-Real · USD · 73 closed trades · generated 12 Aug 2026 10:36
A5: Performance
A6: NET PROFIT | D6: RETURN | G6: WIN RATE | J6: PROFIT FACTOR | M6: EXPECTANCY
A7: 100.81 | D7: 10.08 | G7: 31.51 | J7: 1.343 | M7: 1.381
A8: USD · gross 394.87 | D8: on 1000.0 start | G8: 23W / 49L | J8: gross win ÷ gross loss | M8: per trade · 0.225R
A10: Risk
A11: MAX DRAWDOWN | D11: RECOVERY FACTOR | G11: PAYOFF RATIO | J11: SQN | M11: WORST STREAK
A12: -84.51 | D12: 1.193 | G12: 2.861 | J12: 0.86 | M12: 6
A13: 8.2% of peak | D13: net ÷ max drawdown | G13: avg win ÷ avg loss | J13: Below average | M13: best 3 · -54.4 deepest run
A15: Trade management
A16: AVG MFE | D16: AVG MAE | G16: WINNER CAPTURE | J16: MEDIAN HEAT | M16: GAVE BACK
A17: 8.68 | D17: -5.76 | G17: 0.933 | J17: 101.5 | M17: 25
A18: money offered | D18: heat taken | G18: median 0.988 | J18: p90 167.0% | M18: 51.0% of losers reached 0.5R
A20: Duration
A21: AVG DURATION | D21: MEDIAN DURATION | G21: AVG RISK | J21: RISK CONSISTENCY | M21: PLANNED RR
A22: 18m | D22: 10m | G22: 5.92 | J22: 0.408 | M22: 1.52
A23: 1105.6 seconds | D23: half the trades are shorter | G23: 0.59% of balance | J23: stdev ÷ mean · lower is steadier | M23: realised 0.225R
A25: Equity curve · balance in USD | K25: Outcome split | V25: Outcome | W25: Trades
V26: Wins | W26: 23
V27: Losses | W27: 49
V28: Breakeven | W28: 1
A44: R-multiple distribution · trades per band | K44: MFE offered (up) vs MAE heat taken (right) | V44: R band | W44: Trades
V45: <= -1.5R | W45: 8
V46: -1.5R..-1R | W46: 25
V47: -1R..-0.5R | W47: 4
V48: -0.5R..0 | W48: 12
V49: Breakeven | W49: 1
V50: 0..0.5R | W50: 2
V51: 1R..2R | W51: 4
V52: 2R..3R | W52: 10
V53: >= 3R | W53: 7
A63: Forward risk (Monte Carlo)
A64: 5,000 runs of 100 trades, drawn with replacement from this account's own 73 results - so the tails in the real record stay in the projection.
A66: MEDIAN OUTCOME | D66: BAD CASE (5%) | G66: GOOD CASE (95%) | J66: DRAWDOWN TO EXPECT | M66: CHANCE OF PROFIT
A67: 1130.48 | D67: 910.92 | G67: 1368.83 | J67: 91.16 | M67: 83.6
A68: balance after 100 trades | D68: 1 run in 20 ends here or worse | G68: 1 run in 20 ends here or better | J68: p95 181.1 · worst 363.37 | M68: risk of halving the account 0.0%
A72: Every figure on this sheet is computed from the Trades sheet, which is the only source of data in this workbook. Change a filter there and the pivot sheets follow; the cards above are point-in-time values from the run that generated the file.

Sheet Trades
A1: # | B1: Ticket | C1: Symbol | D1: Side | E1: Volume | F1: Opened | G1: Closed | H1: Weekday | I1: Hour | J1: Session | K1: Week | L1: Month | M1: Duration | N1: Duration (s) | O1: Duration (min) | P1: Duration band | Q1: Entry | R1: Exit | S1: SL initial | T1: TP initial | U1: SL final | V1: SL moved | W1: SL move (pts) | X1: Risk | Y1: Planned RR | Z1: R multiple | AA1: R band | AB1: Gross | AC1: Costs | AD1: Net | AE1: Outcome | AF1: Exit reason | AG1: Result (pts) | AH1: MFE | AI1: MAE | AJ1: MFE (R) | AK1: MAE (R) | AL1: MFE price | AM1: MAE price | AN1: Time to MFE | AO1: Time to MAE | AP1: Heat % | AQ1: Capture | AR1: Giveback | AS1: Entry eff. | AT1: Exit eff. | AU1: Total eff. | AV1: MFE first | AW1: Near miss | AX1: Risk % bal. | AY1: Balance after | AZ1: Drawdown | BA1: Drawdown % | BB1: Streak | BC1: Excursion src | BD1: Samples | BE1: Shots | BF1: Folder | BG1: Note
A2: 1 | B2: 55869735 | C2: DJIUSD | D2: buy | E2: 0.01 | F2: 46232.563 | G2: 46232.577 | H2: Wednesday | I2: 13 | J2: NY Overlap | K2: 2026-W31 | L2: 2026-07 | M2: 20m 10s | N2: 1209.936 | O2: 20.166 | P2: D. 15-30 min | Q2: 52300.64 | R2: 52201.35 | S2: 52216.33 | T2: 52366.08 | U2: 52201.74 | V2: Widened | W2: -1459 | X2: 8.43 | Y2: 0.776 | Z2: -1.178 | AA2: B. -1.5R..-1R | AB2: -9.93 | AC2: 0 | AD2: -9.93 | AE2: Loss | AF2: Stop Loss | AG2: -9929 | AH2: 5.92 | AI2: -10.23 | AJ2: 0.702 | AK2: -1.214 | AL2: 52359.85 | AM2: 52198.35 | AN2: 27s | AO2: 20m 10s | AP2: 121.4 | AQ2: -1.677 | AR2: 15.85 | AS2: 0.3666 | AT2: 0.0186 | AU2: -0.6148 | AV2: Yes | AW2: No | AX2: 0.843 | AY2: 990.07 | AZ2: 9.93 | BA2: 0.993 | BB2: -1 | BC2: ticks | BD2: 3017 | BE2: 9 | BF2: 3214929/DJIUSD/2026-07-29_55869735_DJIUSD_buy_loss
A3: 2 | B3: 55899455 | C3: DAXEUR | D3: sell | E3: 0.03 | F3: 46232.579 | G3: 46232.585 | H3: Wednesday | I3: 13 | J3: NY Overlap | K3: 2026-W31 | L3: 2026-07 | M3: 9m 01s | N3: 540.932 | O3: 9.016 | P3: C. 5-15 min | Q3: 25472.88 | R3: 25516.62 | S3: 25496.24 | T3: 25336.19 | U3: 25516.13 | V3: Widened | W3: -1989 | X3: 8.09 | Y3: 5.848 | Z3: -1.848 | AA3: A. <= -1.5R | AB3: -14.95 | AC3: 0 | AD3: -14.95 | AE3: Loss | AF3: Stop Loss | AG3: -4374 | AH3: 7.53 | AI3: -15.31 | AJ3: 0.931 | AK3: -1.892 | AL3: 25451.13 | AM3: 25517.12 | AN3: 4m 25s | AO3: 9m 01s | AP3: 189.2 | AQ3: -1.985 | AR3: 22.48 | AS3: 0.3296 | AT3: 0.0076 | AU3: -0.6628 | AV3: Yes | AW3: No | AX3: 0.817 | AY3: 975.12 | AZ3: 24.88 | BA3: 2.488 | BB3: -2 | BC3: ticks | BD3: 1036 | BE3: 9 | BF3: 3214929/DAXEUR/2026-07-29_55899455_DAXEUR_sell_loss
A4: 3 | B4: 55923534 | C4: DJIUSD | D4: buy | E4: 0.01 | F4: 46232.593 | G4: 46232.601 | H4: Wednesday | I4: 14 | J4: NY Overlap | K4: 2026-W31 | L4: 2026-07 | M4: 12m 05s | N4: 724.786 | O4: 12.08 | P4: C. 5-15 min | Q4: 51944.09 | R4: 51943.8 | S4: 51890.57 | T4: 51999.81 | U4: 51944.09 | V4: Breakeven | W4: 5352 | X4: 5.35 | Y4: 1.041 | Z4: -0.006 | AA4: D. -0.5R..0 | AB4: -0.03 | AC4: 0 | AD4: -0.03 | AE4: Loss | AF4: Stop Loss | AG4: -29 | AH4: 9.22 | AI4: -0.33 | AJ4: 1.723 | AK4: -0.062 | AL4: 52036.3 | AM4: 51940.8 | AN4: 8m 33s | AO4: 0.0s | AP4: 6.2 | AQ4: -0.003 | AR4: 9.25 | AS4: 0.9655 | AT4: 0.0314 | AU4: -0.003 | AV4: No | AW4: No | AX4: 0.549 | AY4: 975.09 | AZ4: 24.91 | BA4: 2.491 | BB4: -3 | BC4: ticks | BD4: 1707 | BE4: 9 | BF4: 3214929/DJIUSD/2026-07-29_55923534_DJIUSD_buy_loss
A5: 4 | B5: 55942814 | C5: DJIUSD | D5: buy | E5: 0.01 | F5: 46232.613 | G5: 46232.623 | H5: Wednesday | I5: 14 | J5: NY Overlap | K5: 2026-W31 | L5: 2026-07 | M5: 15m 06s | N5: 906.33 | O5: 15.105 | P5: D. 15-30 min | Q5: 51897.19 | R5: 51896.4 | S5: 51842.73 | T5: 51953.94 | U5: 51897.19 | V5: Breakeven | W5: 5446 | X5: 5.45 | Y5: 1.042 | Z5: -0.015 | AA5: D. -0.5R..0 | AB5: -0.08 | AC5: 0 | AD5: -0.08 | AE5: Loss | AF5: Stop Loss | AG5: -79 | AH5: 5.02 | AI5: -3.78 | AJ5: 0.921 | AK5: -0.694 | AL5: 51947.4 | AM5: 51859.4 | AN5: 11m 36s | AO5: 2m 06s | AP5: 69.4 | AQ5: -0.016 | AR5: 5.1 | AS5: 0.5706 | AT5: 0.4205 | AU5: -0.009 | AV5: No | AW5: No | AX5: 0.559 | AY5: 975.01 | AZ5: 24.99 | BA5: 2.499 | BB5: -4 | BC5: ticks | BD5: 1987 | BE5: 9 | BF5: 3214929/DJIUSD/2026-07-29_55942814_DJIUSD_buy_loss
A6: 5 | B6: 55934591 | C6: DJIUSD | D6: buy | E6: 0.01 | F6: 46232.602 | G6: 46232.642 | H6: Wednesday | I6: 14 | J6: NY Overlap | K6: 2026-W31 | L6: 2026-07 | M6: 56m 32s | N6: 3392.168 | O6: 56.536 | P6: E. 30-60 min | Q6: 51949.09 | R6: 51916.4 | S6: 51869.18 | T6: 52039.09 | U6: 51869.18 | V6: Unchanged | W6: 0 | X6: 7.99 | Y6: 1.126 | Z6: -0.409 | AA6: D. -0.5R..0 | AB6: -3.27 | AC6: 0 | AD6: -3.27 | AE6: Loss | AF6: Expert | AG6: -3269 | AH6: 3.18 | AI6: -8.97 | AJ6: 0.398 | AK6: -1.123 | AL6: 51980.9 | AM6: 51859.4 | AN6: 3m 18s | AO6: 16m 56s | AP6: 112.3 | AQ6: -1.028 | AR6: 6.45 | AS6: 0.2618 | AT6: 0.4691 | AU6: -0.2691 | AV6: Yes | AW6: No | AX6: 0.819 | AY6: 971.74 | AZ6: 28.26 | BA6: 2.826 | BB6: -5 | BC6: ticks | BD6: 7381 | BE6: 9 | BF6: 3214929/DJIUSD/2026-07-29_55934591_DJIUSD_buy_loss
A7: 6 | B7: 55973757 | C7: XAUUSD | D7: sell | E7: 0.01 | F7: 46232.663 | G7: 46232.672 | H7: Wednesday | I7: 15 | J7: NY Overlap | K7: 2026-W31 | L7: 2026-07 | M7: 13m 01s | N7: 780.652 | O7: 13.011 | P7: C. 5-15 min | Q7: 4012.18 | R7: 4012.16 | S7: 4016.77 | T7: 4007.13 | U7: 4012.13 | V7: Tightened | W7: 454 | X7: 4.59 | Y7: 1.1 | Z7: -0.007 | AA7: D. -0.5R..0 | AB7: 0.02 | AC7: -0.05 | AD7: -0.03 | AE7: Loss | AF7: Stop Loss | AG7: 2 | AH7: 4.26 | AI7: -0.5 | AJ7: 0.928 | AK7: -0.109 | AL7: 4007.92 | AM7: 4012.68 | AN7: 6m 41s | AO7: 5.2s | AP7: 10.9 | AQ7: -0.007 | AR7: 4.29 | AS7: 0.895 | AT7: 0.1092 | AU7: 0.0042 | AV7: No | AW7: No | AX7: 0.472 | AY7: 971.71 | AZ7: 28.29 | BA7: 2.829 | BB7: -6 | BC7: ticks | BD7: 1598 | BE7: 9 | BF7: 3214929/XAUUSD/2026-07-29_55973757_XAUUSD_sell_loss
A8: 7 | B8: 55955183 | C8: DAXEUR | D8: sell | E8: 0.01 | F8: 46232.627 | G8: 46232.677 | H8: Wednesday | I8: 15 | J8: NY Overlap | K8: 2026-W31 | L8: 2026-07 | M8: 1h 12m | N8: 4328.04 | O8: 72.134 | P8: F. 1-4 h | Q8: 25467.78 | R8: 25404.52 | S8: 25497.38 | T8: 25434.17 | U8: 25497.38 | V8: Unchanged | W8: 0 | X8: 3.41 | Y8: 1.138 | Z8: 2.111 | AA8: I. 2R..3R | AB8: 7.2 | AC8: 0 | AD8: 7.2 | AE8: Win | AF8: Take Profit | AG8: 6326 | AH8: 7.3 | AI8: -3.48 | AJ8: 2.141 | AK8: -1.021 | AL8: 25404.52 | AM8: 25497.98 | AN8: 1h 12m | AO8: 11m 06s | AP8: 102.1 | AQ8: 0.986 | AR8: 0.1 | AS8: 0.6769 | AT8: 1 | AU8: 0.6769 | AV8: No | AW8: No | AX8: 0.351 | AY8: 978.91 | AZ8: 21.09 | BA8: 2.109 | BB8: 1 | BC8: ticks | BD8: 6605 | BE8: 9 | BF8: 3214929/DAXEUR/2026-07-29_55955183_DAXEUR_sell_win
A9: 8 | B9: 55983574 | C9: DAXEUR | D9: sell | E9: 0.03 | F9: 46232.679 | G9: 46232.683 | H9: Wednesday | I9: 16 | J9: NY Overlap | K9: 2026-W31 | L9: 2026-07 | M9: 4m 52s | N9: 291.879 | O9: 4.865 | P9: B. 1-5 min | Q9: 25414.18 | R9: 25435.02 | S9: 25428.27 | T9: 25400.78 | U9: 25434.19 | V9: Widened | W9: -592 | X9: 4.88 | Y9: 0.951 | Z9: -1.457 | AA9: B. -1.5R..-1R | AB9: -7.11 | AC9: 0 | AD9: -7.11 | AE9: Loss | AF9: Stop Loss | AG9: -2084 | AH9: 0.23 | AI9: -9.11 | AJ9: 0.047 | AK9: -1.867 | AL9: 25413.52 | AM9: 25440.52 | AN9: 7.0s | AO9: 4m 53s | AP9: 186.7 | AQ9: -30.913 | AR9: 7.34 | AS9: 0.0244 | AT9: 0.2037 | AU9: -0.7719 | AV9: Yes | AW9: No | AX9: 0.499 | AY9: 971.8 | AZ9: 28.2 | BA9: 2.82 | BB9: -1 | BC9: ticks | BD9: 376 | BE9: 9 | BF9: 3214929/DAXEUR/2026-07-29_55983574_DAXEUR_sell_loss
A10: 9 | B10: 55984899 | C10: DAXEUR | D10: sell | E10: 0.03 | F10: 46232.682 | G10: 46232.683 | H10: Wednesday | I10: 16 | J10: NY Overlap | K10: 2026-W31 | L10: 2026-07 | M10: 50s | N10: 49.761 | O10: 0.829 | P10: A. < 1 min | Q10: 25426.68 | R10: 25440.52 | S10: 25438.21 | T10: 25412.95 | U10: 25438.21 | V10: Unchanged | W10: 0 | X10: 3.99 | Y10: 1.19 | Z10: -1.183 | AA10: B. -1.5R..-1R | AB10: -4.72 | AC10: 0 | AD10: -4.72 | AE10: Loss | AF10: Stop Loss | AG10: -1384 | AH10: 0.23 | AI10: -4.79 | AJ10: 0.058 | AK10: -1.201 | AL10: 25426.02 | AM10: 25440.52 | AN10: 10s | AO10: 50s | AP10: 120.1 | AQ10: -20.522 | AR10: 4.95 | AS10: 0.0455 | AT10: 0 | AU10: -0.9545 | AV10: Yes | AW10: No | AX10: 0.411 | AY10: 967.08 | AZ10: 32.92 | BA10: 3.292 | BB10: -2 | BC10: ticks | BD10: 60 | BE10: 9 | BF10: 3214929/DAXEUR/2026-07-29_55984899_DAXEUR_sell_loss
A11: 10 | B11: 55957591 | C11: DAXEUR | D11: sell | E11: 0.02 | F11: 46232.632 | G11: 46232.69 | H11: Wednesday | I11: 15 | J11: NY Overlap | K11: 2026-W31 | L11: 2026-07 | M11: 1h 24m | N11: 5051.891 | O11: 84.198 | P11: F. 1-4 h | Q11: 25482.78 | R11: 25443.62 | S11: 25500.68 | T11: 25463.09 | U11: 25500.68 | V11: Unchanged | W11: 0 | X11: 4.13 | Y11: 1.102 | Z11: 2.157 | AA11: I. 2R..3R | AB11: 8.91 | AC11: 0 | AD11: 8.91 | AE11: Win | AF11: Expert | AG11: 3916 | AH11: 18.52 | AI11: -3.51 | AJ11: 4.484 | AK11: -0.85 | AL11: 25402.52 | AM11: 25497.98 | AN11: 1h 05m | AO11: 4m 13s | AP11: 85 | AQ11: 0.481 | AR11: 9.61 | AS11: 0.8408 | AT11: 0.5695 | AU11: 0.4102 | AV11: No | AW11: No | AX11: 0.427 | AY11: 975.99 | AZ11: 24.01 | BA11: 2.401 | BB11: 1 | BC11: ticks | BD11: 7368 | BE11: 9 | BF11: 3214929/DAXEUR/2026-07-29_55957591_DAXEUR_sell_win
A12: 11 | B12: 55988453 | C12: XAUUSD | D12: sell | E12: 0.01 | F12: 46232.689 | G12: 46232.69 | H12: Wednesday | I12: 16 | J12: NY Overlap | K12: 2026-W31 | L12: 2026-07 | M12: 2m 03s | N12: 123.074 | O12: 2.051 | P12: B. 1-5 min | Q12: 4015.12 | R12: 4018.69 | S12: 4018.63 | T12: 4011.21 | U12: 4018.63 | V12: Unchanged | W12: 0 | X12: 3.51 | Y12: 1.114 | Z12: -1.031 | AA12: B. -1.5R..-1R | AB12: -3.57 | AC12: -0.05 | AD12: -3.62 | AE12: Loss | AF12: Stop Loss | AG12: -357 | AH12: 0 | AI12: -3.83 | AJ12: 0 | AK12: -1.091 | AL12: 4015.21 | AM12: 4018.95 | AN12: 18s | AO12: 2m 04s | AP12: 109.1 | AS12: -0.0241 | AT12: 0.0695 | AU12: -0.9545 | AV12: Yes | AW12: No | AX12: 0.36 | AY12: 972.37 | AZ12: 27.63 | BA12: 2.763 | BB12: -1 | BC12: ticks | BD12: 249 | BE12: 9 | BF12: 3214929/XAUUSD/2026-07-29_55988453_XAUUSD_sell_loss
A13: 12 | B13: 55992315 | C13: NIKJPY | D13: sell | E13: 0.11 | F13: 46232.699 | G13: 46232.703 | H13: Wednesday | I13: 16 | J13: NY Overlap | K13: 2026-W31 | L13: 2026-07 | M13: 5m 31s | N13: 330.514 | O13: 5.509 | P13: C. 5-15 min | Q13: 61579 | R13: 61667 | S13: 61719 | T13: 61423 | U13: 61719 | V13: Unchanged | W13: 0 | X13: 9.67 | Y13: 1.114 | Z13: -0.611 | AA13: C. -1R..-0.5R | AB13: -5.91 | AC13: 0 | AD13: -5.91 | AE13: Loss | AF13: Expert | AG13: -88 | AH13: 0.35 | AI13: -6.22 | AJ13: 0.036 | AK13: -0.643 | AL13: 61574 | AM13: 61669 | AN13: 29s | AO13: 3m 07s | AP13: 64.3 | AQ13: -16.886 | AR13: 6.26 | AS13: 0.0526 | AT13: 0.0211 | AU13: -0.9263 | AV13: Yes | AW13: No | AX13: 0.994 | AY13: 966.46 | AZ13: 33.54 | BA13: 3.354 | BB13: -2 | BC13: ticks | BD13: 476 | BE13: 9 | BF13: 3214929/NIKJPY/2026-07-29_55992315_NIKJPY_sell_loss
A14: 13 | B14: 55991304 | C14: XAUUSD | D14: sell | E14: 0.02 | F14: 46232.703 | G14: 46232.703 | H14: Wednesday | I14: 16 | J14: NY Overlap | K14: 2026-W31 | L14: 2026-07 | M14: 45s | N14: 45.213 | O14: 0.754 | P14: A. < 1 min | Q14: 4020.33 | R14: 4023.24 | S14: 4024.88 | T14: 4015 | U14: 4024.88 | V14: Unchanged | W14: 0 | X14: 9.1 | Y14: 1.171 | Z14: -0.649 | AA14: C. -1R..-0.5R | AB14: -5.82 | AC14: -0.09 | AD14: -5.91 | AE14: Loss | AF14: Expert | AG14: -291 | AH14: 0 | AI14: -5.82 | AJ14: 0 | AK14: -0.64 | AL14: 4020.33 | AM14: 4023.24 | AN14: 0.4s | AO14: 45s | AP14: 64 | AS14: 0 | AT14: 0 | AU14: -1 | AV14: Yes | AW14: No | AX14: 0.942 | AY14: 960.55 | AZ14: 39.45 | BA14: 3.945 | BB14: -3 | BC14: ticks | BD14: 99 | BE14: 9 | BF14: 3214929/XAUUSD/2026-07-29_55991304_XAUUSD_sell_loss
A15: 14 | B15: 55997123 | C15: XAUUSD | D15: buy | E15: 0.01 | F15: 46232.706 | G15: 46232.708 | H15: Wednesday | I15: 16 | J15: NY Overlap | K15: 2026-W31 | L15: 2026-07 | M15: 2m 32s | N15: 151.813 | O15: 2.53 | P15: B. 1-5 min | Q15: 4030.62 | R15: 4026.7 | S15: 4027.37 | T15: 4034.69 | U15: 4026.7 | V15: Widened | W15: -67 | X15: 3.25 | Y15: 1.252 | Z15: -1.222 | AA15: B. -1.5R..-1R | AB15: -3.92 | AC15: -0.05 | AD15: -3.97 | AE15: Loss | AF15: Stop Loss | AG15: -392 | AH15: 2.11 | AI15: -3.92 | AJ15: 0.649 | AK15: -1.206 | AL15: 4032.73 | AM15: 4026.7 | AN15: 39s | AO15: 2m 32s | AP15: 120.6 | AQ15: -1.882 | AR15: 6.08 | AS15: 0.3499 | AT15: 0 | AU15: -0.6501 | AV15: Yes | AW15: No | AX15: 0.338 | AY15: 956.58 | AZ15: 43.42 | BA15: 4.342 | BB15: -4 | BC15: ticks | BD15: 386 | BE15: 9 | BF15: 3214929/XAUUSD/2026-07-29_55997123_XAUUSD_buy_loss
A16: 15 | B16: 56010530 | C16: XAUUSD | D16: buy | E16: 0.01 | F16: 46232.728 | G16: 46232.736 | H16: Wednesday | I16: 17 | J16: NY Late | K16: 2026-W31 | L16: 2026-07 | M16: 11m 47s | N16: 706.747 | O16: 11.779 | P16: C. 5-15 min | Q16: 4041.55 | R16: 4041.59 | S16: 4036.22 | T16: 4047.45 | U16: 4041.6 | V16: Tightened | W16: 528 | X16: 5.33 | Y16: 1.107 | Z16: -0.002 | AA16: D. -0.5R..0 | AB16: 0.04 | AC16: -0.05 | AD16: -0.01 | AE16: Loss | AF16: Stop Loss | AG16: 4 | AH16: 0.69 | AI16: -5.27 | AJ16: 0.129 | AK16: -0.989 | AL16: 4042.24 | AM16: 4036.28 | AN16: 11m 40s | AO16: 7m 26s | AP16: 98.9 | AQ16: -0.014 | AR16: 0.7 | AS16: 0.1158 | AT16: 0.8909 | AU16: 0.0067 | AV16: No | AW16: No | AX16: 0.557 | AY16: 956.57 | AZ16: 43.43 | BA16: 4.343 | BB16: -5 | BC16: ticks | BD16: 1648 | BE16: 9 | BF16: 3214929/XAUUSD/2026-07-29_56010530_XAUUSD_buy_loss
A17: 16 | B17: 56010917 | C17: XAUUSD | D17: buy | E17: 0.01 | F17: 46232.729 | G17: 46232.739 | H17: Wednesday | I17: 17 | J17: NY Late | K17: 2026-W31 | L17: 2026-07 | M17: 14m 22s | N17: 861.592 | O17: 14.36 | P17: C. 5-15 min | Q17: 4037.85 | R17: 4047.18 | S17: 4034.16 | T17: 4041.97 | U17: 4034.16 | V17: Unchanged | W17: 0 | X17: 3.69 | Y17: 1.117 | Z17: 2.515 | AA17: I. 2R..3R | AB17: 9.33 | AC17: -0.05 | AD17: 9.28 | AE17: Win | AF17: Take Profit | AG17: 933 | AH17: 9.33 | AI17: -1.57 | AJ17: 2.528 | AK17: -0.425 | AL17: 4047.18 | AM17: 4036.28 | AN17: 14m 21s | AO17: 6m 41s | AP17: 42.5 | AQ17: 0.995 | AR17: 0.05 | AS17: 0.856 | AT17: 1 | AU17: 0.856 | AV17: No | AW17: No | AX17: 0.386 | AY17: 965.85 | AZ17: 34.15 | BA17: 3.415 | BB17: 1 | BC17: ticks | BD17: 1971 | BE17: 9 | BF17: 3214929/XAUUSD/2026-07-29_56010917_XAUUSD_buy_win
A18: 17 | B18: 55998022 | C18: XAUUSD | D18: buy | E18: 0.01 | F18: 46232.707 | G18: 46232.75 | H18: Wednesday | I18: 16 | J18: NY Overlap | K18: 2026-W31 | L18: 2026-07 | M18: 1h 01m | N18: 3712.959 | O18: 61.883 | P18: F. 1-4 h | Q18: 4029.41 | R18: 4075.28 | S18: 4024.64 | T18: 4034.69 | U18: 4024.64 | V18: Unchanged | W18: 0 | X18: 4.77 | Y18: 1.107 | Z18: 9.606 | AA18: J. >= 3R | AB18: 45.87 | AC18: -0.05 | AD18: 45.82 | AE18: Win | AF18: Take Profit | AG18: 4587 | AH18: 45.87 | AI18: -2.71 | AJ18: 9.616 | AK18: -0.568 | AL18: 4075.28 | AM18: 4026.7 | AN18: 1h 01m | AO18: 47s | AP18: 56.8 | AQ18: 0.999 | AR18: 0.05 | AS18: 0.9442 | AT18: 1 | AU18: 0.9442 | AV18: No | AW18: No | AX18: 0.494 | AY18: 1011.67 | AZ18: 0 | BA18: 0 | BB18: 2 | BC18: ticks | BD18: 8441 | BE18: 9 | BF18: 3214929/XAUUSD/2026-07-29_55998022_XAUUSD_buy_win
A19: 18 | B19: 56034556 | C19: DAXEUR | D19: buy | E19: 0.04 | F19: 46232.764 | G19: 46232.764 | H19: Wednesday | I19: 18 | J19: NY Late | K19: 2026-W31 | L19: 2026-07 | M19: 28s | N19: 28.185 | O19: 0.47 | P19: A. < 1 min | Q19: 25503.62 | R19: 25492.18 | S19: 25492.27 | T19: 25515.06 | U19: 25492.27 | V19: Unchanged | W19: 0 | X19: 5.24 | Y19: 1.008 | Z19: -0.998 | AA19: C. -1R..-0.5R | AB19: -5.23 | AC19: 0 | AD19: -5.23 | AE19: Loss | AF19: Stop Loss | AG19: -1144 | AH19: 0.25 | AI19: -5.51 | AJ19: 0.048 | AK19: -1.052 | AL19: 25504.18 | AM19: 25491.68 | AN19: 7.7s | AO19: 28s | AP19: 105.2 | AQ19: -20.92 | AR19: 5.48 | AS19: 0.0448 | AT19: 0.04 | AU19: -0.9152 | AV19: Yes | AW19: No | AX19: 0.518 | AY19: 1006.44 | AZ19: 5.23 | BA19: 0.517 | BB19: -1 | BC19: ticks | BD19: 55 | BE19: 9 | BF19: 3214929/DAXEUR/2026-07-29_56034556_DAXEUR_buy_loss
A20: 19 | B20: 56035232 | C20: DAXEUR | D20: buy | E20: 0.02 | F20: 46232.765 | G20: 46232.772 | H20: Wednesday | I20: 18 | J20: NY Late | K20: 2026-W31 | L20: 2026-07 | M20: 10m 28s | N20: 628.128 | O20: 10.469 | P20: C. 5-15 min | Q20: 25494.62 | R20: 25480.68 | S20: 25478.92 | T20: 25509.79 | U20: 25481.25 | V20: Tightened | W20: 233 | X20: 3.62 | Y20: 0.967 | Z20: -0.878 | AA20: C. -1R..-0.5R | AB20: -3.18 | AC20: 0 | AD20: -3.18 | AE20: Loss | AF20: Stop Loss | AG20: -1394 | AH20: 6.24 | AI20: -3.22 | AJ20: 1.724 | AK20: -0.89 | AL20: 25521.68 | AM20: 25480.68 | AN20: 9m 27s | AO20: 10m 28s | AP20: 89 | AQ20: -0.51 | AR20: 9.42 | AS20: 0.66 | AT20: 0 | AU20: -0.34 | AV20: Yes | AW20: No | AX20: 0.36 | AY20: 1003.26 | AZ20: 8.41 | BA20: 0.831 | BB20: -2 | BC20: ticks | BD20: 1158 | BE20: 9 | BF20: 3214929/DAXEUR/2026-07-29_56035232_DAXEUR_buy_loss
A21: 20 | B21: 56032851 | C21: DAXEUR | D21: buy | E21: 0.02 | F21: 46232.761 | G21: 46232.772 | H21: Wednesday | I21: 18 | J21: NY Late | K21: 2026-W31 | L21: 2026-07 | M21: 16m 10s | N21: 969.954 | O21: 16.166 | P21: D. 15-30 min | Q21: 25532.62 | R21: 25480.68 | S21: 25515.37 | T21: 25549.49 | U21: 25481.25 | V21: Widened | W21: -3412 | X21: 3.98 | Y21: 0.977 | Z21: -2.98 | AA21: A. <= -1.5R | AB21: -11.86 | AC21: 0 | AD21: -11.86 | AE21: Loss | AF21: Stop Loss | AG21: -5194 | AH21: 0.24 | AI21: -11.99 | AJ21: 0.06 | AK21: -3.013 | AL21: 25533.68 | AM21: 25480.68 | AN21: 20s | AO21: 16m 10s | AP21: 301.3 | AQ21: -49.417 | AR21: 12.1 | AS21: 0.02 | AT21: 0 | AU21: -0.98 | AV21: Yes | AW21: No | AX21: 0.397 | AY21: 991.4 | AZ21: 20.27 | BA21: 2.004 | BB21: -3 | BC21: ticks | BD21: 1724 | BE21: 9 | BF21: 3214929/DAXEUR/2026-07-29_56032851_DAXEUR_buy_loss
A22: 21 | B22: 56040932 | C22: DAXEUR | D22: buy | E22: 0.03 | F22: 46232.774 | G22: 46232.775 | H22: Wednesday | I22: 18 | J22: NY Late | K22: 2026-W31 | L22: 2026-07 | M22: 1m 20s | N22: 79.597 | O22: 1.327 | P22: B. 1-5 min | Q22: 25500.62 | R22: 25481.18 | S22: 25486.55 | T22: 25514 | U22: 25481.88 | V22: Widened | W22: -467 | X22: 4.87 | Y22: 0.951 | Z22: -1.366 | AA22: B. -1.5R..-1R | AB22: -6.65 | AC22: 0 | AD22: -6.65 | AE22: Loss | AF22: Stop Loss | AG22: -1944 | AH22: 0 | AI22: -7.59 | AJ22: 0 | AK22: -1.559 | AL22: 25499.18 | AM22: 25478.68 | AN22: 0.0s | AO22: 1m 20s | AP22: 155.9 | AS22: -0.0702 | AT22: 0.122 | AU22: -0.9483 | AV22: Yes | AW22: No | AX22: 0.491 | AY22: 984.75 | AZ22: 26.92 | BA22: 2.661 | BB22: -4 | BC22: ticks | BD22: 168 | BE22: 9 | BF22: 3214929/DAXEUR/2026-07-29_56040932_DAXEUR_buy_loss
A23: 22 | B23: 56042302 | C23: XAUUSD | D23: sell | E23: 0.01 | F23: 46232.777 | G23: 46232.778 | H23: Wednesday | I23: 18 | J23: NY Late | K23: 2026-W31 | L23: 2026-07 | M23: 1m 37s | N23: 97.061 | O23: 1.618 | P23: B. 1-5 min | Q23: 4062.73 | R23: 4069.81 | S23: 4068.83 | T23: 4055.84 | U23: 4069.48 | V23: Widened | W23: -65 | X23: 6.1 | Y23: 1.13 | Z23: -1.169 | AA23: B. -1.5R..-1R | AB23: -7.08 | AC23: -0.05 | AD23: -7.13 | AE23: Loss | AF23: Stop Loss | AG23: -708 | AH23: 0.14 | AI23: -7.08 | AJ23: 0.023 | AK23: -1.161 | AL23: 4062.59 | AM23: 4069.81 | AN23: 1.3s | AO23: 1m 37s | AP23: 116.1 | AQ23: -50.929 | AR23: 7.27 | AS23: 0.0194 | AT23: 0 | AU23: -0.9806 | AV23: Yes | AW23: No | AX23: 0.619 | AY23: 977.62 | AZ23: 34.05 | BA23: 3.366 | BB23: -5 | BC23: ticks | BD23: 273 | BE23: 9 | BF23: 3214929/XAUUSD/2026-07-29_56042302_XAUUSD_sell_loss
A24: 23 | B24: 56043357 | C24: DAXEUR | D24: buy | E24: 0.02 | F24: 46232.778 | G24: 46232.783 | H24: Wednesday | I24: 18 | J24: NY Late | K24: 2026-W31 | L24: 2026-07 | M24: 7m 50s | N24: 469.505 | O24: 7.825 | P24: C. 5-15 min | Q24: 25537.62 | R24: 25579.18 | S24: 25522.96 | T24: 25553.75 | U24: 25522.96 | V24: Unchanged | W24: 0 | X24: 3.38 | Y24: 1.104 | Z24: 2.814 | AA24: I. 2R..3R | AB24: 9.51 | AC24: 0 | AD24: 9.51 | AE24: Win | AF24: Expert | AG24: 4156 | AH24: 11.43 | AI24: -1.37 | AJ24: 3.382 | AK24: -0.405 | AL24: 25587.18 | AM24: 25531.68 | AN24: 7m 33s | AO24: 2m 11s | AP24: 40.5 | AQ24: 0.832 | AR24: 1.92 | AS24: 0.893 | AT24: 0.8559 | AU24: 0.7488 | AV24: No | AW24: No | AX24: 0.346 | AY24: 987.13 | AZ24: 24.54 | BA24: 2.426 | BB24: 1 | BC24: ticks | BD24: 961 | BE24: 9 | BF24: 3214929/DAXEUR/2026-07-29_56043357_DAXEUR_buy_win
A25: 24 | B25: 56045244 | C25: DAXEUR | D25: buy | E25: 0.02 | F25: 46232.78 | G25: 46232.784 | H25: Wednesday | I25: 18 | J25: NY Late | K25: 2026-W31 | L25: 2026-07 | M25: 4m 56s | N25: 295.877 | O25: 4.931 | P25: B. 1-5 min | Q25: 25557.12 | R25: 25556.68 | S25: 25537.87 | T25: 25577.24 | U25: 25557.12 | V25: Breakeven | W25: 1925 | X25: 4.44 | Y25: 1.045 | Z25: -0.023 | AA25: D. -0.5R..0 | AB25: -0.1 | AC25: 0 | AD25: -0.1 | AE25: Loss | AF25: Stop Loss | AG25: -44 | AH25: 6.93 | AI25: -0.68 | AJ25: 1.561 | AK25: -0.153 | AL25: 25587.18 | AM25: 25554.18 | AN25: 3m 55s | AO25: 0.0s | AP25: 15.3 | AQ25: -0.014 | AR25: 7.03 | AS25: 0.9109 | AT25: 0.0758 | AU25: -0.0133 | AV25: No | AW25: No | AX25: 0.45 | AY25: 987.03 | AZ25: 24.64 | BA25: 2.436 | BB25: -1 | BC25: ticks | BD25: 609 | BE25: 9 | BF25: 3214929/DAXEUR/2026-07-29_56045244_DAXEUR_buy_loss
A26: 25 | B26: 56050134 | C26: NDXUSD | D26: sell | E26: 0.01 | F26: 46232.787 | G26: 46232.794 | H26: Wednesday | I26: 18 | J26: NY Late | K26: 2026-W31 | L26: 2026-07 | M26: 10m 18s | N26: 618.145 | O26: 10.302 | P26: C. 5-15 min | Q26: 27912.5 | R26: 27894.75 | S26: 27967.01 | T26: 27848.3 | U26: 27967.01 | V26: Unchanged | W26: 0 | X26: 5.45 | Y26: 1.178 | Z26: 0.327 | AA26: F. 0..0.5R | AB26: 1.78 | AC26: 0 | AD26: 1.78 | AE26: Win | AF26: Expert | AG26: 1775 | AH26: 3.76 | AI26: -3.78 | AJ26: 0.69 | AK26: -0.694 | AL26: 27874.95 | AM26: 27950.25 | AN26: 4m 05s | AO26: 9m 04s | AP26: 69.4 | AQ26: 0.473 | AR26: 1.98 | AS26: 0.4987 | AT26: 0.7371 | AU26: 0.2357 | AV26: Yes | AW26: No | AX26: 0.552 | AY26: 988.81 | AZ26: 22.86 | BA26: 2.26 | BB26: 1 | BC26: ticks | BD26: 1698 | BE26: 9 | BF26: 3214929/NDXUSD/2026-07-29_56050134_NDXUSD_sell_win
A27: 26 | B27: 56052315 | C27: DAXEUR | D27: sell | E27: 0.02 | F27: 46232.791 | G27: 46232.797 | H27: Wednesday | I27: 18 | J27: NY Late | K27: 2026-W31 | L27: 2026-07 | M27: 8m 44s | N27: 523.516 | O27: 8.725 | P27: C. 5-15 min | Q27: 25559.18 | R27: 25527.62 | S27: 25574.55 | T27: 25542.27 | U27: 25574.55 | V27: Unchanged | W27: 0 | X27: 3.54 | Y27: 1.102 | Z27: 2.04 | AA27: I. 2R..3R | AB27: 7.22 | AC27: 0 | AD27: 7.22 | AE27: Win | AF27: Take Profit | AG27: 3156 | AH27: 7.39 | AI27: -2.99 | AJ27: 2.088 | AK27: -0.845 | AL27: 25527.12 | AM27: 25572.12 | AN27: 8m 44s | AO27: 3m 49s | AP27: 84.5 | AQ27: 0.977 | AR27: 0.17 | AS27: 0.7124 | AT27: 0.9889 | AU27: 0.7013 | AV27: No | AW27: No | AX27: 0.358 | AY27: 996.03 | AZ27: 15.64 | BA27: 1.546 | BB27: 2 | BC27: ticks | BD27: 1006 | BE27: 9 | BF27: 3214929/DAXEUR/2026-07-29_56052315_DAXEUR_sell_win
A28: 27 | B28: 56054122 | C28: NDXUSD | D28: sell | E28: 0.01 | F28: 46232.793 | G28: 46232.806 | H28: Wednesday | I28: 19 | J28: NY Late | K28: 2026-W31 | L28: 2026-07 | M28: 18m 27s | N28: 1106.688 | O28: 18.445 | P28: D. 15-30 min | Q28: 27936.2 | R28: 27633.95 | S28: 27978.35 | T28: 27892.78 | U28: 27978.35 | V28: Unchanged | W28: 0 | X28: 4.22 | Y28: 1.028 | Z28: 7.164 | AA28: J. >= 3R | AB28: 30.23 | AC28: 0 | AD28: 30.23 | AE28: Win | AF28: Take Profit | AG28: 30225 | AH28: 30.6 | AI28: -0.39 | AJ28: 7.251 | AK28: -0.092 | AL28: 27630.25 | AM28: 27940.05 | AN28: 18m 27s | AO28: 1.1s | AP28: 9.2 | AQ28: 0.988 | AR28: 0.37 | AS28: 0.9876 | AT28: 0.9881 | AU28: 0.9756 | AV28: No | AW28: No | AX28: 0.424 | AY28: 1026.26 | AZ28: 0 | BA28: 0 | BB28: 3 | BC28: ticks | BD28: 3066 | BE28: 9 | BF28: 3214929/NDXUSD/2026-07-29_56054122_NDXUSD_sell_win
A29: 28 | B29: 56063306 | C29: NDXUSD | D29: buy | E29: 0.01 | F29: 46232.813 | G29: 46232.815 | H29: Wednesday | I29: 19 | J29: NY Late | K29: 2026-W31 | L29: 2026-07 | M29: 3m 03s | N29: 182.644 | O29: 3.044 | P29: B. 1-5 min | Q29: 27559.55 | R29: 27514.1 | S29: 27514.74 | T29: 27606.74 | U29: 27514.74 | V29: Unchanged | W29: 0 | X29: 4.48 | Y29: 1.054 | Z29: -1.016 | AA29: B. -1.5R..-1R | AB29: -4.55 | AC29: 0 | AD29: -4.55 | AE29: Loss | AF29: Stop Loss | AG29: -4545 | AH29: 3.42 | AI29: -4.75 | AJ29: 0.763 | AK29: -1.06 | AL29: 27593.7 | AM29: 27512.1 | AN29: 59s | AO29: 3m 03s | AP29: 106 | AQ29: -1.33 | AR29: 7.97 | AS29: 0.4185 | AT29: 0.0245 | AU29: -0.557 | AV29: Yes | AW29: No | AX29: 0.437 | AY29: 1021.71 | AZ29: 4.55 | BA29: 0.443 | BB29: -1 | BC29: ticks | BD29: 516 | BE29: 9 | BF29: 3214929/NDXUSD/2026-07-29_56063306_NDXUSD_buy_loss
A30: 29 | B30: 56066262 | C30: NDXUSD | D30: sell | E30: 0.01 | F30: 46232.818 | G30: 46232.82 | H30: Wednesday | I30: 19 | J30: NY Late | K30: 2026-W31 | L30: 2026-07 | M30: 2m 04s | N30: 124.389 | O30: 2.073 | P30: B. 1-5 min | Q30: 27419.4 | R30: 27326.95 | S30: 27494.68 | T30: 27334.49 | U30: 27494.68 | V30: Unchanged | W30: 0 | X30: 7.53 | Y30: 1.127 | Z30: 1.228 | AA30: H. 1R..2R | AB30: 9.25 | AC30: 0 | AD30: 9.25 | AE30: Win | AF30: Take Profit | AG30: 9245 | AH30: 9.25 | AI30: -0.87 | AJ30: 1.228 | AK30: -0.116 | AL30: 27326.95 | AM30: 27428.05 | AN30: 2m 04s | AO30: 0.0s | AP30: 11.6 | AQ30: 1 | AR30: 0 | AS30: 0.9144 | AT30: 1 | AU30: 0.9144 | AV30: No | AW30: No | AX30: 0.737 | AY30: 1030.96 | AZ30: 0 | BA30: 0 | BB30: 1 | BC30: ticks | BD30: 353 | BE30: 9 | BF30: 3214929/NDXUSD/2026-07-29_56066262_NDXUSD_sell_win
A31: 30 | B31: 56068541 | C31: NDXUSD | D31: buy | E31: 0.02 | F31: 46232.825 | G31: 46232.83 | H31: Wednesday | I31: 19 | J31: NY Late | K31: 2026-W31 | L31: 2026-07 | M31: 7m 14s | N31: 433.702 | O31: 7.228 | P31: C. 5-15 min | Q31: 27275.25 | R31: 27226.5 | S31: 27226.92 | T31: 27330.18 | U31: 27226.92 | V31: Unchanged | W31: 0 | X31: 9.67 | Y31: 1.137 | Z31: -1.008 | AA31: B. -1.5R..-1R | AB31: -9.75 | AC31: 0 | AD31: -9.75 | AE31: Loss | AF31: Stop Loss | AG31: -4875 | AH31: 16.83 | AI31: -10.11 | AJ31: 1.74 | AK31: -1.046 | AL31: 27359.4 | AM31: 27224.7 | AN31: 2m 01s | AO31: 7m 14s | AP31: 104.6 | AQ31: -0.579 | AR31: 26.58 | AS31: 0.6247 | AT31: 0.0134 | AU31: -0.3619 | AV31: Yes | AW31: No | AX31: 0.938 | AY31: 1021.21 | AZ31: 9.75 | BA31: 0.946 | BB31: -1 | BC31: ticks | BD31: 1212 | BE31: 9 | BF31: 3214929/NDXUSD/2026-07-29_56068541_NDXUSD_buy_loss
A32: 31 | B32: 56072252 | C32: DJIUSD | D32: buy | E32: 0.01 | F32: 46232.834 | G32: 46232.838 | H32: Wednesday | I32: 20 | J32: NY Late | K32: 2026-W31 | L32: 2026-07 | M32: 6m 07s | N32: 367.101 | O32: 6.118 | P32: C. 5-15 min | Q32: 51576.24 | R32: 51573.45 | S32: 51491 | T32: 51668.95 | U32: 51576.24 | V32: Breakeven | W32: 8524 | X32: 8.52 | Y32: 1.088 | Z32: -0.033 | AA32: D. -0.5R..0 | AB32: -0.28 | AC32: 0 | AD32: -0.28 | AE32: Loss | AF32: Stop Loss | AG32: -279 | AH32: 6.72 | AI32: -2.98 | AJ32: 0.789 | AK32: -0.35 | AL32: 51643.45 | AM32: 51546.45 | AN32: 34s | AO32: 5m 34s | AP32: 35 | AQ32: -0.042 | AR32: 7 | AS32: 0.6929 | AT32: 0.2784 | AU32: -0.0288 | AV32: Yes | AW32: No | AX32: 0.834 | AY32: 1020.93 | AZ32: 10.03 | BA32: 0.973 | BB32: -2 | BC32: ticks | BD32: 799 | BE32: 9 | BF32: 3214929/DJIUSD/2026-07-29_56072252_DJIUSD_buy_loss
A33: 32 | B33: 56074196 | C33: NDXUSD | D33: sell | E33: 0.01 | F33: 46232.84 | G33: 46232.842 | H33: Wednesday | I33: 20 | J33: NY Late | K33: 2026-W31 | L33: 2026-07 | M33: 3m 02s | N33: 181.857 | O33: 3.031 | P33: B. 1-5 min | Q33: 27105.95 | R33: 27166.6 | S33: 27164.24 | T33: 27025.87 | U33: 27164.24 | V33: Unchanged | W33: 0 | X33: 5.83 | Y33: 1.374 | Z33: -1.041 | AA33: B. -1.5R..-1R | AB33: -6.07 | AC33: 0 | AD33: -6.07 | AE33: Loss | AF33: Stop Loss | AG33: -6065 | AH33: 2.09 | AI33: -6.07 | AJ33: 0.358 | AK33: -1.041 | AL33: 27085.1 | AM33: 27166.6 | AN33: 1m 11s | AO33: 3m 02s | AP33: 104.1 | AQ33: -2.904 | AR33: 8.16 | AS33: 0.2558 | AT33: 0 | AU33: -0.7442 | AV33: Yes | AW33: No | AX33: 0.571 | AY33: 1014.86 | AZ33: 16.1 | BA33: 1.562 | BB33: -3 | BC33: ticks | BD33: 496 | BE33: 9 | BF33: 3214929/NDXUSD/2026-07-29_56074196_NDXUSD_sell_loss
A34: 33 | B34: 56075382 | C34: DJIUSD | D34: buy | E34: 0.01 | F34: 46232.845 | G34: 46232.848 | H34: Wednesday | I34: 20 | J34: NY Late | K34: 2026-W31 | L34: 2026-07 | M34: 4m 19s | N34: 259.037 | O34: 4.317 | P34: B. 1-5 min | Q34: 51552.99 | R34: 51539.2 | S34: 51501.53 | T34: 51609.6 | U34: 51501.53 | V34: Unchanged | W34: 0 | X34: 5.15 | Y34: 1.099 | Z34: -0.268 | AA34: D. -0.5R..0 | AB34: -1.38 | AC34: 0 | AD34: -1.38 | AE34: Loss | AF34: Expert | AG34: -1379 | AH34: 0.37 | AI34: -3.18 | AJ34: 0.072 | AK34: -0.617 | AL34: 51556.7 | AM34: 51521.2 | AN34: 31s | AO34: 2m 04s | AP34: 61.7 | AQ34: -3.73 | AR34: 1.75 | AS34: 0.1045 | AT34: 0.507 | AU34: -0.3885 | AV34: Yes | AW34: No | AX34: 0.507 | AY34: 1013.48 | AZ34: 17.48 | BA34: 1.696 | BB34: -4 | BC34: ticks | BD34: 465 | BE34: 9 | BF34: 3214929/DJIUSD/2026-07-29_56075382_DJIUSD_buy_loss
... A40: 39 | B40: 56086025 | C40: NIKJPY | D40: buy | E40: 0.02 | F40: 46232.99 | G40: 46232.993 | H40: Wednesday | I40: 23 | J40: NY Late | K40: 2026-W31 | L40: 2026-07 | M40: 4m 11s | N40: 251.189 | O40: 4.186 | P40: B. 1-5 min | Q40: 61992 | R40: 61647 | S40: 61692 | T40: 62326 | U40: 61647 | V40: Widened | W40: -45 | X40: 3.77 | Y40: 1.111 | Z40: -1.119 | AA40: B. -1.5R..-1R | AB40: -4.22 | AC40: 0 | AD40: -4.22 | AE40: Loss | AF40: Stop Loss | AG40: -345 | AH40: 1.28 | AI40: -4.37 | AJ40: 0.34 | AK40: -1.159 | AL40: 62094 | AM40: 61644 | AN40: 7.9s | AO40: 4m 11s | AP40: 115.9 | AQ40: -3.297 | AR40: 5.5 | AS40: 0.2267 | AT40: 0.0067 | AU40: -0.7667 | AV40: Yes | AW40: No | AX40: 0.376 | AY40: 998.43 | AZ40: 32.53 | BA40: 3.155 | BB40: -2 | BC40: ticks | BD40: 576 | BE40: 9 | BF40: 3214929/NIKJPY/2026-07-29_56086025_NIKJPY_buy_loss
A41: 40 | B41: 56314087 | C41: XAUUSD | D41: sell | E41: 0.01 | F41: 46233.571 | G41: 46233.583 | H41: Thursday | I41: 13 | J41: NY Overlap | K41: 2026-W31 | L41: 2026-07 | M41: 16m 46s | N41: 1005.829 | O41: 16.764 | P41: D. 15-30 min | Q41: 4094.12 | R41: 4110.5 | S41: 4099.14 | U41: 4110.37 | V41: Widened | W41: -1123 | X41: 5.02 | Z41: -3.273 | AA41: A. <= -1.5R | AB41: -16.38 | AC41: -0.05 | AD41: -16.43 | AE41: Loss | AF41: Stop Loss | AG41: -1638 | AH41: 8.2 | AI41: -16.43 | AJ41: 1.633 | AK41: -3.273 | AL41: 4085.92 | AM41: 4110.55 | AN41: 3m 56s | AO41: 16m 46s | AP41: 327.3 | AQ41: -2.004 | AR41: 24.63 | AS41: 0.3329 | AT41: 0.002 | AU41: -0.665 | AV41: Yes | AW41: No | AX41: 0.503 | AY41: 982 | AZ41: 48.96 | BA41: 4.749 | BB41: -3 | BC41: ticks | BD41: 2737 | BE41: 9 | BF41: 3214929/XAUUSD/2026-07-30_56314087_XAUUSD_sell_loss
A42: 41 | B42: 56390633 | C42: XAUUSD | D42: buy | E42: 0.02 | F42: 46233.64 | G42: 46233.656 | H42: Thursday | I42: 15 | J42: NY Overlap | K42: 2026-W31 | L42: 2026-07 | M42: 22m 03s | N42: 1322.548 | O42: 22.042 | P42: D. 15-30 min | Q42: 4096 | R42: 4105.47 | S42: 4092.31 | T42: 4102.71 | U42: 4092.31 | V42: Unchanged | W42: 0 | X42: 7.38 | Y42: 1.818 | Z42: 2.554 | AA42: I. 2R..3R | AB42: 18.94 | AC42: -0.09 | AD42: 18.85 | AE42: Win | AF42: Take Profit | AG42: 947 | AH42: 19.32 | AI42: -8.14 | AJ42: 2.618 | AK42: -1.103 | AL42: 4105.66 | AM42: 4091.93 | AN42: 22m 03s | AO42: 4m 09s | AP42: 110.3 | AQ42: 0.976 | AR42: 0.47 | AS42: 0.7036 | AT42: 0.9862 | AU42: 0.6897 | AV42: No | AW42: No | AX42: 0.752 | AY42: 1000.85 | AZ42: 30.11 | BA42: 2.921 | BB42: 1 | BC42: ticks | BD42: 3132 | BE42: 9 | BF42: 3214929/XAUUSD/2026-07-30_56390633_XAUUSD_buy_win
A43: 42 | B43: 56429370 | C43: DAXEUR | D43: sell | E43: 0.04 | F43: 46233.732 | G43: 46233.738 | H43: Thursday | I43: 17 | J43: NY Late | K43: 2026-W31 | L43: 2026-07 | M43: 9m 31s | N43: 571.471 | O43: 9.525 | P43: C. 5-15 min | Q43: 25660.78 | R43: 25680.03 | S43: 25670.37 | T43: 25650.23 | U43: 25680.02 | V43: Widened | W43: -965 | X43: 4.43 | Y43: 1.099 | Z43: -2.002 | AA43: A. <= -1.5R | AB43: -8.87 | AC43: 0 | AD43: -8.87 | AE43: Loss | AF43: Stop Loss | AG43: -1925 | AH43: 1.96 | AI43: -8.88 | AJ43: 0.442 | AK43: -2.005 | AL43: 25656.53 | AM43: 25680.03 | AN43: 4m 22s | AO43: 9m 31s | AP43: 200.5 | AQ43: -4.526 | AR43: 10.83 | AS43: 0.1809 | AT43: 0 | AU43: -0.8191 | AV43: Yes | AW43: No | AX43: 0.443 | AY43: 991.98 | AZ43: 38.98 | BA43: 3.781 | BB43: -1 | BC43: ticks | BD43: 632 | BE43: 9 | BF43: 3214929/DAXEUR/2026-07-30_56429370_DAXEUR_sell_loss
A44: 43 | B44: 56441184 | C44: DAXEUR | D44: sell | E44: 0.04 | F44: 46233.786 | G44: 46233.791 | H44: Thursday | I44: 18 | J44: NY Late | K44: 2026-W31 | L44: 2026-07 | M44: 7m 27s | N44: 447.456 | O44: 7.458 | P44: C. 5-15 min | Q44: 25678.28 | R44: 25689.03 | S44: 25688.39 | T44: 25667.16 | U44: 25689.03 | V44: Widened | W44: -64 | X44: 4.66 | Y44: 1.101 | Z44: -1.064 | AA44: B. -1.5R..-1R | AB44: -4.96 | AC44: 0 | AD44: -4.96 | AE44: Loss | AF44: Stop Loss | AG44: -1075 | AH44: 0 | AI44: -4.96 | AJ44: 0 | AK44: -1.064 | AL44: 25678.53 | AM44: 25689.03 | AN44: 10s | AO44: 7m 27s | AP44: 106.4 | AS44: -0.0238 | AT44: 0 | AU44: -1.0238 | AV44: Yes | AW44: No | AX44: 0.47 | AY44: 987.02 | AZ44: 43.94 | BA44: 4.262 | BB44: -2 | BC44: ticks | BD44: 189 | BE44: 9 | BF44: 3214929/DAXEUR/2026-07-30_56441184_DAXEUR_sell_loss
A45: 44 | B45: 56431283 | C45: DAXEUR | D45: sell | E45: 0.04 | F45: 46233.737 | G45: 46233.791 | H45: Thursday | I45: 17 | J45: NY Late | K45: 2026-W31 | L45: 2026-07 | M45: 1h 17m | N45: 4663.883 | O45: 77.731 | P45: F. 1-4 h | Q45: 25669.78 | R45: 25689.03 | S45: 25681.11 | T45: 25659.42 | U45: 25688.92 | V45: Widened | W45: -781 | X45: 5.23 | Y45: 0.914 | Z45: -1.698 | AA45: A. <= -1.5R | AB45: -8.88 | AC45: 0 | AD45: -8.88 | AE45: Loss | AF45: Stop Loss | AG45: -1925 | AH45: 4.04 | AI45: -8.88 | AJ45: 0.772 | AK45: -1.698 | AL45: 25661.03 | AM45: 25689.03 | AN45: 23m 31s | AO45: 1h 17m | AP45: 169.8 | AQ45: -2.198 | AR45: 12.92 | AS45: 0.3125 | AT45: 0 | AU45: -0.6875 | AV45: Yes | AW45: No | AX45: 0.53 | AY45: 978.14 | AZ45: 52.82 | BA45: 5.123 | BB45: -3 | BC45: ticks | BD45: 3091 | BE45: 9 | BF45: 3214929/DAXEUR/2026-07-30_56431283_DAXEUR_sell_loss
A46: 45 | B46: 56441872 | C46: DAXEUR | D46: sell | E46: 0.05 | F46: 46233.789 | G46: 46233.793 | H46: Thursday | I46: 18 | J46: NY Late | K46: 2026-W31 | L46: 2026-07 | M46: 6m 04s | N46: 364.204 | O46: 6.07 | P46: C. 5-15 min | Q46: 25684.28 | R46: 25700.53 | S46: 25693.36 | T46: 25675.34 | U46: 25700.37 | V46: Widened | W46: -701 | X46: 5.24 | Y46: 0.985 | Z46: -1.79 | AA46: A. <= -1.5R | AB46: -9.38 | AC46: 0 | AD46: -9.38 | AE46: Loss | AF46: Stop Loss | AG46: -1625 | AH46: 0.44 | AI46: -9.38 | AJ46: 0.084 | AK46: -1.79 | AL46: 25683.53 | AM46: 25700.53 | AN46: 22s | AO46: 6m 04s | AP46: 179 | AQ46: -21.318 | AR46: 9.82 | AS46: 0.0441 | AT46: 0 | AU46: -0.9559 | AV46: Yes | AW46: No | AX46: 0.536 | AY46: 968.76 | AZ46: 62.2 | BA46: 6.033 | BB46: -4 | BC46: ticks | BD46: 189 | BE46: 9 | BF46: 3214929/DAXEUR/2026-07-30_56441872_DAXEUR_sell_loss
A47: 46 | B47: 56432997 | C47: XAUUSD | D47: sell | E47: 0.03 | F47: 46233.757 | G47: 46233.804 | H47: Thursday | I47: 18 | J47: NY Late | K47: 2026-W31 | L47: 2026-07 | M47: 1h 07m | N47: 4058.529 | O47: 67.642 | P47: F. 1-4 h | Q47: 4106.16 | R47: 4109.92 | S47: 4109.36 | T47: 4089.34 | U47: 4109.91 | V47: Widened | W47: -55 | X47: 9.6 | Y47: 5.256 | Z47: -1.19 | AA47: B. -1.5R..-1R | AB47: -11.28 | AC47: -0.14 | AD47: -11.42 | AE47: Loss | AF47: Stop Loss | AG47: -376 | AH47: 21.24 | AI47: -11.7 | AJ47: 2.212 | AK47: -1.219 | AL47: 4099.08 | AM47: 4110.06 | AN47: 51m 01s | AO47: 1h 07m | AP47: 121.9 | AQ47: -0.538 | AR47: 32.66 | AS47: 0.6448 | AT47: 0.0128 | AU47: -0.3424 | AV47: Yes | AW47: No | AX47: 0.991 | AY47: 957.34 | AZ47: 73.62 | BA47: 7.141 | BB47: -5 | BC47: ticks | BD47: 6584 | BE47: 9 | BF47: 3214929/XAUUSD/2026-07-30_56432997_XAUUSD_sell_loss
A48: 47 | B48: 56578223 | C48: NDXUSD | D48: sell | E48: 0.06 | F48: 46234.453 | G48: 46234.459 | H48: Friday | I48: 10 | J48: London | K48: 2026-W31 | L48: 2026-07 | M48: 9m 12s | N48: 551.638 | O48: 9.194 | P48: C. 5-15 min | Q48: 28445.4 | R48: 28463.55 | S48: 28459.32 | T48: 28378.31 | U48: 28461.01 | V48: Widened | W48: -169 | X48: 8.35 | Y48: 4.82 | Z48: -1.304 | AA48: B. -1.5R..-1R | AB48: -10.89 | AC48: 0 | AD48: -10.89 | AE48: Loss | AF48: Stop Loss | AG48: -1815 | AH48: 7.95 | AI48: -10.95 | AJ48: 0.952 | AK48: -1.311 | AL48: 28432.15 | AM48: 28463.65 | AN48: 7m 27s | AO48: 9m 12s | AP48: 131.1 | AQ48: -1.37 | AR48: 18.84 | AS48: 0.4206 | AT48: 0.0032 | AU48: -0.5762 | AV48: Yes | AW48: No | AX48: 0.872 | AY48: 946.45 | AZ48: 84.51 | BA48: 8.197 | BB48: -6 | BC48: ticks | BD48: 1244 | BE48: 9 | BF48: 3214929/NDXUSD/2026-07-31_56578223_NDXUSD_sell_loss
A49: 48 | B49: 56583758 | C49: XAUUSD | D49: sell | E49: 0.04 | F49: 46234.467 | G49: 46234.488 | H49: Friday | I49: 11 | J49: London | K49: 2026-W31 | L49: 2026-07 | M49: 30m 39s | N49: 1838.861 | O49: 30.648 | P49: E. 30-60 min | Q49: 4058.78 | R49: 4051.74 | S49: 4061.53 | U49: 4061.53 | V49: Unchanged | W49: 0 | X49: 11 | Z49: 2.544 | AA49: I. 2R..3R | AB49: 28.16 | AC49: -0.18 | AD49: 27.98 | AE49: Win | AF49: Take Profit | AG49: 704 | AH49: 28.16 | AI49: -10.08 | AJ49: 2.56 | AK49: -0.916 | AL49: 4051.74 | AM49: 4061.3 | AN49: 30m 39s | AO49: 13m 10s | AP49: 91.6 | AQ49: 0.994 | AR49: 0.18 | AS49: 0.7364 | AT49: 1 | AU49: 0.7364 | AV49: No | AW49: No | AX49: 1.162 | AY49: 974.43 | AZ49: 56.53 | BA49: 5.483 | BB49: 1 | BC49: ticks | BD49: 2812 | BE49: 9 | BF49: 3214929/XAUUSD/2026-07-31_56583758_XAUUSD_sell_win
A50: 49 | B50: 56651727 | C50: DJIUSD | D50: buy | E50: 0.03 | F50: 46234.566 | G50: 46234.569 | H50: Friday | I50: 13 | J50: NY Overlap | K50: 2026-W31 | L50: 2026-07 | M50: 4m 18s | N50: 257.526 | O50: 4.292 | P50: B. 1-5 min | Q50: 52397.84 | R50: 52361.05 | S50: 52366.96 | T50: 52497.5 | U50: 52361.46 | V50: Widened | W50: -550 | X50: 9.26 | Y50: 3.229 | Z50: -1.192 | AA50: B. -1.5R..-1R | AB50: -11.04 | AC50: 0 | AD50: -11.04 | AE50: Loss | AF50: Stop Loss | AG50: -3679 | AH50: 9.21 | AI50: -13.44 | AJ50: 0.995 | AK50: -1.451 | AL50: 52428.55 | AM50: 52353.05 | AN50: 2m 00s | AO50: 4m 18s | AP50: 145.1 | AQ50: -1.199 | AR50: 20.25 | AS50: 0.4068 | AT50: 0.106 | AU50: -0.4873 | AV50: Yes | AW50: No | AX50: 0.95 | AY50: 963.39 | AZ50: 67.57 | BA50: 6.554 | BB50: -1 | BC50: ticks | BD50: 651 | BE50: 9 | BF50: 3214929/DJIUSD/2026-07-31_56651727_DJIUSD_buy_loss
A51: 50 | B51: 56718085 | C51: DJIUSD | D51: sell | E51: 0.03 | F51: 46234.627 | G51: 46234.635 | H51: Friday | I51: 15 | J51: NY Overlap | K51: 2026-W31 | L51: 2026-07 | M51: 10m 39s | N51: 638.901 | O51: 10.648 | P51: C. 5-15 min | Q51: 52281.1 | R51: 52322.89 | S51: 52321.94 | T51: 52072.66 | U51: 52321.94 | V51: Unchanged | W51: 0 | X51: 12.25 | Y51: 5.104 | Z51: -1.024 | AA51: B. -1.5R..-1R | AB51: -12.54 | AC51: 0 | AD51: -12.54 | AE51: Loss | AF51: Stop Loss | AG51: -4179 | AH51: 13.86 | AI51: -12.84 | AJ51: 1.131 | AK51: -1.048 | AL51: 52234.89 | AM51: 52323.89 | AN51: 6m 21s | AO51: 10m 39s | AP51: 104.8 | AQ51: -0.905 | AR51: 26.4 | AS51: 0.5192 | AT51: 0.0112 | AU51: -0.4696 | AV51: Yes | AW51: No | AX51: 1.272 | AY51: 950.85 | AZ51: 80.11 | BA51: 7.77 | BB51: -2 | BC51: ticks | BD51: 1446 | BE51: 9 | BF51: 3214929/DJIUSD/2026-07-31_56718085_DJIUSD_sell_loss
A52: 51 | B52: 56724703 | C52: DJIUSD | D52: buy | E52: 0.02 | F52: 46234.644 | G52: 46234.725 | H52: Friday | I52: 15 | J52: NY Overlap | K52: 2026-W31 | L52: 2026-07 | M52: 1h 57m | N52: 7059.082 | O52: 117.651 | P52: F. 1-4 h | Q52: 52248.89 | R52: 52500.05 | S52: 52204.16 | U52: 52204.16 | V52: Unchanged | W52: 0 | X52: 8.95 | Z52: 5.612 | AA52: J. >= 3R | AB52: 50.23 | AC52: 0 | AD52: 50.23 | AE52: Win | AF52: Take Profit | AG52: 25116 | AH52: 50.23 | AI52: -7.16 | AJ52: 5.612 | AK52: -0.8 | AL52: 52500.05 | AM52: 52213.1 | AN52: 1h 57m | AO52: 7m 34s | AP52: 80 | AQ52: 1 | AR52: 0 | AS52: 0.8753 | AT52: 1 | AU52: 0.8753 | AV52: No | AW52: No | AX52: 0.941 | AY52: 1001.08 | AZ52: 29.88 | BA52: 2.898 | BB52: 1 | BC52: ticks | BD52: 13593 | BE52: 9 | BF52: 3214929/DJIUSD/2026-07-31_56724703_DJIUSD_buy_win
A53: 52 | B53: 56847975 | C53: DAXEUR | D53: buy | E53: 0.02 | F53: 46237.315 | G53: 46237.32 | H53: Monday | I53: 7 | J53: Asia | K53: 2026-W32 | L53: 2026-08 | M53: 6m 51s | N53: 410.77 | O53: 6.846 | P53: C. 5-15 min | Q53: 25968.82 | R53: 25949.48 | S53: 25950.05 | T53: 25990.52 | U53: 25950.05 | V53: Unchanged | W53: 0 | X53: 4.33 | Y53: 1.157 | Z53: -1.03 | AA53: B. -1.5R..-1R | AB53: -4.46 | AC53: 0 | AD53: -4.46 | AE53: Loss | AF53: Stop Loss | AG53: -1934 | AH53: 6.26 | AI53: -4.46 | AJ53: 1.446 | AK53: -1.03 | AL53: 25995.98 | AM53: 25949.48 | AN53: 1m 51s | AO53: 6m 50s | AP53: 103 | AQ53: -0.712 | AR53: 10.72 | AS53: 0.5841 | AT53: 0 | AU53: -0.4159 | AV53: Yes | AW53: No | AX53: 0.433 | AY53: 996.62 | AZ53: 34.34 | BA53: 3.331 | BB53: -1 | BC53: ticks | BD53: 579 | BE53: 9 | BF53: 3214929/DAXEUR/2026-08-03_56847975_DAXEUR_buy_loss
A54: 53 | B54: 56851593 | C54: DAXEUR | D54: buy | E54: 0.04 | F54: 46237.322 | G54: 46237.331 | H54: Monday | I54: 7 | J54: Asia | K54: 2026-W32 | L54: 2026-08 | M54: 12m 02s | N54: 721.7 | O54: 12.028 | P54: C. 5-15 min | Q54: 25949.73 | R54: 25980.88 | S54: 25939.53 | T54: 25962 | U54: 25939.53 | V54: Unchanged | W54: 0 | X54: 4.71 | Y54: 1.202 | Z54: 3.049 | AA54: J. >= 3R | AB54: 14.36 | AC54: 0 | AD54: 14.36 | AE54: Win | AF54: Take Profit | AG54: 3115 | AH54: 14.37 | AI54: -2.42 | AJ54: 3.051 | AK54: -0.514 | AL54: 25980.88 | AM54: 25944.48 | AN54: 12m 01s | AO54: 1m 11s | AP54: 51.4 | AQ54: 0.999 | AR54: 0.01 | AS54: 0.8558 | AT54: 1 | AU54: 0.8558 | AV54: No | AW54: No | AX54: 0.473 | AY54: 1010.98 | AZ54: 19.98 | BA54: 1.938 | BB54: 1 | BC54: ticks | BD54: 1061 | BE54: 9 | BF54: 3214929/DAXEUR/2026-08-03_56851593_DAXEUR_buy_win
A55: 54 | B55: 56856761 | C55: DAXEUR | D55: sell | E55: 0.02 | F55: 46237.336 | G55: 46237.344 | H55: Monday | I55: 8 | J55: London | K55: 2026-W32 | L55: 2026-08 | M55: 12m 09s | N55: 729.298 | O55: 12.155 | P55: C. 5-15 min | Q55: 25986.38 | R55: 26006.68 | S55: 26006.36 | T55: 25961.92 | U55: 26006.36 | V55: Unchanged | W55: 0 | X55: 4.61 | Y55: 1.223 | Z55: -1.015 | AA55: B. -1.5R..-1R | AB55: -4.68 | AC55: 0 | AD55: -4.68 | AE55: Loss | AF55: Stop Loss | AG55: -2030 | AH55: 5.01 | AI55: -4.68 | AJ55: 1.087 | AK55: -1.015 | AL55: 25964.68 | AM55: 26006.68 | AN55: 3m 22s | AO55: 12m 09s | AP55: 101.5 | AQ55: -0.934 | AR55: 9.69 | AS55: 0.5167 | AT55: 0 | AU55: -0.4833 | AV55: Yes | AW55: No | AX55: 0.456 | AY55: 1006.3 | AZ55: 24.66 | BA55: 2.392 | BB55: -1 | BC55: ticks | BD55: 1013 | BE55: 9 | BF55: 3214929/DAXEUR/2026-08-03_56856761_DAXEUR_sell_loss
A56: 55 | B56: 56869455 | C56: XAUUSD | D56: sell | E56: 0.01 | F56: 46237.368 | G56: 46237.375 | H56: Monday | I56: 8 | J56: London | K56: 2026-W32 | L56: 2026-08 | M56: 9m 30s | N56: 570.325 | O56: 9.505 | P56: C. 5-15 min | Q56: 4059.56 | R56: 4059.52 | S56: 4062.11 | T56: 4056.83 | U56: 4059.51 | V56: Tightened | W56: 250 | X56: 2.55 | Y56: 1.071 | Z56: -0.004 | AA56: D. -0.5R..0 | AB56: 0.04 | AC56: -0.05 | AD56: -0.01 | AE56: Loss | AF56: Stop Loss | AG56: 4 | AH56: 1.56 | AI56: -1.6 | AJ56: 0.612 | AK56: -0.627 | AL56: 4058 | AM56: 4061.16 | AN56: 3m 28s | AO56: 5m 46s | AP56: 62.7 | AQ56: -0.006 | AR56: 1.57 | AS56: 0.4937 | AT56: 0.519 | AU56: 0.0127 | AV56: Yes | AW56: No | AX56: 0.253 | AY56: 1006.29 | AZ56: 24.67 | BA56: 2.393 | BB56: -2 | BC56: ticks | BD56: 785 | BE56: 9 | BF56: 3214929/XAUUSD/2026-08-03_56869455_XAUUSD_sell_loss
A57: 56 | B57: 56869513 | C57: XAUUSD | D57: sell | E57: 0.03 | F57: 46237.368 | G57: 46237.392 | H57: Monday | I57: 8 | J57: London | K57: 2026-W32 | L57: 2026-08 | M57: 34m 41s | N57: 2080.849 | O57: 34.681 | P57: E. 30-60 min | Q57: 4059.56 | R57: 4056.04 | S57: 4062.84 | T57: 4056.2 | U57: 4056.04 | V57: Widened | W57: -24 | X57: 9.84 | Y57: 1.024 | Z57: 1.059 | AA57: H. 1R..2R | AB57: 10.56 | AC57: -0.14 | AD57: 10.42 | AE57: Win | AF57: Stop Loss | AG57: 352 | AH57: 19.59 | AI57: -8.61 | AJ57: 1.991 | AK57: -0.875 | AL57: 4053.03 | AM57: 4062.43 | AN57: 33m 36s | AO57: 23m 22s | AP57: 87.5 | AQ57: 0.532 | AR57: 9.17 | AS57: 0.6947 | AT57: 0.6798 | AU57: 0.3745 | AV57: No | AW57: No | AX57: 0.978 | AY57: 1016.71 | AZ57: 14.25 | BA57: 1.382 | BB57: 1 | BC57: ticks | BD57: 3044 | BE57: 9 | BF57: 3214929/XAUUSD/2026-08-03_56869513_XAUUSD_sell_win
A58: 57 | B58: 56871255 | C58: DAXEUR | D58: sell | E58: 0.04 | F58: 46237.375 | G58: 46237.396 | H58: Monday | I58: 8 | J58: London | K58: 2026-W32 | L58: 2026-08 | M58: 30m 58s | N58: 1857.606 | O58: 30.96 | P58: E. 30-60 min | Q58: 26003.93 | R58: 26009.68 | S58: 26021.79 | T58: 25984.28 | U58: 26009.37 | V58: Tightened | W58: 1242 | X58: 8.24 | Y58: 1.101 | Z58: -0.322 | AA58: D. -0.5R..0 | AB58: -2.65 | AC58: 0 | AD58: -2.65 | AE58: Loss | AF58: Stop Loss | AG58: -575 | AH58: 6.58 | AI58: -6.11 | AJ58: 0.799 | AK58: -0.742 | AL58: 25989.68 | AM58: 26017.18 | AN58: 26m 45s | AO58: 40s | AP58: 74.2 | AQ58: -0.403 | AR58: 9.23 | AS58: 0.5182 | AT58: 0.2727 | AU58: -0.2091 | AV58: No | AW58: No | AX58: 0.81 | AY58: 1014.06 | AZ58: 16.9 | BA58: 1.639 | BB58: -1 | BC58: ticks | BD58: 2118 | BE58: 9 | BF58: 3214929/DAXEUR/2026-08-03_56871255_DAXEUR_sell_loss
A59: 58 | B59: 56887531 | C59: DAXEUR | D59: sell | E59: 0.03 | F59: 46237.409 | G59: 46237.416 | H59: Monday | I59: 9 | J59: London | K59: 2026-W32 | L59: 2026-08 | M59: 9m 31s | N59: 571.044 | O59: 9.517 | P59: C. 5-15 min | Q59: 26035.93 | R59: 25997.68 | S59: 26047.39 | T59: 26023.32 | U59: 26047.39 | V59: Unchanged | W59: 0 | X59: 3.97 | Y59: 1.098 | Z59: 3.332 | AA59: J. >= 3R | AB59: 13.23 | AC59: 0 | AD59: 13.23 | AE59: Win | AF59: Take Profit | AG59: 3825 | AH59: 13.24 | AI59: -0.78 | AJ59: 3.335 | AK59: -0.196 | AL59: 25997.68 | AM59: 26038.18 | AN59: 9m 31s | AO59: 2.6s | AP59: 19.6 | AQ59: 0.999 | AR59: 0.01 | AS59: 0.9444 | AT59: 1 | AU59: 0.9444 | AV59: No | AW59: No | AX59: 0.391 | AY59: 1027.29 | AZ59: 3.67 | BA59: 0.356 | BB59: 1 | BC59: ticks | BD59: 604 | BE59: 9 | BF59: 3214929/DAXEUR/2026-08-03_56887531_DAXEUR_sell_win
A60: 59 | B60: 56885565 | C60: DAXEUR | D60: sell | E60: 0.04 | F60: 46237.408 | G60: 46237.424 | H60: Monday | I60: 9 | J60: London | K60: 2026-W32 | L60: 2026-08 | M60: 22m 22s | N60: 1341.505 | O60: 22.358 | P60: D. 15-30 min | Q60: 26029.43 | R60: 25985.18 | S60: 26042.3 | T60: 26003.97 | U60: 26042.3 | V60: Unchanged | W60: 0 | X60: 5.94 | Y60: 1.976 | Z60: 3.433 | AA60: J. >= 3R | AB60: 20.39 | AC60: 0 | AD60: 20.39 | AE60: Win | AF60: Take Profit | AG60: 4425 | AH60: 20.65 | AI60: -4.04 | AJ60: 3.476 | AK60: -0.68 | AL60: 25984.68 | AM60: 26038.18 | AN60: 15m 18s | AO60: 57s | AP60: 68 | AQ60: 0.987 | AR60: 0.26 | AS60: 0.8364 | AT60: 0.9907 | AU60: 0.8271 | AV60: No | AW60: No | AX60: 0.578 | AY60: 1047.68 | AZ60: 0 | BA60: 0 | BB60: 2 | BC60: ticks | BD60: 1433 | BE60: 9 | BF60: 3214929/DAXEUR/2026-08-03_56885565_DAXEUR_sell_win
A61: 60 | B61: 56906785 | C61: XAUUSD | D61: buy | E61: 0.04 | F61: 46237.473 | G61: 46237.493 | H61: Monday | I61: 11 | J61: London | K61: 2026-W32 | L61: 2026-08 | M61: 28m 12s | N61: 1692.456 | O61: 28.208 | P61: D. 15-30 min | Q61: 4046.96 | R61: 4058.62 | S61: 4044.32 | T61: 4058.31 | U61: 4044.32 | V61: Unchanged | W61: 0 | X61: 10.56 | Y61: 4.299 | Z61: 4.4 | AA61: J. >= 3R | AB61: 46.64 | AC61: -0.18 | AD61: 46.46 | AE61: Win | AF61: Take Profit | AG61: 1166 | AH61: 46.64 | AI61: -5.76 | AJ61: 4.417 | AK61: -0.545 | AL61: 4058.62 | AM61: 4045.52 | AN61: 28m 12s | AO61: 1m 29s | AP61: 54.5 | AQ61: 0.996 | AR61: 0.18 | AS61: 0.8901 | AT61: 1 | AU61: 0.8901 | AV61: No | AW61: No | AX61: 1.008 | AY61: 1094.14 | AZ61: 0 | BA61: 0 | BB61: 3 | BC61: ticks | BD61: 2441 | BE61: 9 | BF61: 3214929/XAUUSD/2026-08-03_56906785_XAUUSD_buy_win
A62: 61 | B62: 56908570 | C62: NIKJPY | D62: buy | E62: 0.1 | F62: 46237.486 | G62: 46237.494 | H62: Monday | I62: 11 | J62: London | K62: 2026-W32 | L62: 2026-08 | M62: 11m 20s | N62: 679.801 | O62: 11.33 | P62: C. 5-15 min | Q62: 62765 | R62: 62605 | S62: 62606 | T62: 63158 | U62: 62606 | V62: Unchanged | W62: 0 | X62: 9.98 | Y62: 2.472 | Z62: -1.023 | AA62: B. -1.5R..-1R | AB62: -10.21 | AC62: 0 | AD62: -10.21 | AE62: Loss | AF62: Stop Loss | AG62: -160 | AH62: 0 | AI62: -10.05 | AJ62: 0 | AK62: -1.007 | AL62: 62765 | AM62: 62605 | AN62: 0.0s | AO62: 11m 20s | AP62: 100.7 | AS62: 0 | AT62: 0 | AU62: -1 | AV62: Yes | AW62: Yes | AX62: 0.912 | AY62: 1083.93 | AZ62: 10.21 | BA62: 0.933 | BB62: -1 | BC62: ticks | BD62: 687 | BE62: 9 | BF62: 3214929/NIKJPY/2026-08-03_56908570_NIKJPY_buy_loss
A63: 62 | B63: 57008578 | C63: DJIUSD | D63: buy | E63: 0.02 | F63: 46237.585 | G63: 46237.586 | H63: Monday | I63: 14 | J63: NY Overlap | K63: 2026-W32 | L63: 2026-08 | M63: 1m 13s | N63: 72.754 | O63: 1.213 | P63: B. 1-5 min | Q63: 53233.94 | R63: 53209.65 | S63: 53211.15 | T63: 53253.76 | U63: 53211.15 | V63: Unchanged | W63: 0 | X63: 4.56 | Y63: 0.868 | Z63: -1.066 | AA63: B. -1.5R..-1R | AB63: -4.86 | AC63: 0 | AD63: -4.86 | AE63: Loss | AF63: Stop Loss | AG63: -2429 | AH63: 1.94 | AI63: -5.06 | AJ63: 0.425 | AK63: -1.11 | AL63: 53243.65 | AM63: 53208.65 | AN63: 48s | AO63: 1m 13s | AP63: 111 | AQ63: -2.505 | AR63: 6.8 | AS63: 0.2774 | AT63: 0.0286 | AU63: -0.694 | AV63: Yes | AW63: No | AX63: 0.421 | AY63: 1079.07 | AZ63: 15.07 | BA63: 1.377 | BB63: -2 | BC63: ticks | BD63: 158 | BE63: 9 | BF63: 3214929/DJIUSD/2026-08-03_57008578_DJIUSD_buy_loss
A64: 63 | B64: 57019000 | C64: DJIUSD | D64: buy | E64: 0.01 | F64: 46237.593 | G64: 46237.597 | H64: Monday | I64: 14 | J64: NY Overlap | K64: 2026-W32 | L64: 2026-08 | M64: 5m 36s | N64: 336.485 | O64: 5.608 | P64: C. 5-15 min | Q64: 53209.89 | R64: 53163.1 | S64: 53169.42 | T64: 53221.96 | U64: 53163.85 | V64: Widened | W64: -557 | X64: 4.05 | Y64: 0.299 | Z64: -1.156 | AA64: B. -1.5R..-1R | AB64: -4.68 | AC64: 0 | AD64: -4.68 | AE64: Loss | AF64: Stop Loss | AG64: -4679 | AH64: 1.22 | AI64: -5.68 | AJ64: 0.301 | AK64: -1.402 | AL64: 53222.1 | AM64: 53153.1 | AN64: 51s | AO64: 5m 37s | AP64: 140.2 | AQ64: -3.836 | AR64: 5.9 | AS64: 0.177 | AT64: 0.1449 | AU64: -0.6781 | AV64: Yes | AW64: No | AX64: 0.375 | AY64: 1074.39 | AZ64: 19.75 | BA64: 1.805 | BB64: -3 | BC64: ticks | BD64: 703 | BE64: 9 | BF64: 3214929/DJIUSD/2026-08-03_57019000_DJIUSD_buy_loss
A65: 64 | B65: 57028737 | C65: XAUUSD | D65: buy | E65: 0.03 | F65: 46237.603 | G65: 46237.629 | H65: Monday | I65: 14 | J65: NY Overlap | K65: 2026-W32 | L65: 2026-08 | M65: 37m 46s | N65: 2266.312 | O65: 37.772 | P65: E. 30-60 min | Q65: 4034.8 | R65: 4030.41 | S65: 4031.89 | T65: 4038.18 | U65: 4030.43 | V65: Widened | W65: -146 | X65: 8.73 | Y65: 1.162 | Z65: -1.525 | AA65: A. <= -1.5R | AB65: -13.17 | AC65: -0.14 | AD65: -13.31 | AE65: Loss | AF65: Stop Loss | AG65: -439 | AH65: 13.08 | AI65: -13.17 | AJ65: 1.498 | AK65: -1.509 | AL65: 4039.16 | AM65: 4030.41 | AN65: 29m 06s | AO65: 37m 46s | AP65: 150.9 | AQ65: -1.018 | AR65: 26.39 | AS65: 0.4983 | AT65: 0 | AU65: -0.5017 | AV65: Yes | AW65: No | AX65: 0.813 | AY65: 1061.08 | AZ65: 33.06 | BA65: 3.022 | BB65: -4 | BC65: ticks | BD65: 4488 | BE65: 9 | BF65: 3214929/XAUUSD/2026-08-03_57028737_XAUUSD_buy_loss
A66: 65 | B66: 57056264 | C66: DAXEUR | D66: buy | E66: 0.01 | F66: 46237.637 | G66: 46237.639 | H66: Monday | I66: 15 | J66: NY Overlap | K66: 2026-W32 | L66: 2026-08 | M66: 3m 12s | N66: 192.489 | O66: 3.208 | P66: B. 1-5 min | Q66: 26042.28 | R66: 26041.53 | S66: 26025.66 | T66: 26102.56 | U66: 26042.28 | V66: Breakeven | W66: 1662 | X66: 1.92 | Y66: 3.625 | Z66: -0.047 | AA66: D. -0.5R..0 | AB66: -0.09 | AC66: 0 | AD66: -0.09 | AE66: Loss | AF66: Stop Loss | AG66: -75 | AH66: 0.78 | AI66: -1.53 | AJ66: 0.406 | AK66: -0.797 | AL66: 26049.03 | AM66: 26029.03 | AN66: 3m 13s | AO66: 49s | AP66: 79.7 | AQ66: -0.115 | AR66: 0.87 | AS66: 0.3375 | AT66: 0.625 | AU66: -0.0375 | AV66: No | AW66: No | AX66: 0.181 | AY66: 1060.99 | AZ66: 33.15 | BA66: 3.03 | BB66: -5 | BC66: ticks | BD66: 211 | BE66: 9 | BF66: 3214929/DAXEUR/2026-08-03_57056264_DAXEUR_buy_loss
A67: 66 | B67: 57056600 | C67: DAXEUR | D67: buy | E67: 0.04 | F67: 46237.637 | G67: 46237.644 | H67: Monday | I67: 15 | J67: NY Overlap | K67: 2026-W32 | L67: 2026-08 | M67: 9m 09s | N67: 549.012 | O67: 9.15 | P67: C. 5-15 min | Q67: 26030.28 | R67: 26057.48 | S67: 26021.01 | T67: 26040.48 | U67: 26021.01 | V67: Unchanged | W67: 0 | X67: 4.28 | Y67: 1.1 | Z67: 2.925 | AA67: I. 2R..3R | AB67: 12.52 | AC67: 0 | AD67: 12.52 | AE67: Win | AF67: Expert | AG67: 2720 | AH67: 12.78 | AI67: -0.58 | AJ67: 2.986 | AK67: -0.136 | AL67: 26057.98 | AM67: 26029.03 | AN67: 9m 07s | AO67: 0.0s | AP67: 13.6 | AQ67: 0.98 | AR67: 0.26 | AS67: 0.9568 | AT67: 0.9827 | AU67: 0.9396 | AV67: No | AW67: No | AX67: 0.403 | AY67: 1073.51 | AZ67: 20.63 | BA67: 1.885 | BB67: 1 | BC67: ticks | BD67: 602 | BE67: 9 | BF67: 3214929/DAXEUR/2026-08-03_57056600_DAXEUR_buy_win
A68: 67 | B68: 57064381 | C68: DJIUSD | D68: sell | E68: 0.05 | F68: 46237.654 | G68: 46237.664 | H68: Monday | I68: 15 | J68: NY Overlap | K68: 2026-W32 | L68: 2026-08 | M68: 14m 39s | N68: 879.06 | O68: 14.651 | P68: C. 5-15 min | Q68: 53061.55 | R68: 53036.34 | S68: 53077.17 | T68: 53037.44 | U68: 53077.17 | V68: Unchanged | W68: 0 | X68: 7.81 | Y68: 1.544 | Z68: 1.615 | AA68: H. 1R..2R | AB68: 12.61 | AC68: 0 | AD68: 12.61 | AE68: Win | AF68: Expert | AG68: 2521 | AH68: 14.36 | AI68: -8.4 | AJ68: 1.839 | AK68: -1.076 | AL68: 53032.84 | AM68: 53078.34 | AN68: 14m 36s | AO68: 10m 49s | AP68: 107.6 | AQ68: 0.878 | AR68: 1.75 | AS68: 0.631 | AT68: 0.9231 | AU68: 0.5541 | AV68: No | AW68: No | AX68: 0.728 | AY68: 1086.12 | AZ68: 8.02 | BA68: 0.733 | BB68: 2 | BC68: ticks | BD68: 1293 | BE68: 9 | BF68: 3214929/DJIUSD/2026-08-03_57064381_DJIUSD_sell_win
A69: 68 | B69: 57062642 | C69: NDXUSD | D69: sell | E69: 0.01 | F69: 46237.649 | G69: 46237.678 | H69: Monday | I69: 15 | J69: NY Overlap | K69: 2026-W32 | L69: 2026-08 | M69: 41m 43s | N69: 2503.277 | O69: 41.721 | P69: E. 30-60 min | Q69: 28648.4 | R69: 28707.95 | S69: 28679.77 | T69: 28613.9 | U69: 28707.9 | V69: Widened | W69: -2813 | X69: 3.14 | Y69: 1.099 | Z69: -1.898 | AA69: A. <= -1.5R | AB69: -5.96 | AC69: 0 | AD69: -5.96 | AE69: Loss | AF69: Stop Loss | AG69: -5955 | AH69: 1.77 | AI69: -5.96 | AJ69: 0.564 | AK69: -1.898 | AL69: 28630.7 | AM69: 28707.95 | AN69: 3m 11s | AO69: 41m 43s | AP69: 189.8 | AQ69: -3.367 | AR69: 7.73 | AS69: 0.2291 | AT69: 0 | AU69: -0.7709 | AV69: Yes | AW69: No | AX69: 0.289 | AY69: 1080.16 | AZ69: 13.98 | BA69: 1.278 | BB69: -1 | BC69: ticks | BD69: 6221 | BE69: 9 | BF69: 3214929/NDXUSD/2026-08-03_57062642_NDXUSD_sell_loss
A70: 69 | B70: 57073391 | C70: DJIUSD | D70: sell | E70: 0.01 | F70: 46237.671 | G70: 46237.738 | H70: Monday | I70: 16 | J70: NY Overlap | K70: 2026-W32 | L70: 2026-08 | M70: 1h 37m | N70: 5854.162 | O70: 97.569 | P70: F. 1-4 h | Q70: 52999.15 | R70: 53067.94 | S70: 53046.02 | T70: 52946.54 | U70: 53067.15 | V70: Widened | W70: -2113 | X70: 4.69 | Y70: 1.122 | Z70: -1.467 | AA70: B. -1.5R..-1R | AB70: -6.88 | AC70: 0 | AD70: -6.88 | AE70: Loss | AF70: Stop Loss | AG70: -6879 | AH70: 6.72 | AI70: -6.98 | AJ70: 1.433 | AK70: -1.488 | AL70: 52931.94 | AM70: 53068.94 | AN70: 1h 01m | AO70: 1h 37m | AP70: 148.8 | AQ70: -1.024 | AR70: 13.6 | AS70: 0.4906 | AT70: 0.0073 | AU70: -0.5021 | AV70: Yes | AW70: No | AX70: 0.434 | AY70: 1073.28 | AZ70: 20.86 | BA70: 1.907 | BB70: -2 | BC70: ticks | BD70: 7481 | BE70: 9 | BF70: 3214929/DJIUSD/2026-08-03_57073391_DJIUSD_sell_loss
A71: 70 | B71: 57103528 | C71: DJIUSD | D71: buy | E71: 0.04 | F71: 46237.77 | G71: 46237.774 | H71: Monday | I71: 18 | J71: NY Late | K71: 2026-W32 | L71: 2026-08 | M71: 5m 16s | N71: 315.848 | O71: 5.264 | P71: C. 5-15 min | Q71: 53113.94 | R71: 53090.15 | S71: 53090.23 | T71: 53181.9 | U71: 53090.23 | V71: Unchanged | W71: 0 | X71: 9.48 | Y71: 2.867 | Z71: -1.004 | AA71: B. -1.5R..-1R | AB71: -9.52 | AC71: 0 | AD71: -9.52 | AE71: Loss | AF71: Stop Loss | AG71: -2379 | AH71: 10.48 | AI71: -9.52 | AJ71: 1.105 | AK71: -1.004 | AL71: 53140.15 | AM71: 53090.15 | AN71: 1m 32s | AO71: 5m 16s | AP71: 100.4 | AQ71: -0.908 | AR71: 20 | AS71: 0.5242 | AT71: 0 | AU71: -0.4758 | AV71: Yes | AW71: No | AX71: 0.883 | AY71: 1063.76 | AZ71: 30.38 | BA71: 2.777 | BB71: -3 | BC71: ticks | BD71: 463 | BE71: 9 | BF71: 3214929/DJIUSD/2026-08-03_57103528_DJIUSD_buy_loss
A72: 71 | B72: 57182957 | C72: DAXEUR | D72: buy | E72: 0.03 | F72: 46238.307 | G72: 46238.311 | H72: Tuesday | I72: 7 | J72: Asia | K72: 2026-W32 | L72: 2026-08 | M72: 5m 58s | N72: 358.241 | O72: 5.971 | P72: C. 5-15 min | Q72: 26213.78 | R72: 26236.53 | S72: 26200.83 | T72: 26230.12 | U72: 26200.83 | V72: Unchanged | W72: 0 | X72: 4.49 | Y72: 1.258 | Z72: 1.751 | AA72: H. 1R..2R | AB72: 7.86 | AC72: 0 | AD72: 7.86 | AE72: Win | AF72: Expert | AG72: 2275 | AH72: 7.88 | AI72: -1.3 | AJ72: 1.755 | AK72: -0.29 | AL72: 26236.53 | AM72: 26210.03 | AN72: 4m 47s | AO72: 18s | AP72: 29 | AQ72: 0.997 | AR72: 0.02 | AS72: 0.8585 | AT72: 1 | AU72: 0.8585 | AV72: No | AW72: No | AX72: 0.422 | AY72: 1071.62 | AZ72: 22.52 | BA72: 2.058 | BB72: 1 | BC72: ticks | BD72: 462 | BE72: 9 | BF72: 3214929/DAXEUR/2026-08-04_57182957_DAXEUR_buy_win
A73: 72 | B73: 57182998 | C73: DAXEUR | D73: buy | E73: 0.03 | F73: 46238.307 | G73: 46238.311 | H73: Tuesday | I73: 7 | J73: Asia | K73: 2026-W32 | L73: 2026-08 | M73: 5m 53s | N73: 353.48 | O73: 5.891 | P73: C. 5-15 min | Q73: 26212.78 | R73: 26238.53 | S73: 26200.3 | T73: 26227.56 | U73: 26200.3 | V73: Unchanged | W73: 0 | X73: 4.31 | Y73: 1.186 | Z73: 2.065 | AA73: I. 2R..3R | AB73: 8.9 | AC73: 0 | AD73: 8.9 | AE73: Win | AF73: Take Profit | AG73: 2575 | AH73: 8.92 | AI73: -0.96 | AJ73: 2.07 | AK73: -0.223 | AL73: 26238.53 | AM73: 26210.03 | AN73: 5m 53s | AO73: 8.8s | AP73: 22.3 | AQ73: 0.998 | AR73: 0.02 | AS73: 0.9035 | AT73: 1 | AU73: 0.9035 | AV73: No | AW73: No | AX73: 0.402 | AY73: 1080.52 | AZ73: 13.62 | BA73: 1.245 | BB73: 2 | BC73: ticks | BD73: 457 | BE73: 9 | BF73: 3214929/DAXEUR/2026-08-04_57182998_DAXEUR_buy_win
A74: 73 | B74: 57186051 | C74: DAXEUR | D74: sell | E74: 0.05 | F74: 46238.315 | G74: 46238.322 | H74: Tuesday | I74: 7 | J74: Asia | K74: 2026-W32 | L74: 2026-08 | M74: 10m 34s | N74: 633.989 | O74: 10.566 | P74: C. 5-15 min | Q74: 26258.03 | R74: 26222.78 | S74: 26275.4 | T74: 26223.19 | U74: 26275.4 | V74: Unchanged | W74: 0 | X74: 10.02 | Y74: 2.006 | Z74: 2.025 | AA74: I. 2R..3R | AB74: 20.29 | AC74: 0 | AD74: 20.29 | AE74: Win | AF74: Take Profit | AG74: 3525 | AH74: 20.34 | AI74: -2.17 | AJ74: 2.03 | AK74: -0.217 | AL74: 26222.78 | AM74: 26261.78 | AN74: 10m 34s | AO74: 19s | AP74: 21.7 | AQ74: 0.998 | AR74: 0.05 | AS74: 0.9038 | AT74: 1 | AU74: 0.9038 | AV74: No | AW74: No | AX74: 0.927 | AY74: 1100.81 | AZ74: 0 | BA74: 0 | BB74: 3 | BC74: ticks | BD74: 821 | BE74: 9 | BF74: 3214929/DAXEUR/2026-08-04_57186051_DAXEUR_sell_win

Sheet Pivots
A1: What is making and losing the money
A2: Live formula grids over the Trades table. Both dropdowns apply to every grid on the sheet.
A4: Filters | C4: Symbol | D4: (All) | F4: Outcome | G4: (All) | I4: Change either dropdown - every grid below recalculates.
A6: By symbol | E6: Concentration check: one instrument carrying the account is a risk, not a strength.
A7: Symbol | B7: Trades | C7: Wins | D7: Win % | E7: Net | F7: Expectancy | G7: Avg R | H7: Profit factor | I7: Avg MFE | J7: Avg MAE | K7: Avg dur (min) | L7: Share of net
A8: DAXEUR | B8: =COUNTIFS(Trades!$C$2:$C$74,$A$8,Trades!$C$2:$C$74,IF($D$4="(All)","*",$D$4),Trades!$AE$2:$AE$74,IF($G$4="(All)","*",$G$4)) | C8: =COUNTIFS(Trades!$AE$2:$AE$74,"Win",Trades!$C$2:$C$74,$A$8,Trades!$C$2:$C$74,IF($D$4="(All)","*",$D$4),Trades!$AE$2:$AE$74,IF($G$4="(All)","*",$G$4)) | D8: =IFERROR(C8/B8*100,"") | E8: =SUMIFS(Trades!$AD$2:$AD$74,Trades!$C$2:$C$74,$A$8,Trades!$C$2:$C$74,IF($D$4="(All)","*",$D$4),Trades!$AE$2:$AE$74,IF($G$4="(All)","*",$G$4)) | F8: =IFERROR(E8/B8,"") | G8: =IFERROR(AVERAGEIFS(Trades!$Z$2:$Z$74,Trades!$C$2:$C$74,$A$8,Trades!$C$2:$C$74,IF($D$4="(All)","*",$D$4),Trades!$AE$2:$AE$74,IF($G$4="(All)","*",$G$4)),"") | H8: =IFERROR(SUMIFS(Trades!$AD$2:$AD$74,Trades!$C$2:$C$74,$A$8,Trades!$AD$2:$AD$74,">0",Trades!$C$2:$C$74,IF($D$4="(All)","*",$D$4),Trades!$AE$2:$AE$74,IF($G$4="(All)","*",$G$4))/-SUMIFS(Trades!$AD$2:$AD$74,Trades!$C$2:$C$74,$A$8,Trades!$AD$2:$AD$74,"<0",Trades!$C$2:$C$74,IF($D$4="(All)","*",$D$4),Trades!$AE$2:$AE$74,IF($G$4="(All)","*",$G$4)),"") | I8: =IFERROR(AVERAGEIFS(Trades!$AH$2:$AH$74,Trades!$C$2:$C$74,$A$8,Trades!$C$2:$C$74,IF($D$4="(All)","*",$D$4),Trades!$AE$2:$AE$74,IF($G$4="(All)","*",$G$4)),"") | J8: =IFERROR(AVERAGEIFS(Trades!$AI$2:$AI$74,Trades!$C$2:$C$74,$A$8,Trades!$C$2:$C$74,IF($D$4="(All)","*",$D$4),Trades!$AE$2:$AE$74,IF($G$4="(All)","*",$G$4)),"") | K8: =IFERROR(AVERAGEIFS(Trades!$O$2:$O$74,Trades!$C$2:$C$74,$A$8,Trades!$C$2:$C$74,IF($D$4="(All)","*",$D$4),Trades!$AE$2:$AE$74,IF($G$4="(All)","*",$G$4)),"") | L8: =IFERROR(E8/SUMIFS(Trades!$AD$2:$AD$74,Trades!$C$2:$C$74,IF($D$4="(All)","*",$D$4),Trades!$AE$2:$AE$74,IF($G$4="(All)","*",$G$4))*100,"")
A9: DJIUSD | B9: =COUNTIFS(Trades!$C$2:$C$74,$A$9,Trades!$C$2:$C$74,IF($D$4="(All)","*",$D$4),Trades!$AE$2:$AE$74,IF($G$4="(All)","*",$G$4)) | C9: =COUNTIFS(Trades!$AE$2:$AE$74,"Win",Trades!$C$2:$C$74,$A$9,Trades!$C$2:$C$74,IF($D$4="(All)","*",$D$4),Trades!$AE$2:$AE$74,IF($G$4="(All)","*",$G$4)) | D9: =IFERROR(C9/B9*100,"") | E9: =SUMIFS(Trades!$AD$2:$AD$74,Trades!$C$2:$C$74,$A$9,Trades!$C$2:$C$74,IF($D$4="(All)","*",$D$4),Trades!$AE$2:$AE$74,IF($G$4="(All)","*",$G$4)) | F9: =IFERROR(E9/B9,"") | G9: =IFERROR(AVERAGEIFS(Trades!$Z$2:$Z$74,Trades!$C$2:$C$74,$A$9,Trades!$C$2:$C$74,IF($D$4="(All)","*",$D$4),Trades!$AE$2:$AE$74,IF($G$4="(All)","*",$G$4)),"") | H9: =IFERROR(SUMIFS(Trades!$AD$2:$AD$74,Trades!$C$2:$C$74,$A$9,Trades!$AD$2:$AD$74,">0",Trades!$C$2:$C$74,IF($D$4="(All)","*",$D$4),Trades!$AE$2:$AE$74,IF($G$4="(All)","*",$G$4))/-SUMIFS(Trades!$AD$2:$AD$74,Trades!$C$2:$C$74,$A$9,Trades!$AD$2:$AD$74,"<0",Trades!$C$2:$C$74,IF($D$4="(All)","*",$D$4),Trades!$AE$2:$AE$74,IF($G$4="(All)","*",$G$4)),"") | I9: =IFERROR(AVERAGEIFS(Trades!$AH$2:$AH$74,Trades!$C$2:$C$74,$A$9,Trades!$C$2:$C$74,IF($D$4="(All)","*",$D$4),Trades!$AE$2:$AE$74,IF($G$4="(All)","*",$G$4)),"") | J9: =IFERROR(AVERAGEIFS(Trades!$AI$2:$AI$74,Trades!$C$2:$C$74,$A$9,Trades!$C$2:$C$74,IF($D$4="(All)","*",$D$4),Trades!$AE$2:$AE$74,IF($G$4="(All)","*",$G$4)),"") | K9: =IFERROR(AVERAGEIFS(Trades!$O$2:$O$74,Trades!$C$2:$C$74,$A$9,Trades!$C$2:$C$74,IF($D$4="(All)","*",$D$4),Trades!$AE$2:$AE$74,IF($G$4="(All)","*",$G$4)),"") | L9: =IFERROR(E9/SUMIFS(Trades!$AD$2:$AD$74,Trades!$C$2:$C$74,IF($D$4="(All)","*",$D$4),Trades!$AE$2:$AE$74,IF($G$4="(All)","*",$G$4))*100,"")
A10: NDXUSD | B10: =COUNTIFS(Trades!$C$2:$C$74,$A$10,Trades!$C$2:$C$74,IF($D$4="(All)","*",$D$4),Trades!$AE$2:$AE$74,IF($G$4="(All)","*",$G$4)) | C10: =COUNTIFS(Trades!$AE$2:$AE$74,"Win",Trades!$C$2:$C$74,$A$10,Trades!$C$2:$C$74,IF($D$4="(All)","*",$D$4),Trades!$AE$2:$AE$74,IF($G$4="(All)","*",$G$4)) | D10: =IFERROR(C10/B10*100,"") | E10: =SUMIFS(Trades!$AD$2:$AD$74,Trades!$C$2:$C$74,$A$10,Trades!$C$2:$C$74,IF($D$4="(All)","*",$D$4),Trades!$AE$2:$AE$74,IF($G$4="(All)","*",$G$4)) | F10: =IFERROR(E10/B10,"") | G10: =IFERROR(AVERAGEIFS(Trades!$Z$2:$Z$74,Trades!$C$2:$C$74,$A$10,Trades!$C$2:$C$74,IF($D$4="(All)","*",$D$4),Trades!$AE$2:$AE$74,IF($G$4="(All)","*",$G$4)),"") | H10: =IFERROR(SUMIFS(Trades!$AD$2:$AD$74,Trades!$C$2:$C$74,$A$10,Trades!$AD$2:$AD$74,">0",Trades!$C$2:$C$74,IF($D$4="(All)","*",$D$4),Trades!$AE$2:$AE$74,IF($G$4="(All)","*",$G$4))/-SUMIFS(Trades!$AD$2:$AD$74,Trades!$C$2:$C$74,$A$10,Trades!$AD$2:$AD$74,"<0",Trades!$C$2:$C$74,IF($D$4="(All)","*",$D$4),Trades!$AE$2:$AE$74,IF($G$4="(All)","*",$G$4)),"") | I10: =IFERROR(AVERAGEIFS(Trades!$AH$2:$AH$74,Trades!$C$2:$C$74,$A$10,Trades!$C$2:$C$74,IF($D$4="(All)","*",$D$4),Trades!$AE$2:$AE$74,IF($G$4="(All)","*",$G$4)),"") | J10: =IFERROR(AVERAGEIFS(Trades!$AI$2:$AI$74,Trades!$C$2:$C$74,$A$10,Trades!$C$2:$C$74,IF($D$4="(All)","*",$D$4),Trades!$AE$2:$AE$74,IF($G$4="(All)","*",$G$4)),"") | K10: =IFERROR(AVERAGEIFS(Trades!$O$2:$O$74,Trades!$C$2:$C$74,$A$10,Trades!$C$2:$C$74,IF($D$4="(All)","*",$D$4),Trades!$AE$2:$AE$74,IF($G$4="(All)","*",$G$4)),"") | L10: =IFERROR(E10/SUMIFS(Trades!$AD$2:$AD$74,Trades!$C$2:$C$74,IF($D$4="(All)","*",$D$4),Trades!$AE$2:$AE$74,IF($G$4="(All)","*",$G$4))*100,"")
A11: NIKJPY | B11: =COUNTIFS(Trades!$C$2:$C$74,$A$11,Trades!$C$2:$C$74,IF($D$4="(All)","*",$D$4),Trades!$AE$2:$AE$74,IF($G$4="(All)","*",$G$4)) | C11: =COUNTIFS(Trades!$AE$2:$AE$74,"Win",Trades!$C$2:$C$74,$A$11,Trades!$C$2:$C$74,IF($D$4="(All)","*",$D$4),Trades!$AE$2:$AE$74,IF($G$4="(All)","*",$G$4)) | D11: =IFERROR(C11/B11*100,"") | E11: =SUMIFS(Trades!$AD$2:$AD$74,Trades!$C$2:$C$74,$A$11,Trades!$C$2:$C$74,IF($D$4="(All)","*",$D$4),Trades!$AE$2:$AE$74,IF($G$4="(All)","*",$G$4)) | F11: =IFERROR(E11/B11,"") | G11: =IFERROR(AVERAGEIFS(Trades!$Z$2:$Z$74,Trades!$C$2:$C$74,$A$11,Trades!$C$2:$C$74,IF($D$4="(All)","*",$D$4),Trades!$AE$2:$AE$74,IF($G$4="(All)","*",$G$4)),"") | H11: =IFERROR(SUMIFS(Trades!$AD$2:$AD$74,Trades!$C$2:$C$74,$A$11,Trades!$AD$2:$AD$74,">0",Trades!$C$2:$C$74,IF($D$4="(All)","*",$D$4),Trades!$AE$2:$AE$74,IF($G$4="(All)","*",$G$4))/-SUMIFS(Trades!$AD$2:$AD$74,Trades!$C$2:$C$74,$A$11,Trades!$AD$2:$AD$74,"<0",Trades!$C$2:$C$74,IF($D$4="(All)","*",$D$4),Trades!$AE$2:$AE$74,IF($G$4="(All)","*",$G$4)),"") | I11: =IFERROR(AVERAGEIFS(Trades!$AH$2:$AH$74,Trades!$C$2:$C$74,$A$11,Trades!$C$2:$C$74,IF($D$4="(All)","*",$D$4),Trades!$AE$2:$AE$74,IF($G$4="(All)","*",$G$4)),"") | J11: =IFERROR(AVERAGEIFS(Trades!$AI$2:$AI$74,Trades!$C$2:$C$74,$A$11,Trades!$C$2:$C$74,IF($D$4="(All)","*",$D$4),Trades!$AE$2:$AE$74,IF($G$4="(All)","*",$G$4)),"") | K11: =IFERROR(AVERAGEIFS(Trades!$O$2:$O$74,Trades!$C$2:$C$74,$A$11,Trades!$C$2:$C$74,IF($D$4="(All)","*",$D$4),Trades!$AE$2:$AE$74,IF($G$4="(All)","*",$G$4)),"") | L11: =IFERROR(E11/SUMIFS(Trades!$AD$2:$AD$74,Trades!$C$2:$C$74,IF($D$4="(All)","*",$D$4),Trades!$AE$2:$AE$74,IF($G$4="(All)","*",$G$4))*100,"")
A12: XAUUSD | B12: =COUNTIFS(Trades!$C$2:$C$74,$A$12,Trades!$C$2:$C$74,IF($D$4="(All)","*",$D$4),Trades!$AE$2:$AE$74,IF($G$4="(All)","*",$G$4)) | C12: =COUNTIFS(Trades!$AE$2:$AE$74,"Win",Trades!$C$2:$C$74,$A$12,Trades!$C$2:$C$74,IF($D$4="(All)","*",$D$4),Trades!$AE$2:$AE$74,IF($G$4="(All)","*",$G$4)) | D12: =IFERROR(C12/B12*100,"") | E12: =SUMIFS(Trades!$AD$2:$AD$74,Trades!$C$2:$C$74,$A$12,Trades!$C$2:$C$74,IF($D$4="(All)","*",$D$4),Trades!$AE$2:$AE$74,IF($G$4="(All)","*",$G$4)) | F12: =IFERROR(E12/B12,"") | G12: =IFERROR(AVERAGEIFS(Trades!$Z$2:$Z$74,Trades!$C$2:$C$74,$A$12,Trades!$C$2:$C$74,IF($D$4="(All)","*",$D$4),Trades!$AE$2:$AE$74,IF($G$4="(All)","*",$G$4)),"") | H12: =IFERROR(SUMIFS(Trades!$AD$2:$AD$74,Trades!$C$2:$C$74,$A$12,Trades!$AD$2:$AD$74,">0",Trades!$C$2:$C$74,IF($D$4="(All)","*",$D$4),Trades!$AE$2:$AE$74,IF($G$4="(All)","*",$G$4))/-SUMIFS(Trades!$AD$2:$AD$74,Trades!$C$2:$C$74,$A$12,Trades!$AD$2:$AD$74,"<0",Trades!$C$2:$C$74,IF($D$4="(All)","*",$D$4),Trades!$AE$2:$AE$74,IF($G$4="(All)","*",$G$4)),"") | I12: =IFERROR(AVERAGEIFS(Trades!$AH$2:$AH$74,Trades!$C$2:$C$74,$A$12,Trades!$C$2:$C$74,IF($D$4="(All)","*",$D$4),Trades!$AE$2:$AE$74,IF($G$4="(All)","*",$G$4)),"") | J12: =IFERROR(AVERAGEIFS(Trades!$AI$2:$AI$74,Trades!$C$2:$C$74,$A$12,Trades!$C$2:$C$74,IF($D$4="(All)","*",$D$4),Trades!$AE$2:$AE$74,IF($G$4="(All)","*",$G$4)),"") | K12: =IFERROR(AVERAGEIFS(Trades!$O$2:$O$74,Trades!$C$2:$C$74,$A$12,Trades!$C$2:$C$74,IF($D$4="(All)","*",$D$4),Trades!$AE$2:$AE$74,IF($G$4="(All)","*",$G$4)),"") | L12: =IFERROR(E12/SUMIFS(Trades!$AD$2:$AD$74,Trades!$C$2:$C$74,IF($D$4="(All)","*",$D$4),Trades!$AE$2:$AE$74,IF($G$4="(All)","*",$G$4))*100,"")
A13: All trades | B13: =COUNTIFS(Trades!$C$2:$C$74,IF($D$4="(All)","*",$D$4),Trades!$AE$2:$AE$74,IF($G$4="(All)","*",$G$4)) | C13: =COUNTIFS(Trades!$AE$2:$AE$74,"Win",Trades!$C$2:$C$74,IF($D$4="(All)","*",$D$4),Trades!$AE$2:$AE$74,IF($G$4="(All)","*",$G$4)) | D13: =IFERROR(C13/B13*100,"") | E13: =SUMIFS(Trades!$AD$2:$AD$74,Trades!$C$2:$C$74,IF($D$4="(All)","*",$D$4),Trades!$AE$2:$AE$74,IF($G$4="(All)","*",$G$4)) | F13: =IFERROR(E13/B13,"") | G13: =IFERROR(AVERAGEIFS(Trades!$Z$2:$Z$74,Trades!$C$2:$C$74,IF($D$4="(All)","*",$D$4),Trades!$AE$2:$AE$74,IF($G$4="(All)","*",$G$4)),"") | H13: =IFERROR(SUMIFS(Trades!$AD$2:$AD$74,Trades!$AD$2:$AD$74,">0",Trades!$C$2:$C$74,IF($D$4="(All)","*",$D$4),Trades!$AE$2:$AE$74,IF($G$4="(All)","*",$G$4))/-SUMIFS(Trades!$AD$2:$AD$74,Trades!$AD$2:$AD$74,"<0",Trades!$C$2:$C$74,IF($D$4="(All)","*",$D$4),Trades!$AE$2:$AE$74,IF($G$4="(All)","*",$G$4)),"") | I13: =IFERROR(AVERAGEIFS(Trades!$AH$2:$AH$74,Trades!$C$2:$C$74,IF($D$4="(All)","*",$D$4),Trades!$AE$2:$AE$74,IF($G$4="(All)","*",$G$4)),"") | J13: =IFERROR(AVERAGEIFS(Trades!$AI$2:$AI$74,Trades!$C$2:$C$74,IF($D$4="(All)","*",$D$4),Trades!$AE$2:$AE$74,IF($G$4="(All)","*",$G$4)),"") | K13: =IFERROR(AVERAGEIFS(Trades!$O$2:$O$74,Trades!$C$2:$C$74,IF($D$4="(All)","*",$D$4),Trades!$AE$2:$AE$74,IF($G$4="(All)","*",$G$4)),"") | L13: =IFERROR(E13/SUMIFS(Trades!$AD$2:$AD$74,Trades!$C$2:$C$74,IF($D$4="(All)","*",$D$4),Trades!$AE$2:$AE$74,IF($G$4="(All)","*",$G$4))*100,"")
A16: By side | E16: A large gap between buy and sell says the edge is directional, not systematic.
A17: Side | B17: Trades | C17: Wins | D17: Win % | E17: Net | F17: Expectancy | G17: Avg R | H17: Profit factor | I17: Avg MFE | J17: Avg MAE | K17: Avg dur (min) | L17: Share of net
A18: buy | B18: =COUNTIFS(Trades!$D$2:$D$74,$A$18,Trades!$C$2:$C$74,IF($D$4="(All)","*",$D$4),Trades!$AE$2:$AE$74,IF($G$4="(All)","*",$G$4)) | C18: =COUNTIFS(Trades!$AE$2:$AE$74,"Win",Trades!$D$2:$D$74,$A$18,Trades!$C$2:$C$74,IF($D$4="(All)","*",$D$4),Trades!$AE$2:$AE$74,IF($G$4="(All)","*",$G$4)) | D18: =IFERROR(C18/B18*100,"") | E18: =SUMIFS(Trades!$AD$2:$AD$74,Trades!$D$2:$D$74,$A$18,Trades!$C$2:$C$74,IF($D$4="(All)","*",$D$4),Trades!$AE$2:$AE$74,IF($G$4="(All)","*",$G$4)) | F18: =IFERROR(E18/B18,"") | G18: =IFERROR(AVERAGEIFS(Trades!$Z$2:$Z$74,Trades!$D$2:$D$74,$A$18,Trades!$C$2:$C$74,IF($D$4="(All)","*",$D$4),Trades!$AE$2:$AE$74,IF($G$4="(All)","*",$G$4)),"") | H18: =IFERROR(SUMIFS(Trades!$AD$2:$AD$74,Trades!$D$2:$D$74,$A$18,Trades!$AD$2:$AD$74,">0",Trades!$C$2:$C$74,IF($D$4="(All)","*",$D$4),Trades!$AE$2:$AE$74,IF($G$4="(All)","*",$G$4))/-SUMIFS(Trades!$AD$2:$AD$74,Trades!$D$2:$D$74,$A$18,Trades!$AD$2:$AD$74,"<0",Trades!$C$2:$C$74,IF($D$4="(All)","*",$D$4),Trades!$AE$2:$AE$74,IF($G$4="(All)","*",$G$4)),"") | I18: =IFERROR(AVERAGEIFS(Trades!$AH$2:$AH$74,Trades!$D$2:$D$74,$A$18,Trades!$C$2:$C$74,IF($D$4="(All)","*",$D$4),Trades!$AE$2:$AE$74,IF($G$4="(All)","*",$G$4)),"") | J18: =IFERROR(AVERAGEIFS(Trades!$AI$2:$AI$74,Trades!$D$2:$D$74,$A$18,Trades!$C$2:$C$74,IF($D$4="(All)","*",$D$4),Trades!$AE$2:$AE$74,IF($G$4="(All)","*",$G$4)),"") | K18: =IFERROR(AVERAGEIFS(Trades!$O$2:$O$74,Trades!$D$2:$D$74,$A$18,Trades!$C$2:$C$74,IF($D$4="(All)","*",$D$4),Trades!$AE$2:$AE$74,IF($G$4="(All)","*",$G$4)),"") | L18: =IFERROR(E18/SUMIFS(Trades!$AD$2:$AD$74,Trades!$C$2:$C$74,IF($D$4="(All)","*",$D$4),Trades!$AE$2:$AE$74,IF($G$4="(All)","*",$G$4))*100,"")
A19: sell | B19: =COUNTIFS(Trades!$D$2:$D$74,$A$19,Trades!$C$2:$C$74,IF($D$4="(All)","*",$D$4),Trades!$AE$2:$AE$74,IF($G$4="(All)","*",$G$4)) | C19: =COUNTIFS(Trades!$AE$2:$AE$74,"Win",Trades!$D$2:$D$74,$A$19,Trades!$C$2:$C$74,IF($D$4="(All)","*",$D$4),Trades!$AE$2:$AE$74,IF($G$4="(All)","*",$G$4)) | D19: =IFERROR(C19/B19*100,"") | E19: =SUMIFS(Trades!$AD$2:$AD$74,Trades!$D$2:$D$74,$A$19,Trades!$C$2:$C$74,IF($D$4="(All)","*",$D$4),Trades!$AE$2:$AE$74,IF($G$4="(All)","*",$G$4)) | F19: =IFERROR(E19/B19,"") | G19: =IFERROR(AVERAGEIFS(Trades!$Z$2:$Z$74,Trades!$D$2:$D$74,$A$19,Trades!$C$2:$C$74,IF($D$4="(All)","*",$D$4),Trades!$AE$2:$AE$74,IF($G$4="(All)","*",$G$4)),"") | H19: =IFERROR(SUMIFS(Trades!$AD$2:$AD$74,Trades!$D$2:$D$74,$A$19,Trades!$AD$2:$AD$74,">0",Trades!$C$2:$C$74,IF($D$4="(All)","*",$D$4),Trades!$AE$2:$AE$74,IF($G$4="(All)","*",$G$4))/-SUMIFS(Trades!$AD$2:$AD$74,Trades!$D$2:$D$74,$A$19,Trades!$AD$2:$AD$74,"<0",Trades!$C$2:$C$74,IF($D$4="(All)","*",$D$4),Trades!$AE$2:$AE$74,IF($G$4="(All)","*",$G$4)),"") | I19: =IFERROR(AVERAGEIFS(Trades!$AH$2:$AH$74,Trades!$D$2:$D$74,$A$19,Trades!$C$2:$C$74,IF($D$4="(All)","*",$D$4),Trades!$AE$2:$AE$74,IF($G$4="(All)","*",$G$4)),"") | J19: =IFERROR(AVERAGEIFS(Trades!$AI$2:$AI$74,Trades!$D$2:$D$74,$A$19,Trades!$C$2:$C$74,IF($D$4="(All)","*",$D$4),Trades!$AE$2:$AE$74,IF($G$4="(All)","*",$G$4)),"") | K19: =IFERROR(AVERAGEIFS(Trades!$O$2:$O$74,Trades!$D$2:$D$74,$A$19,Trades!$C$2:$C$74,IF($D$4="(All)","*",$D$4),Trades!$AE$2:$AE$74,IF($G$4="(All)","*",$G$4)),"") | L19: =IFERROR(E19/SUMIFS(Trades!$AD$2:$AD$74,Trades!$C$2:$C$74,IF($D$4="(All)","*",$D$4),Trades!$AE$2:$AE$74,IF($G$4="(All)","*",$G$4))*100,"")
A20: All trades | B20: =COUNTIFS(Trades!$C$2:$C$74,IF($D$4="(All)","*",$D$4),Trades!$AE$2:$AE$74,IF($G$4="(All)","*",$G$4)) | C20: =COUNTIFS(Trades!$AE$2:$AE$74,"Win",Trades!$C$2:$C$74,IF($D$4="(All)","*",$D$4),Trades!$AE$2:$AE$74,IF($G$4="(All)","*",$G$4)) | D20: =IFERROR(C20/B20*100,"") | E20: =SUMIFS(Trades!$AD$2:$AD$74,Trades!$C$2:$C$74,IF($D$4="(All)","*",$D$4),Trades!$AE$2:$AE$74,IF($G$4="(All)","*",$G$4)) | F20: =IFERROR(E20/B20,"") | G20: =IFERROR(AVERAGEIFS(Trades!$Z$2:$Z$74,Trades!$C$2:$C$74,IF($D$4="(All)","*",$D$4),Trades!$AE$2:$AE$74,IF($G$4="(All)","*",$G$4)),"") | H20: =IFERROR(SUMIFS(Trades!$AD$2:$AD$74,Trades!$AD$2:$AD$74,">0",Trades!$C$2:$C$74,IF($D$4="(All)","*",$D$4),Trades!$AE$2:$AE$74,IF($G$4="(All)","*",$G$4))/-SUMIFS(Trades!$AD$2:$AD$74,Trades!$AD$2:$AD$74,"<0",Trades!$C$2:$C$74,IF($D$4="(All)","*",$D$4),Trades!$AE$2:$AE$74,IF($G$4="(All)","*",$G$4)),"") | I20: =IFERROR(AVERAGEIFS(Trades!$AH$2:$AH$74,Trades!$C$2:$C$74,IF($D$4="(All)","*",$D$4),Trades!$AE$2:$AE$74,IF($G$4="(All)","*",$G$4)),"") | J20: =IFERROR(AVERAGEIFS(Trades!$AI$2:$AI$74,Trades!$C$2:$C$74,IF($D$4="(All)","*",$D$4),Trades!$AE$2:$AE$74,IF($G$4="(All)","*",$G$4)),"") | K20: =IFERROR(AVERAGEIFS(Trades!$O$2:$O$74,Trades!$C$2:$C$74,IF($D$4="(All)","*",$D$4),Trades!$AE$2:$AE$74,IF($G$4="(All)","*",$G$4)),"") | L20: =IFERROR(E20/SUMIFS(Trades!$AD$2:$AD$74,Trades!$C$2:$C$74,IF($D$4="(All)","*",$D$4),Trades!$AE$2:$AE$74,IF($G$4="(All)","*",$G$4))*100,"")
A23: By exit reason | E23: How trades actually end, versus how they were planned to end.
A24: Exit reason | B24: Trades | C24: Wins | D24: Win % | E24: Net | F24: Expectancy | G24: Avg R | H24: Profit factor | I24: Avg MFE | J24: Avg MAE | K24: Avg dur (min) | L24: Share of net
A25: Expert | B25: =COUNTIFS(Trades!$AF$2:$AF$74,$A$25,Trades!$C$2:$C$74,IF($D$4="(All)","*",$D$4),Trades!$AE$2:$AE$74,IF($G$4="(All)","*",$G$4)) | C25: =COUNTIFS(Trades!$AE$2:$AE$74,"Win",Trades!$AF$2:$AF$74,$A$25,Trades!$C$2:$C$74,IF($D$4="(All)","*",$D$4),Trades!$AE$2:$AE$74,IF($G$4="(All)","*",$G$4)) | D25: =IFERROR(C25/B25*100,"") | E25: =SUMIFS(Trades!$AD$2:$AD$74,Trades!$AF$2:$AF$74,$A$25,Trades!$C$2:$C$74,IF($D$4="(All)","*",$D$4),Trades!$AE$2:$AE$74,IF($G$4="(All)","*",$G$4)) | F25: =IFERROR(E25/B25,"") | G25: =IFERROR(AVERAGEIFS(Trades!$Z$2:$Z$74,Trades!$AF$2:$AF$74,$A$25,Trades!$C$2:$C$74,IF($D$4="(All)","*",$D$4),Trades!$AE$2:$AE$74,IF($G$4="(All)","*",$G$4)),"") | H25: =IFERROR(SUMIFS(Trades!$AD$2:$AD$74,Trades!$AF$2:$AF$74,$A$25,Trades!$AD$2:$AD$74,">0",Trades!$C$2:$C$74,IF($D$4="(All)","*",$D$4),Trades!$AE$2:$AE$74,IF($G$4="(All)","*",$G$4))/-SUMIFS(Trades!$AD$2:$AD$74,Trades!$AF$2:$AF$74,$A$25,Trades!$AD$2:$AD$74,"<0",Trades!$C$2:$C$74,IF($D$4="(All)","*",$D$4),Trades!$AE$2:$AE$74,IF($G$4="(All)","*",$G$4)),"") | I25: =IFERROR(AVERAGEIFS(Trades!$AH$2:$AH$74,Trades!$AF$2:$AF$74,$A$25,Trades!$C$2:$C$74,IF($D$4="(All)","*",$D$4),Trades!$AE$2:$AE$74,IF($G$4="(All)","*",$G$4)),"") | J25: =IFERROR(AVERAGEIFS(Trades!$AI$2:$AI$74,Trades!$AF$2:$AF$74,$A$25,Trades!$C$2:$C$74,IF($D$4="(All)","*",$D$4),Trades!$AE$2:$AE$74,IF($G$4="(All)","*",$G$4)),"") | K25: =IFERROR(AVERAGEIFS(Trades!$O$2:$O$74,Trades!$AF$2:$AF$74,$A$25,Trades!$C$2:$C$74,IF($D$4="(All)","*",$D$4),Trades!$AE$2:$AE$74,IF($G$4="(All)","*",$G$4)),"") | L25: =IFERROR(E25/SUMIFS(Trades!$AD$2:$AD$74,Trades!$C$2:$C$74,IF($D$4="(All)","*",$D$4),Trades!$AE$2:$AE$74,IF($G$4="(All)","*",$G$4))*100,"")
A26: Stop Loss | B26: =COUNTIFS(Trades!$AF$2:$AF$74,$A$26,Trades!$C$2:$C$74,IF($D$4="(All)","*",$D$4),Trades!$AE$2:$AE$74,IF($G$4="(All)","*",$G$4)) | C26: =COUNTIFS(Trades!$AE$2:$AE$74,"Win",Trades!$AF$2:$AF$74,$A$26,Trades!$C$2:$C$74,IF($D$4="(All)","*",$D$4),Trades!$AE$2:$AE$74,IF($G$4="(All)","*",$G$4)) | D26: =IFERROR(C26/B26*100,"") | E26: =SUMIFS(Trades!$AD$2:$AD$74,Trades!$AF$2:$AF$74,$A$26,Trades!$C$2:$C$74,IF($D$4="(All)","*",$D$4),Trades!$AE$2:$AE$74,IF($G$4="(All)","*",$G$4)) | F26: =IFERROR(E26/B26,"") | G26: =IFERROR(AVERAGEIFS(Trades!$Z$2:$Z$74,Trades!$AF$2:$AF$74,$A$26,Trades!$C$2:$C$74,IF($D$4="(All)","*",$D$4),Trades!$AE$2:$AE$74,IF($G$4="(All)","*",$G$4)),"") | H26: =IFERROR(SUMIFS(Trades!$AD$2:$AD$74,Trades!$AF$2:$AF$74,$A$26,Trades!$AD$2:$AD$74,">0",Trades!$C$2:$C$74,IF($D$4="(All)","*",$D$4),Trades!$AE$2:$AE$74,IF($G$4="(All)","*",$G$4))/-SUMIFS(Trades!$AD$2:$AD$74,Trades!$AF$2:$AF$74,$A$26,Trades!$AD$2:$AD$74,"<0",Trades!$C$2:$C$74,IF($D$4="(All)","*",$D$4),Trades!$AE$2:$AE$74,IF($G$4="(All)","*",$G$4)),"") | I26: =IFERROR(AVERAGEIFS(Trades!$AH$2:$AH$74,Trades!$AF$2:$AF$74,$A$26,Trades!$C$2:$C$74,IF($D$4="(All)","*",$D$4),Trades!$AE$2:$AE$74,IF($G$4="(All)","*",$G$4)),"") | J26: =IFERROR(AVERAGEIFS(Trades!$AI$2:$AI$74,Trades!$AF$2:$AF$74,$A$26,Trades!$C$2:$C$74,IF($D$4="(All)","*",$D$4),Trades!$AE$2:$AE$74,IF($G$4="(All)","*",$G$4)),"") | K26: =IFERROR(AVERAGEIFS(Trades!$O$2:$O$74,Trades!$AF$2:$AF$74,$A$26,Trades!$C$2:$C$74,IF($D$4="(All)","*",$D$4),Trades!$AE$2:$AE$74,IF($G$4="(All)","*",$G$4)),"") | L26: =IFERROR(E26/SUMIFS(Trades!$AD$2:$AD$74,Trades!$C$2:$C$74,IF($D$4="(All)","*",$D$4),Trades!$AE$2:$AE$74,IF($G$4="(All)","*",$G$4))*100,"")
A27: Take Profit | B27: =COUNTIFS(Trades!$AF$2:$AF$74,$A$27,Trades!$C$2:$C$74,IF($D$4="(All)","*",$D$4),Trades!$AE$2:$AE$74,IF($G$4="(All)","*",$G$4)) | C27: =COUNTIFS(Trades!$AE$2:$AE$74,"Win",Trades!$AF$2:$AF$74,$A$27,Trades!$C$2:$C$74,IF($D$4="(All)","*",$D$4),Trades!$AE$2:$AE$74,IF($G$4="(All)","*",$G$4)) | D27: =IFERROR(C27/B27*100,"") | E27: =SUMIFS(Trades!$AD$2:$AD$74,Trades!$AF$2:$AF$74,$A$27,Trades!$C$2:$C$74,IF($D$4="(All)","*",$D$4),Trades!$AE$2:$AE$74,IF($G$4="(All)","*",$G$4)) | F27: =IFERROR(E27/B27,"") | G27: =IFERROR(AVERAGEIFS(Trades!$Z$2:$Z$74,Trades!$AF$2:$AF$74,$A$27,Trades!$C$2:$C$74,IF($D$4="(All)","*",$D$4),Trades!$AE$2:$AE$74,IF($G$4="(All)","*",$G$4)),"") | H27: =IFERROR(SUMIFS(Trades!$AD$2:$AD$74,Trades!$AF$2:$AF$74,$A$27,Trades!$AD$2:$AD$74,">0",Trades!$C$2:$C$74,IF($D$4="(All)","*",$D$4),Trades!$AE$2:$AE$74,IF($G$4="(All)","*",$G$4))/-SUMIFS(Trades!$AD$2:$AD$74,Trades!$AF$2:$AF$74,$A$27,Trades!$AD$2:$AD$74,"<0",Trades!$C$2:$C$74,IF($D$4="(All)","*",$D$4),Trades!$AE$2:$AE$74,IF($G$4="(All)","*",$G$4)),"") | I27: =IFERROR(AVERAGEIFS(Trades!$AH$2:$AH$74,Trades!$AF$2:$AF$74,$A$27,Trades!$C$2:$C$74,IF($D$4="(All)","*",$D$4),Trades!$AE$2:$AE$74,IF($G$4="(All)","*",$G$4)),"") | J27: =IFERROR(AVERAGEIFS(Trades!$AI$2:$AI$74,Trades!$AF$2:$AF$74,$A$27,Trades!$C$2:$C$74,IF($D$4="(All)","*",$D$4),Trades!$AE$2:$AE$74,IF($G$4="(All)","*",$G$4)),"") | K27: =IFERROR(AVERAGEIFS(Trades!$O$2:$O$74,Trades!$AF$2:$AF$74,$A$27,Trades!$C$2:$C$74,IF($D$4="(All)","*",$D$4),Trades!$AE$2:$AE$74,IF($G$4="(All)","*",$G$4)),"") | L27: =IFERROR(E27/SUMIFS(Trades!$AD$2:$AD$74,Trades!$C$2:$C$74,IF($D$4="(All)","*",$D$4),Trades!$AE$2:$AE$74,IF($G$4="(All)","*",$G$4))*100,"")
A28: All trades | B28: =COUNTIFS(Trades!$C$2:$C$74,IF($D$4="(All)","*",$D$4),Trades!$AE$2:$AE$74,IF($G$4="(All)","*",$G$4)) | C28: =COUNTIFS(Trades!$AE$2:$AE$74,"Win",Trades!$C$2:$C$74,IF($D$4="(All)","*",$D$4),Trades!$AE$2:$AE$74,IF($G$4="(All)","*",$G$4)) | D28: =IFERROR(C28/B28*100,"") | E28: =SUMIFS(Trades!$AD$2:$AD$74,Trades!$C$2:$C$74,IF($D$4="(All)","*",$D$4),Trades!$AE$2:$AE$74,IF($G$4="(All)","*",$G$4)) | F28: =IFERROR(E28/B28,"") | G28: =IFERROR(AVERAGEIFS(Trades!$Z$2:$Z$74,Trades!$C$2:$C$74,IF($D$4="(All)","*",$D$4),Trades!$AE$2:$AE$74,IF($G$4="(All)","*",$G$4)),"") | H28: =IFERROR(SUMIFS(Trades!$AD$2:$AD$74,Trades!$AD$2:$AD$74,">0",Trades!$C$2:$C$74,IF($D$4="(All)","*",$D$4),Trades!$AE$2:$AE$74,IF($G$4="(All)","*",$G$4))/-SUMIFS(Trades!$AD$2:$AD$74,Trades!$AD$2:$AD$74,"<0",Trades!$C$2:$C$74,IF($D$4="(All)","*",$D$4),Trades!$AE$2:$AE$74,IF($G$4="(All)","*",$G$4)),"") | I28: =IFERROR(AVERAGEIFS(Trades!$AH$2:$AH$74,Trades!$C$2:$C$74,IF($D$4="(All)","*",$D$4),Trades!$AE$2:$AE$74,IF($G$4="(All)","*",$G$4)),"") | J28: =IFERROR(AVERAGEIFS(Trades!$AI$2:$AI$74,Trades!$C$2:$C$74,IF($D$4="(All)","*",$D$4),Trades!$AE$2:$AE$74,IF($G$4="(All)","*",$G$4)),"") | K28: =IFERROR(AVERAGEIFS(Trades!$O$2:$O$74,Trades!$C$2:$C$74,IF($D$4="(All)","*",$D$4),Trades!$AE$2:$AE$74,IF($G$4="(All)","*",$G$4)),"") | L28: =IFERROR(E28/SUMIFS(Trades!$AD$2:$AD$74,Trades!$C$2:$C$74,IF($D$4="(All)","*",$D$4),Trades!$AE$2:$AE$74,IF($G$4="(All)","*",$G$4))*100,"")
A31: By sl moved | E31: Whether moving a stop after entry helped or cost.
A32: SL moved | B32: Trades | C32: Wins | D32: Win % | E32: Net | F32: Expectancy | G32: Avg R | H32: Profit factor | I32: Avg MFE | J32: Avg MAE | K32: Avg dur (min) | L32: Share of net
A33: Breakeven | B33: =COUNTIFS(Trades!$V$2:$V$74,$A$33,Trades!$C$2:$C$74,IF($D$4="(All)","*",$D$4),Trades!$AE$2:$AE$74,IF($G$4="(All)","*",$G$4)) | C33: =COUNTIFS(Trades!$AE$2:$AE$74,"Win",Trades!$V$2:$V$74,$A$33,Trades!$C$2:$C$74,IF($D$4="(All)","*",$D$4),Trades!$AE$2:$AE$74,IF($G$4="(All)","*",$G$4)) | D33: =IFERROR(C33/B33*100,"") | E33: =SUMIFS(Trades!$AD$2:$AD$74,Trades!$V$2:$V$74,$A$33,Trades!$C$2:$C$74,IF($D$4="(All)","*",$D$4),Trades!$AE$2:$AE$74,IF($G$4="(All)","*",$G$4)) | F33: =IFERROR(E33/B33,"") | G33: =IFERROR(AVERAGEIFS(Trades!$Z$2:$Z$74,Trades!$V$2:$V$74,$A$33,Trades!$C$2:$C$74,IF($D$4="(All)","*",$D$4),Trades!$AE$2:$AE$74,IF($G$4="(All)","*",$G$4)),"") | H33: =IFERROR(SUMIFS(Trades!$AD$2:$AD$74,Trades!$V$2:$V$74,$A$33,Trades!$AD$2:$AD$74,">0",Trades!$C$2:$C$74,IF($D$4="(All)","*",$D$4),Trades!$AE$2:$AE$74,IF($G$4="(All)","*",$G$4))/-SUMIFS(Trades!$AD$2:$AD$74,Trades!$V$2:$V$74,$A$33,Trades!$AD$2:$AD$74,"<0",Trades!$C$2:$C$74,IF($D$4="(All)","*",$D$4),Trades!$AE$2:$AE$74,IF($G$4="(All)","*",$G$4)),"") | I33: =IFERROR(AVERAGEIFS(Trades!$AH$2:$AH$74,Trades!$V$2:$V$74,$A$33,Trades!$C$2:$C$74,IF($D$4="(All)","*",$D$4),Trades!$AE$2:$AE$74,IF($G$4="(All)","*",$G$4)),"") | J33: =IFERROR(AVERAGEIFS(Trades!$AI$2:$AI$74,Trades!$V$2:$V$74,$A$33,Trades!$C$2:$C$74,IF($D$4="(All)","*",$D$4),Trades!$AE$2:$AE$74,IF($G$4="(All)","*",$G$4)),"") | K33: =IFERROR(AVERAGEIFS(Trades!$O$2:$O$74,Trades!$V$2:$V$74,$A$33,Trades!$C$2:$C$74,IF($D$4="(All)","*",$D$4),Trades!$AE$2:$AE$74,IF($G$4="(All)","*",$G$4)),"") | L33: =IFERROR(E33/SUMIFS(Trades!$AD$2:$AD$74,Trades!$C$2:$C$74,IF($D$4="(All)","*",$D$4),Trades!$AE$2:$AE$74,IF($G$4="(All)","*",$G$4))*100,"")
A34: Tightened | B34: =COUNTIFS(Trades!$V$2:$V$74,$A$34,Trades!$C$2:$C$74,IF($D$4="(All)","*",$D$4),Trades!$AE$2:$AE$74,IF($G$4="(All)","*",$G$4)) | C34: =COUNTIFS(Trades!$AE$2:$AE$74,"Win",Trades!$V$2:$V$74,$A$34,Trades!$C$2:$C$74,IF($D$4="(All)","*",$D$4),Trades!$AE$2:$AE$74,IF($G$4="(All)","*",$G$4)) | D34: =IFERROR(C34/B34*100,"") | E34: =SUMIFS(Trades!$AD$2:$AD$74,Trades!$V$2:$V$74,$A$34,Trades!$C$2:$C$74,IF($D$4="(All)","*",$D$4),Trades!$AE$2:$AE$74,IF($G$4="(All)","*",$G$4)) | F34: =IFERROR(E34/B34,"") | G34: =IFERROR(AVERAGEIFS(Trades!$Z$2:$Z$74,Trades!$V$2:$V$74,$A$34,Trades!$C$2:$C$74,IF($D$4="(All)","*",$D$4),Trades!$AE$2:$AE$74,IF($G$4="(All)","*",$G$4)),"") | H34: =IFERROR(SUMIFS(Trades!$AD$2:$AD$74,Trades!$V$2:$V$74,$A$34,Trades!$AD$2:$AD$74,">0",Trades!$C$2:$C$74,IF($D$4="(All)","*",$D$4),Trades!$AE$2:$AE$74,IF($G$4="(All)","*",$G$4))/-SUMIFS(Trades!$AD$2:$AD$74,Trades!$V$2:$V$74,$A$34,Trades!$AD$2:$AD$74,"<0",Trades!$C$2:$C$74,IF($D$4="(All)","*",$D$4),Trades!$AE$2:$AE$74,IF($G$4="(All)","*",$G$4)),"") | I34: =IFERROR(AVERAGEIFS(Trades!$AH$2:$AH$74,Trades!$V$2:$V$74,$A$34,Trades!$C$2:$C$74,IF($D$4="(All)","*",$D$4),Trades!$AE$2:$AE$74,IF($G$4="(All)","*",$G$4)),"") | J34: =IFERROR(AVERAGEIFS(Trades!$AI$2:$AI$74,Trades!$V$2:$V$74,$A$34,Trades!$C$2:$C$74,IF($D$4="(All)","*",$D$4),Trades!$AE$2:$AE$74,IF($G$4="(All)","*",$G$4)),"") | K34: =IFERROR(AVERAGEIFS(Trades!$O$2:$O$74,Trades!$V$2:$V$74,$A$34,Trades!$C$2:$C$74,IF($D$4="(All)","*",$D$4),Trades!$AE$2:$AE$74,IF($G$4="(All)","*",$G$4)),"") | L34: =IFERROR(E34/SUMIFS(Trades!$AD$2:$AD$74,Trades!$C$2:$C$74,IF($D$4="(All)","*",$D$4),Trades!$AE$2:$AE$74,IF($G$4="(All)","*",$G$4))*100,"")
A35: Unchanged | B35: =COUNTIFS(Trades!$V$2:$V$74,$A$35,Trades!$C$2:$C$74,IF($D$4="(All)","*",$D$4),Trades!$AE$2:$AE$74,IF($G$4="(All)","*",$G$4)) | C35: =COUNTIFS(Trades!$AE$2:$AE$74,"Win",Trades!$V$2:$V$74,$A$35,Trades!$C$2:$C$74,IF($D$4="(All)","*",$D$4),Trades!$AE$2:$AE$74,IF($G$4="(All)","*",$G$4)) | D35: =IFERROR(C35/B35*100,"") | E35: =SUMIFS(Trades!$AD$2:$AD$74,Trades!$V$2:$V$74,$A$35,Trades!$C$2:$C$74,IF($D$4="(All)","*",$D$4),Trades!$AE$2:$AE$74,IF($G$4="(All)","*",$G$4)) | F35: =IFERROR(E35/B35,"") | G35: =IFERROR(AVERAGEIFS(Trades!$Z$2:$Z$74,Trades!$V$2:$V$74,$A$35,Trades!$C$2:$C$74,IF($D$4="(All)","*",$D$4),Trades!$AE$2:$AE$74,IF($G$4="(All)","*",$G$4)),"") | H35: =IFERROR(SUMIFS(Trades!$AD$2:$AD$74,Trades!$V$2:$V$74,$A$35,Trades!$AD$2:$AD$74,">0",Trades!$C$2:$C$74,IF($D$4="(All)","*",$D$4),Trades!$AE$2:$AE$74,IF($G$4="(All)","*",$G$4))/-SUMIFS(Trades!$AD$2:$AD$74,Trades!$V$2:$V$74,$A$35,Trades!$AD$2:$AD$74,"<0",Trades!$C$2:$C$74,IF($D$4="(All)","*",$D$4),Trades!$AE$2:$AE$74,IF($G$4="(All)","*",$G$4)),"") | I35: =IFERROR(AVERAGEIFS(Trades!$AH$2:$AH$74,Trades!$V$2:$V$74,$A$35,Trades!$C$2:$C$74,IF($D$4="(All)","*",$D$4),Trades!$AE$2:$AE$74,IF($G$4="(All)","*",$G$4)),"") | J35: =IFERROR(AVERAGEIFS(Trades!$AI$2:$AI$74,Trades!$V$2:$V$74,$A$35,Trades!$C$2:$C$74,IF($D$4="(All)","*",$D$4),Trades!$AE$2:$AE$74,IF($G$4="(All)","*",$G$4)),"") | K35: =IFERROR(AVERAGEIFS(Trades!$O$2:$O$74,Trades!$V$2:$V$74,$A$35,Trades!$C$2:$C$74,IF($D$4="(All)","*",$D$4),Trades!$AE$2:$AE$74,IF($G$4="(All)","*",$G$4)),"") | L35: =IFERROR(E35/SUMIFS(Trades!$AD$2:$AD$74,Trades!$C$2:$C$74,IF($D$4="(All)","*",$D$4),Trades!$AE$2:$AE$74,IF($G$4="(All)","*",$G$4))*100,"")
A36: Widened | B36: =COUNTIFS(Trades!$V$2:$V$74,$A$36,Trades!$C$2:$C$74,IF($D$4="(All)","*",$D$4),Trades!$AE$2:$AE$74,IF($G$4="(All)","*",$G$4)) | C36: =COUNTIFS(Trades!$AE$2:$AE$74,"Win",Trades!$V$2:$V$74,$A$36,Trades!$C$2:$C$74,IF($D$4="(All)","*",$D$4),Trades!$AE$2:$AE$74,IF($G$4="(All)","*",$G$4)) | D36: =IFERROR(C36/B36*100,"") | E36: =SUMIFS(Trades!$AD$2:$AD$74,Trades!$V$2:$V$74,$A$36,Trades!$C$2:$C$74,IF($D$4="(All)","*",$D$4),Trades!$AE$2:$AE$74,IF($G$4="(All)","*",$G$4)) | F36: =IFERROR(E36/B36,"") | G36: =IFERROR(AVERAGEIFS(Trades!$Z$2:$Z$74,Trades!$V$2:$V$74,$A$36,Trades!$C$2:$C$74,IF($D$4="(All)","*",$D$4),Trades!$AE$2:$AE$74,IF($G$4="(All)","*",$G$4)),"") | H36: =IFERROR(SUMIFS(Trades!$AD$2:$AD$74,Trades!$V$2:$V$74,$A$36,Trades!$AD$2:$AD$74,">0",Trades!$C$2:$C$74,IF($D$4="(All)","*",$D$4),Trades!$AE$2:$AE$74,IF($G$4="(All)","*",$G$4))/-SUMIFS(Trades!$AD$2:$AD$74,Trades!$V$2:$V$74,$A$36,Trades!$AD$2:$AD$74,"<0",Trades!$C$2:$C$74,IF($D$4="(All)","*",$D$4),Trades!$AE$2:$AE$74,IF($G$4="(All)","*",$G$4)),"") | I36: =IFERROR(AVERAGEIFS(Trades!$AH$2:$AH$74,Trades!$V$2:$V$74,$A$36,Trades!$C$2:$C$74,IF($D$4="(All)","*",$D$4),Trades!$AE$2:$AE$74,IF($G$4="(All)","*",$G$4)),"") | J36: =IFERROR(AVERAGEIFS(Trades!$AI$2:$AI$74,Trades!$V$2:$V$74,$A$36,Trades!$C$2:$C$74,IF($D$4="(All)","*",$D$4),Trades!$AE$2:$AE$74,IF($G$4="(All)","*",$G$4)),"") | K36: =IFERROR(AVERAGEIFS(Trades!$O$2:$O$74,Trades!$V$2:$V$74,$A$36,Trades!$C$2:$C$74,IF($D$4="(All)","*",$D$4),Trades!$AE$2:$AE$74,IF($G$4="(All)","*",$G$4)),"") | L36: =IFERROR(E36/SUMIFS(Trades!$AD$2:$AD$74,Trades!$C$2:$C$74,IF($D$4="(All)","*",$D$4),Trades!$AE$2:$AE$74,IF($G$4="(All)","*",$G$4))*100,"")
A37: All trades | B37: =COUNTIFS(Trades!$C$2:$C$74,IF($D$4="(All)","*",$D$4),Trades!$AE$2:$AE$74,IF($G$4="(All)","*",$G$4)) | C37: =COUNTIFS(Trades!$AE$2:$AE$74,"Win",Trades!$C$2:$C$74,IF($D$4="(All)","*",$D$4),Trades!$AE$2:$AE$74,IF($G$4="(All)","*",$G$4)) | D37: =IFERROR(C37/B37*100,"") | E37: =SUMIFS(Trades!$AD$2:$AD$74,Trades!$C$2:$C$74,IF($D$4="(All)","*",$D$4),Trades!$AE$2:$AE$74,IF($G$4="(All)","*",$G$4)) | F37: =IFERROR(E37/B37,"") | G37: =IFERROR(AVERAGEIFS(Trades!$Z$2:$Z$74,Trades!$C$2:$C$74,IF($D$4="(All)","*",$D$4),Trades!$AE$2:$AE$74,IF($G$4="(All)","*",$G$4)),"") | H37: =IFERROR(SUMIFS(Trades!$AD$2:$AD$74,Trades!$AD$2:$AD$74,">0",Trades!$C$2:$C$74,IF($D$4="(All)","*",$D$4),Trades!$AE$2:$AE$74,IF($G$4="(All)","*",$G$4))/-SUMIFS(Trades!$AD$2:$AD$74,Trades!$AD$2:$AD$74,"<0",Trades!$C$2:$C$74,IF($D$4="(All)","*",$D$4),Trades!$AE$2:$AE$74,IF($G$4="(All)","*",$G$4)),"") | I37: =IFERROR(AVERAGEIFS(Trades!$AH$2:$AH$74,Trades!$C$2:$C$74,IF($D$4="(All)","*",$D$4),Trades!$AE$2:$AE$74,IF($G$4="(All)","*",$G$4)),"") | J37: =IFERROR(AVERAGEIFS(Trades!$AI$2:$AI$74,Trades!$C$2:$C$74,IF($D$4="(All)","*",$D$4),Trades!$AE$2:$AE$74,IF($G$4="(All)","*",$G$4)),"") | K37: =IFERROR(AVERAGEIFS(Trades!$O$2:$O$74,Trades!$C$2:$C$74,IF($D$4="(All)","*",$D$4),Trades!$AE$2:$AE$74,IF($G$4="(All)","*",$G$4)),"") | L37: =IFERROR(E37/SUMIFS(Trades!$AD$2:$AD$74,Trades!$C$2:$C$74,IF($D$4="(All)","*",$D$4),Trades!$AE$2:$AE$74,IF($G$4="(All)","*",$G$4))*100,"")

Sheet Timing
A1: When the edge shows up
A2: Same grids, cut by clock and calendar. Broker server time throughout.
A4: Filters | C4: Symbol | D4: (All) | F4: Outcome | G4: (All) | I4: Change either dropdown - every grid below recalculates.
A6: By session | E6: Sessions come from settings, in broker hours.
A7: Session | B7: Trades | C7: Wins | D7: Win % | E7: Net | F7: Expectancy | G7: Avg R | H7: Profit factor | I7: Avg MFE | J7: Avg MAE | K7: Avg dur (min) | L7: Share of net
A8: Asia | B8: =COUNTIFS(Trades!$J$2:$J$74,$A$8,Trades!$C$2:$C$74,IF($D$4="(All)","*",$D$4),Trades!$AE$2:$AE$74,IF($G$4="(All)","*",$G$4)) | C8: =COUNTIFS(Trades!$AE$2:$AE$74,"Win",Trades!$J$2:$J$74,$A$8,Trades!$C$2:$C$74,IF($D$4="(All)","*",$D$4),Trades!$AE$2:$AE$74,IF($G$4="(All)","*",$G$4)) | D8: =IFERROR(C8/B8*100,"") | E8: =SUMIFS(Trades!$AD$2:$AD$74,Trades!$J$2:$J$74,$A$8,Trades!$C$2:$C$74,IF($D$4="(All)","*",$D$4),Trades!$AE$2:$AE$74,IF($G$4="(All)","*",$G$4)) | F8: =IFERROR(E8/B8,"") | G8: =IFERROR(AVERAGEIFS(Trades!$Z$2:$Z$74,Trades!$J$2:$J$74,$A$8,Trades!$C$2:$C$74,IF($D$4="(All)","*",$D$4),Trades!$AE$2:$AE$74,IF($G$4="(All)","*",$G$4)),"") | H8: =IFERROR(SUMIFS(Trades!$AD$2:$AD$74,Trades!$J$2:$J$74,$A$8,Trades!$AD$2:$AD$74,">0",Trades!$C$2:$C$74,IF($D$4="(All)","*",$D$4),Trades!$AE$2:$AE$74,IF($G$4="(All)","*",$G$4))/-SUMIFS(Trades!$AD$2:$AD$74,Trades!$J$2:$J$74,$A$8,Trades!$AD$2:$AD$74,"<0",Trades!$C$2:$C$74,IF($D$4="(All)","*",$D$4),Trades!$AE$2:$AE$74,IF($G$4="(All)","*",$G$4)),"") | I8: =IFERROR(AVERAGEIFS(Trades!$AH$2:$AH$74,Trades!$J$2:$J$74,$A$8,Trades!$C$2:$C$74,IF($D$4="(All)","*",$D$4),Trades!$AE$2:$AE$74,IF($G$4="(All)","*",$G$4)),"") | J8: =IFERROR(AVERAGEIFS(Trades!$AI$2:$AI$74,Trades!$J$2:$J$74,$A$8,Trades!$C$2:$C$74,IF($D$4="(All)","*",$D$4),Trades!$AE$2:$AE$74,IF($G$4="(All)","*",$G$4)),"") | K8: =IFERROR(AVERAGEIFS(Trades!$O$2:$O$74,Trades!$J$2:$J$74,$A$8,Trades!$C$2:$C$74,IF($D$4="(All)","*",$D$4),Trades!$AE$2:$AE$74,IF($G$4="(All)","*",$G$4)),"") | L8: =IFERROR(E8/SUMIFS(Trades!$AD$2:$AD$74,Trades!$C$2:$C$74,IF($D$4="(All)","*",$D$4),Trades!$AE$2:$AE$74,IF($G$4="(All)","*",$G$4))*100,"")
A9: London | B9: =COUNTIFS(Trades!$J$2:$J$74,$A$9,Trades!$C$2:$C$74,IF($D$4="(All)","*",$D$4),Trades!$AE$2:$AE$74,IF($G$4="(All)","*",$G$4)) | C9: =COUNTIFS(Trades!$AE$2:$AE$74,"Win",Trades!$J$2:$J$74,$A$9,Trades!$C$2:$C$74,IF($D$4="(All)","*",$D$4),Trades!$AE$2:$AE$74,IF($G$4="(All)","*",$G$4)) | D9: =IFERROR(C9/B9*100,"") | E9: =SUMIFS(Trades!$AD$2:$AD$74,Trades!$J$2:$J$74,$A$9,Trades!$C$2:$C$74,IF($D$4="(All)","*",$D$4),Trades!$AE$2:$AE$74,IF($G$4="(All)","*",$G$4)) | F9: =IFERROR(E9/B9,"") | G9: =IFERROR(AVERAGEIFS(Trades!$Z$2:$Z$74,Trades!$J$2:$J$74,$A$9,Trades!$C$2:$C$74,IF($D$4="(All)","*",$D$4),Trades!$AE$2:$AE$74,IF($G$4="(All)","*",$G$4)),"") | H9: =IFERROR(SUMIFS(Trades!$AD$2:$AD$74,Trades!$J$2:$J$74,$A$9,Trades!$AD$2:$AD$74,">0",Trades!$C$2:$C$74,IF($D$4="(All)","*",$D$4),Trades!$AE$2:$AE$74,IF($G$4="(All)","*",$G$4))/-SUMIFS(Trades!$AD$2:$AD$74,Trades!$J$2:$J$74,$A$9,Trades!$AD$2:$AD$74,"<0",Trades!$C$2:$C$74,IF($D$4="(All)","*",$D$4),Trades!$AE$2:$AE$74,IF($G$4="(All)","*",$G$4)),"") | I9: =IFERROR(AVERAGEIFS(Trades!$AH$2:$AH$74,Trades!$J$2:$J$74,$A$9,Trades!$C$2:$C$74,IF($D$4="(All)","*",$D$4),Trades!$AE$2:$AE$74,IF($G$4="(All)","*",$G$4)),"") | J9: =IFERROR(AVERAGEIFS(Trades!$AI$2:$AI$74,Trades!$J$2:$J$74,$A$9,Trades!$C$2:$C$74,IF($D$4="(All)","*",$D$4),Trades!$AE$2:$AE$74,IF($G$4="(All)","*",$G$4)),"") | K9: =IFERROR(AVERAGEIFS(Trades!$O$2:$O$74,Trades!$J$2:$J$74,$A$9,Trades!$C$2:$C$74,IF($D$4="(All)","*",$D$4),Trades!$AE$2:$AE$74,IF($G$4="(All)","*",$G$4)),"") | L9: =IFERROR(E9/SUMIFS(Trades!$AD$2:$AD$74,Trades!$C$2:$C$74,IF($D$4="(All)","*",$D$4),Trades!$AE$2:$AE$74,IF($G$4="(All)","*",$G$4))*100,"")
A10: NY Late | B10: =COUNTIFS(Trades!$J$2:$J$74,$A$10,Trades!$C$2:$C$74,IF($D$4="(All)","*",$D$4),Trades!$AE$2:$AE$74,IF($G$4="(All)","*",$G$4)) | C10: =COUNTIFS(Trades!$AE$2:$AE$74,"Win",Trades!$J$2:$J$74,$A$10,Trades!$C$2:$C$74,IF($D$4="(All)","*",$D$4),Trades!$AE$2:$AE$74,IF($G$4="(All)","*",$G$4)) | D10: =IFERROR(C10/B10*100,"") | E10: =SUMIFS(Trades!$AD$2:$AD$74,Trades!$J$2:$J$74,$A$10,Trades!$C$2:$C$74,IF($D$4="(All)","*",$D$4),Trades!$AE$2:$AE$74,IF($G$4="(All)","*",$G$4)) | F10: =IFERROR(E10/B10,"") | G10: =IFERROR(AVERAGEIFS(Trades!$Z$2:$Z$74,Trades!$J$2:$J$74,$A$10,Trades!$C$2:$C$74,IF($D$4="(All)","*",$D$4),Trades!$AE$2:$AE$74,IF($G$4="(All)","*",$G$4)),"") | H10: =IFERROR(SUMIFS(Trades!$AD$2:$AD$74,Trades!$J$2:$J$74,$A$10,Trades!$AD$2:$AD$74,">0",Trades!$C$2:$C$74,IF($D$4="(All)","*",$D$4),Trades!$AE$2:$AE$74,IF($G$4="(All)","*",$G$4))/-SUMIFS(Trades!$AD$2:$AD$74,Trades!$J$2:$J$74,$A$10,Trades!$AD$2:$AD$74,"<0",Trades!$C$2:$C$74,IF($D$4="(All)","*",$D$4),Trades!$AE$2:$AE$74,IF($G$4="(All)","*",$G$4)),"") | I10: =IFERROR(AVERAGEIFS(Trades!$AH$2:$AH$74,Trades!$J$2:$J$74,$A$10,Trades!$C$2:$C$74,IF($D$4="(All)","*",$D$4),Trades!$AE$2:$AE$74,IF($G$4="(All)","*",$G$4)),"") | J10: =IFERROR(AVERAGEIFS(Trades!$AI$2:$AI$74,Trades!$J$2:$J$74,$A$10,Trades!$C$2:$C$74,IF($D$4="(All)","*",$D$4),Trades!$AE$2:$AE$74,IF($G$4="(All)","*",$G$4)),"") | K10: =IFERROR(AVERAGEIFS(Trades!$O$2:$O$74,Trades!$J$2:$J$74,$A$10,Trades!$C$2:$C$74,IF($D$4="(All)","*",$D$4),Trades!$AE$2:$AE$74,IF($G$4="(All)","*",$G$4)),"") | L10: =IFERROR(E10/SUMIFS(Trades!$AD$2:$AD$74,Trades!$C$2:$C$74,IF($D$4="(All)","*",$D$4),Trades!$AE$2:$AE$74,IF($G$4="(All)","*",$G$4))*100,"")
A11: NY Overlap | B11: =COUNTIFS(Trades!$J$2:$J$74,$A$11,Trades!$C$2:$C$74,IF($D$4="(All)","*",$D$4),Trades!$AE$2:$AE$74,IF($G$4="(All)","*",$G$4)) | C11: =COUNTIFS(Trades!$AE$2:$AE$74,"Win",Trades!$J$2:$J$74,$A$11,Trades!$C$2:$C$74,IF($D$4="(All)","*",$D$4),Trades!$AE$2:$AE$74,IF($G$4="(All)","*",$G$4)) | D11: =IFERROR(C11/B11*100,"") | E11: =SUMIFS(Trades!$AD$2:$AD$74,Trades!$J$2:$J$74,$A$11,Trades!$C$2:$C$74,IF($D$4="(All)","*",$D$4),Trades!$AE$2:$AE$74,IF($G$4="(All)","*",$G$4)) | F11: =IFERROR(E11/B11,"") | G11: =IFERROR(AVERAGEIFS(Trades!$Z$2:$Z$74,Trades!$J$2:$J$74,$A$11,Trades!$C$2:$C$74,IF($D$4="(All)","*",$D$4),Trades!$AE$2:$AE$74,IF($G$4="(All)","*",$G$4)),"") | H11: =IFERROR(SUMIFS(Trades!$AD$2:$AD$74,Trades!$J$2:$J$74,$A$11,Trades!$AD$2:$AD$74,">0",Trades!$C$2:$C$74,IF($D$4="(All)","*",$D$4),Trades!$AE$2:$AE$74,IF($G$4="(All)","*",$G$4))/-SUMIFS(Trades!$AD$2:$AD$74,Trades!$J$2:$J$74,$A$11,Trades!$AD$2:$AD$74,"<0",Trades!$C$2:$C$74,IF($D$4="(All)","*",$D$4),Trades!$AE$2:$AE$74,IF($G$4="(All)","*",$G$4)),"") | I11: =IFERROR(AVERAGEIFS(Trades!$AH$2:$AH$74,Trades!$J$2:$J$74,$A$11,Trades!$C$2:$C$74,IF($D$4="(All)","*",$D$4),Trades!$AE$2:$AE$74,IF($G$4="(All)","*",$G$4)),"") | J11: =IFERROR(AVERAGEIFS(Trades!$AI$2:$AI$74,Trades!$J$2:$J$74,$A$11,Trades!$C$2:$C$74,IF($D$4="(All)","*",$D$4),Trades!$AE$2:$AE$74,IF($G$4="(All)","*",$G$4)),"") | K11: =IFERROR(AVERAGEIFS(Trades!$O$2:$O$74,Trades!$J$2:$J$74,$A$11,Trades!$C$2:$C$74,IF($D$4="(All)","*",$D$4),Trades!$AE$2:$AE$74,IF($G$4="(All)","*",$G$4)),"") | L11: =IFERROR(E11/SUMIFS(Trades!$AD$2:$AD$74,Trades!$C$2:$C$74,IF($D$4="(All)","*",$D$4),Trades!$AE$2:$AE$74,IF($G$4="(All)","*",$G$4))*100,"")
A12: All trades | B12: =COUNTIFS(Trades!$C$2:$C$74,IF($D$4="(All)","*",$D$4),Trades!$AE$2:$AE$74,IF($G$4="(All)","*",$G$4)) | C12: =COUNTIFS(Trades!$AE$2:$AE$74,"Win",Trades!$C$2:$C$74,IF($D$4="(All)","*",$D$4),Trades!$AE$2:$AE$74,IF($G$4="(All)","*",$G$4)) | D12: =IFERROR(C12/B12*100,"") | E12: =SUMIFS(Trades!$AD$2:$AD$74,Trades!$C$2:$C$74,IF($D$4="(All)","*",$D$4),Trades!$AE$2:$AE$74,IF($G$4="(All)","*",$G$4)) | F12: =IFERROR(E12/B12,"") | G12: =IFERROR(AVERAGEIFS(Trades!$Z$2:$Z$74,Trades!$C$2:$C$74,IF($D$4="(All)","*",$D$4),Trades!$AE$2:$AE$74,IF($G$4="(All)","*",$G$4)),"") | H12: =IFERROR(SUMIFS(Trades!$AD$2:$AD$74,Trades!$AD$2:$AD$74,">0",Trades!$C$2:$C$74,IF($D$4="(All)","*",$D$4),Trades!$AE$2:$AE$74,IF($G$4="(All)","*",$G$4))/-SUMIFS(Trades!$AD$2:$AD$74,Trades!$AD$2:$AD$74,"<0",Trades!$C$2:$C$74,IF($D$4="(All)","*",$D$4),Trades!$AE$2:$AE$74,IF($G$4="(All)","*",$G$4)),"") | I12: =IFERROR(AVERAGEIFS(Trades!$AH$2:$AH$74,Trades!$C$2:$C$74,IF($D$4="(All)","*",$D$4),Trades!$AE$2:$AE$74,IF($G$4="(All)","*",$G$4)),"") | J12: =IFERROR(AVERAGEIFS(Trades!$AI$2:$AI$74,Trades!$C$2:$C$74,IF($D$4="(All)","*",$D$4),Trades!$AE$2:$AE$74,IF($G$4="(All)","*",$G$4)),"") | K12: =IFERROR(AVERAGEIFS(Trades!$O$2:$O$74,Trades!$C$2:$C$74,IF($D$4="(All)","*",$D$4),Trades!$AE$2:$AE$74,IF($G$4="(All)","*",$G$4)),"") | L12: =IFERROR(E12/SUMIFS(Trades!$AD$2:$AD$74,Trades!$C$2:$C$74,IF($D$4="(All)","*",$D$4),Trades!$AE$2:$AE$74,IF($G$4="(All)","*",$G$4))*100,"")
A15: By weekday
A16: Weekday | B16: Trades | C16: Wins | D16: Win % | E16: Net | F16: Expectancy | G16: Avg R | H16: Profit factor | I16: Avg MFE | J16: Avg MAE | K16: Avg dur (min) | L16: Share of net
A17: Friday | B17: =COUNTIFS(Trades!$H$2:$H$74,$A$17,Trades!$C$2:$C$74,IF($D$4="(All)","*",$D$4),Trades!$AE$2:$AE$74,IF($G$4="(All)","*",$G$4)) | C17: =COUNTIFS(Trades!$AE$2:$AE$74,"Win",Trades!$H$2:$H$74,$A$17,Trades!$C$2:$C$74,IF($D$4="(All)","*",$D$4),Trades!$AE$2:$AE$74,IF($G$4="(All)","*",$G$4)) | D17: =IFERROR(C17/B17*100,"") | E17: =SUMIFS(Trades!$AD$2:$AD$74,Trades!$H$2:$H$74,$A$17,Trades!$C$2:$C$74,IF($D$4="(All)","*",$D$4),Trades!$AE$2:$AE$74,IF($G$4="(All)","*",$G$4)) | F17: =IFERROR(E17/B17,"") | G17: =IFERROR(AVERAGEIFS(Trades!$Z$2:$Z$74,Trades!$H$2:$H$74,$A$17,Trades!$C$2:$C$74,IF($D$4="(All)","*",$D$4),Trades!$AE$2:$AE$74,IF($G$4="(All)","*",$G$4)),"") | H17: =IFERROR(SUMIFS(Trades!$AD$2:$AD$74,Trades!$H$2:$H$74,$A$17,Trades!$AD$2:$AD$74,">0",Trades!$C$2:$C$74,IF($D$4="(All)","*",$D$4),Trades!$AE$2:$AE$74,IF($G$4="(All)","*",$G$4))/-SUMIFS(Trades!$AD$2:$AD$74,Trades!$H$2:$H$74,$A$17,Trades!$AD$2:$AD$74,"<0",Trades!$C$2:$C$74,IF($D$4="(All)","*",$D$4),Trades!$AE$2:$AE$74,IF($G$4="(All)","*",$G$4)),"") | I17: =IFERROR(AVERAGEIFS(Trades!$AH$2:$AH$74,Trades!$H$2:$H$74,$A$17,Trades!$C$2:$C$74,IF($D$4="(All)","*",$D$4),Trades!$AE$2:$AE$74,IF($G$4="(All)","*",$G$4)),"") | J17: =IFERROR(AVERAGEIFS(Trades!$AI$2:$AI$74,Trades!$H$2:$H$74,$A$17,Trades!$C$2:$C$74,IF($D$4="(All)","*",$D$4),Trades!$AE$2:$AE$74,IF($G$4="(All)","*",$G$4)),"") | K17: =IFERROR(AVERAGEIFS(Trades!$O$2:$O$74,Trades!$H$2:$H$74,$A$17,Trades!$C$2:$C$74,IF($D$4="(All)","*",$D$4),Trades!$AE$2:$AE$74,IF($G$4="(All)","*",$G$4)),"") | L17: =IFERROR(E17/SUMIFS(Trades!$AD$2:$AD$74,Trades!$C$2:$C$74,IF($D$4="(All)","*",$D$4),Trades!$AE$2:$AE$74,IF($G$4="(All)","*",$G$4))*100,"")
A18: Monday | B18: =COUNTIFS(Trades!$H$2:$H$74,$A$18,Trades!$C$2:$C$74,IF($D$4="(All)","*",$D$4),Trades!$AE$2:$AE$74,IF($G$4="(All)","*",$G$4)) | C18: =COUNTIFS(Trades!$AE$2:$AE$74,"Win",Trades!$H$2:$H$74,$A$18,Trades!$C$2:$C$74,IF($D$4="(All)","*",$D$4),Trades!$AE$2:$AE$74,IF($G$4="(All)","*",$G$4)) | D18: =IFERROR(C18/B18*100,"") | E18: =SUMIFS(Trades!$AD$2:$AD$74,Trades!$H$2:$H$74,$A$18,Trades!$C$2:$C$74,IF($D$4="(All)","*",$D$4),Trades!$AE$2:$AE$74,IF($G$4="(All)","*",$G$4)) | F18: =IFERROR(E18/B18,"") | G18: =IFERROR(AVERAGEIFS(Trades!$Z$2:$Z$74,Trades!$H$2:$H$74,$A$18,Trades!$C$2:$C$74,IF($D$4="(All)","*",$D$4),Trades!$AE$2:$AE$74,IF($G$4="(All)","*",$G$4)),"") | H18: =IFERROR(SUMIFS(Trades!$AD$2:$AD$74,Trades!$H$2:$H$74,$A$18,Trades!$AD$2:$AD$74,">0",Trades!$C$2:$C$74,IF($D$4="(All)","*",$D$4),Trades!$AE$2:$AE$74,IF($G$4="(All)","*",$G$4))/-SUMIFS(Trades!$AD$2:$AD$74,Trades!$H$2:$H$74,$A$18,Trades!$AD$2:$AD$74,"<0",Trades!$C$2:$C$74,IF($D$4="(All)","*",$D$4),Trades!$AE$2:$AE$74,IF($G$4="(All)","*",$G$4)),"") | I18: =IFERROR(AVERAGEIFS(Trades!$AH$2:$AH$74,Trades!$H$2:$H$74,$A$18,Trades!$C$2:$C$74,IF($D$4="(All)","*",$D$4),Trades!$AE$2:$AE$74,IF($G$4="(All)","*",$G$4)),"") | J18: =IFERROR(AVERAGEIFS(Trades!$AI$2:$AI$74,Trades!$H$2:$H$74,$A$18,Trades!$C$2:$C$74,IF($D$4="(All)","*",$D$4),Trades!$AE$2:$AE$74,IF($G$4="(All)","*",$G$4)),"") | K18: =IFERROR(AVERAGEIFS(Trades!$O$2:$O$74,Trades!$H$2:$H$74,$A$18,Trades!$C$2:$C$74,IF($D$4="(All)","*",$D$4),Trades!$AE$2:$AE$74,IF($G$4="(All)","*",$G$4)),"") | L18: =IFERROR(E18/SUMIFS(Trades!$AD$2:$AD$74,Trades!$C$2:$C$74,IF($D$4="(All)","*",$D$4),Trades!$AE$2:$AE$74,IF($G$4="(All)","*",$G$4))*100,"")
A19: Thursday | B19: =COUNTIFS(Trades!$H$2:$H$74,$A$19,Trades!$C$2:$C$74,IF($D$4="(All)","*",$D$4),Trades!$AE$2:$AE$74,IF($G$4="(All)","*",$G$4)) | C19: =COUNTIFS(Trades!$AE$2:$AE$74,"Win",Trades!$H$2:$H$74,$A$19,Trades!$C$2:$C$74,IF($D$4="(All)","*",$D$4),Trades!$AE$2:$AE$74,IF($G$4="(All)","*",$G$4)) | D19: =IFERROR(C19/B19*100,"") | E19: =SUMIFS(Trades!$AD$2:$AD$74,Trades!$H$2:$H$74,$A$19,Trades!$C$2:$C$74,IF($D$4="(All)","*",$D$4),Trades!$AE$2:$AE$74,IF($G$4="(All)","*",$G$4)) | F19: =IFERROR(E19/B19,"") | G19: =IFERROR(AVERAGEIFS(Trades!$Z$2:$Z$74,Trades!$H$2:$H$74,$A$19,Trades!$C$2:$C$74,IF($D$4="(All)","*",$D$4),Trades!$AE$2:$AE$74,IF($G$4="(All)","*",$G$4)),"") | H19: =IFERROR(SUMIFS(Trades!$AD$2:$AD$74,Trades!$H$2:$H$74,$A$19,Trades!$AD$2:$AD$74,">0",Trades!$C$2:$C$74,IF($D$4="(All)","*",$D$4),Trades!$AE$2:$AE$74,IF($G$4="(All)","*",$G$4))/-SUMIFS(Trades!$AD$2:$AD$74,Trades!$H$2:$H$74,$A$19,Trades!$AD$2:$AD$74,"<0",Trades!$C$2:$C$74,IF($D$4="(All)","*",$D$4),Trades!$AE$2:$AE$74,IF($G$4="(All)","*",$G$4)),"") | I19: =IFERROR(AVERAGEIFS(Trades!$AH$2:$AH$74,Trades!$H$2:$H$74,$A$19,Trades!$C$2:$C$74,IF($D$4="(All)","*",$D$4),Trades!$AE$2:$AE$74,IF($G$4="(All)","*",$G$4)),"") | J19: =IFERROR(AVERAGEIFS(Trades!$AI$2:$AI$74,Trades!$H$2:$H$74,$A$19,Trades!$C$2:$C$74,IF($D$4="(All)","*",$D$4),Trades!$AE$2:$AE$74,IF($G$4="(All)","*",$G$4)),"") | K19: =IFERROR(AVERAGEIFS(Trades!$O$2:$O$74,Trades!$H$2:$H$74,$A$19,Trades!$C$2:$C$74,IF($D$4="(All)","*",$D$4),Trades!$AE$2:$AE$74,IF($G$4="(All)","*",$G$4)),"") | L19: =IFERROR(E19/SUMIFS(Trades!$AD$2:$AD$74,Trades!$C$2:$C$74,IF($D$4="(All)","*",$D$4),Trades!$AE$2:$AE$74,IF($G$4="(All)","*",$G$4))*100,"")
A20: Tuesday | B20: =COUNTIFS(Trades!$H$2:$H$74,$A$20,Trades!$C$2:$C$74,IF($D$4="(All)","*",$D$4),Trades!$AE$2:$AE$74,IF($G$4="(All)","*",$G$4)) | C20: =COUNTIFS(Trades!$AE$2:$AE$74,"Win",Trades!$H$2:$H$74,$A$20,Trades!$C$2:$C$74,IF($D$4="(All)","*",$D$4),Trades!$AE$2:$AE$74,IF($G$4="(All)","*",$G$4)) | D20: =IFERROR(C20/B20*100,"") | E20: =SUMIFS(Trades!$AD$2:$AD$74,Trades!$H$2:$H$74,$A$20,Trades!$C$2:$C$74,IF($D$4="(All)","*",$D$4),Trades!$AE$2:$AE$74,IF($G$4="(All)","*",$G$4)) | F20: =IFERROR(E20/B20,"") | G20: =IFERROR(AVERAGEIFS(Trades!$Z$2:$Z$74,Trades!$H$2:$H$74,$A$20,Trades!$C$2:$C$74,IF($D$4="(All)","*",$D$4),Trades!$AE$2:$AE$74,IF($G$4="(All)","*",$G$4)),"") | H20: =IFERROR(SUMIFS(Trades!$AD$2:$AD$74,Trades!$H$2:$H$74,$A$20,Trades!$AD$2:$AD$74,">0",Trades!$C$2:$C$74,IF($D$4="(All)","*",$D$4),Trades!$AE$2:$AE$74,IF($G$4="(All)","*",$G$4))/-SUMIFS(Trades!$AD$2:$AD$74,Trades!$H$2:$H$74,$A$20,Trades!$AD$2:$AD$74,"<0",Trades!$C$2:$C$74,IF($D$4="(All)","*",$D$4),Trades!$AE$2:$AE$74,IF($G$4="(All)","*",$G$4)),"") | I20: =IFERROR(AVERAGEIFS(Trades!$AH$2:$AH$74,Trades!$H$2:$H$74,$A$20,Trades!$C$2:$C$74,IF($D$4="(All)","*",$D$4),Trades!$AE$2:$AE$74,IF($G$4="(All)","*",$G$4)),"") | J20: =IFERROR(AVERAGEIFS(Trades!$AI$2:$AI$74,Trades!$H$2:$H$74,$A$20,Trades!$C$2:$C$74,IF($D$4="(All)","*",$D$4),Trades!$AE$2:$AE$74,IF($G$4="(All)","*",$G$4)),"") | K20: =IFERROR(AVERAGEIFS(Trades!$O$2:$O$74,Trades!$H$2:$H$74,$A$20,Trades!$C$2:$C$74,IF($D$4="(All)","*",$D$4),Trades!$AE$2:$AE$74,IF($G$4="(All)","*",$G$4)),"") | L20: =IFERROR(E20/SUMIFS(Trades!$AD$2:$AD$74,Trades!$C$2:$C$74,IF($D$4="(All)","*",$D$4),Trades!$AE$2:$AE$74,IF($G$4="(All)","*",$G$4))*100,"")
A21: Wednesday | B21: =COUNTIFS(Trades!$H$2:$H$74,$A$21,Trades!$C$2:$C$74,IF($D$4="(All)","*",$D$4),Trades!$AE$2:$AE$74,IF($G$4="(All)","*",$G$4)) | C21: =COUNTIFS(Trades!$AE$2:$AE$74,"Win",Trades!$H$2:$H$74,$A$21,Trades!$C$2:$C$74,IF($D$4="(All)","*",$D$4),Trades!$AE$2:$AE$74,IF($G$4="(All)","*",$G$4)) | D21: =IFERROR(C21/B21*100,"") | E21: =SUMIFS(Trades!$AD$2:$AD$74,Trades!$H$2:$H$74,$A$21,Trades!$C$2:$C$74,IF($D$4="(All)","*",$D$4),Trades!$AE$2:$AE$74,IF($G$4="(All)","*",$G$4)) | F21: =IFERROR(E21/B21,"") | G21: =IFERROR(AVERAGEIFS(Trades!$Z$2:$Z$74,Trades!$H$2:$H$74,$A$21,Trades!$C$2:$C$74,IF($D$4="(All)","*",$D$4),Trades!$AE$2:$AE$74,IF($G$4="(All)","*",$G$4)),"") | H21: =IFERROR(SUMIFS(Trades!$AD$2:$AD$74,Trades!$H$2:$H$74,$A$21,Trades!$AD$2:$AD$74,">0",Trades!$C$2:$C$74,IF($D$4="(All)","*",$D$4),Trades!$AE$2:$AE$74,IF($G$4="(All)","*",$G$4))/-SUMIFS(Trades!$AD$2:$AD$74,Trades!$H$2:$H$74,$A$21,Trades!$AD$2:$AD$74,"<0",Trades!$C$2:$C$74,IF($D$4="(All)","*",$D$4),Trades!$AE$2:$AE$74,IF($G$4="(All)","*",$G$4)),"") | I21: =IFERROR(AVERAGEIFS(Trades!$AH$2:$AH$74,Trades!$H$2:$H$74,$A$21,Trades!$C$2:$C$74,IF($D$4="(All)","*",$D$4),Trades!$AE$2:$AE$74,IF($G$4="(All)","*",$G$4)),"") | J21: =IFERROR(AVERAGEIFS(Trades!$AI$2:$AI$74,Trades!$H$2:$H$74,$A$21,Trades!$C$2:$C$74,IF($D$4="(All)","*",$D$4),Trades!$AE$2:$AE$74,IF($G$4="(All)","*",$G$4)),"") | K21: =IFERROR(AVERAGEIFS(Trades!$O$2:$O$74,Trades!$H$2:$H$74,$A$21,Trades!$C$2:$C$74,IF($D$4="(All)","*",$D$4),Trades!$AE$2:$AE$74,IF($G$4="(All)","*",$G$4)),"") | L21: =IFERROR(E21/SUMIFS(Trades!$AD$2:$AD$74,Trades!$C$2:$C$74,IF($D$4="(All)","*",$D$4),Trades!$AE$2:$AE$74,IF($G$4="(All)","*",$G$4))*100,"")
A22: All trades | B22: =COUNTIFS(Trades!$C$2:$C$74,IF($D$4="(All)","*",$D$4),Trades!$AE$2:$AE$74,IF($G$4="(All)","*",$G$4)) | C22: =COUNTIFS(Trades!$AE$2:$AE$74,"Win",Trades!$C$2:$C$74,IF($D$4="(All)","*",$D$4),Trades!$AE$2:$AE$74,IF($G$4="(All)","*",$G$4)) | D22: =IFERROR(C22/B22*100,"") | E22: =SUMIFS(Trades!$AD$2:$AD$74,Trades!$C$2:$C$74,IF($D$4="(All)","*",$D$4),Trades!$AE$2:$AE$74,IF($G$4="(All)","*",$G$4)) | F22: =IFERROR(E22/B22,"") | G22: =IFERROR(AVERAGEIFS(Trades!$Z$2:$Z$74,Trades!$C$2:$C$74,IF($D$4="(All)","*",$D$4),Trades!$AE$2:$AE$74,IF($G$4="(All)","*",$G$4)),"") | H22: =IFERROR(SUMIFS(Trades!$AD$2:$AD$74,Trades!$AD$2:$AD$74,">0",Trades!$C$2:$C$74,IF($D$4="(All)","*",$D$4),Trades!$AE$2:$AE$74,IF($G$4="(All)","*",$G$4))/-SUMIFS(Trades!$AD$2:$AD$74,Trades!$AD$2:$AD$74,"<0",Trades!$C$2:$C$74,IF($D$4="(All)","*",$D$4),Trades!$AE$2:$AE$74,IF($G$4="(All)","*",$G$4)),"") | I22: =IFERROR(AVERAGEIFS(Trades!$AH$2:$AH$74,Trades!$C$2:$C$74,IF($D$4="(All)","*",$D$4),Trades!$AE$2:$AE$74,IF($G$4="(All)","*",$G$4)),"") | J22: =IFERROR(AVERAGEIFS(Trades!$AI$2:$AI$74,Trades!$C$2:$C$74,IF($D$4="(All)","*",$D$4),Trades!$AE$2:$AE$74,IF($G$4="(All)","*",$G$4)),"") | K22: =IFERROR(AVERAGEIFS(Trades!$O$2:$O$74,Trades!$C$2:$C$74,IF($D$4="(All)","*",$D$4),Trades!$AE$2:$AE$74,IF($G$4="(All)","*",$G$4)),"") | L22: =IFERROR(E22/SUMIFS(Trades!$AD$2:$AD$74,Trades!$C$2:$C$74,IF($D$4="(All)","*",$D$4),Trades!$AE$2:$AE$74,IF($G$4="(All)","*",$G$4))*100,"")
A25: By hour | E25: Hour of entry. Thin rows are noise - read the trade count before the net.
A26: Hour | B26: Trades | C26: Wins | D26: Win % | E26: Net | F26: Expectancy | G26: Avg R | H26: Profit factor | I26: Avg MFE | J26: Avg MAE | K26: Avg dur (min) | L26: Share of net
A27: 7 | B27: =COUNTIFS(Trades!$I$2:$I$74,$A$27,Trades!$C$2:$C$74,IF($D$4="(All)","*",$D$4),Trades!$AE$2:$AE$74,IF($G$4="(All)","*",$G$4)) | C27: =COUNTIFS(Trades!$AE$2:$AE$74,"Win",Trades!$I$2:$I$74,$A$27,Trades!$C$2:$C$74,IF($D$4="(All)","*",$D$4),Trades!$AE$2:$AE$74,IF($G$4="(All)","*",$G$4)) | D27: =IFERROR(C27/B27*100,"") | E27: =SUMIFS(Trades!$AD$2:$AD$74,Trades!$I$2:$I$74,$A$27,Trades!$C$2:$C$74,IF($D$4="(All)","*",$D$4),Trades!$AE$2:$AE$74,IF($G$4="(All)","*",$G$4)) | F27: =IFERROR(E27/B27,"") | G27: =IFERROR(AVERAGEIFS(Trades!$Z$2:$Z$74,Trades!$I$2:$I$74,$A$27,Trades!$C$2:$C$74,IF($D$4="(All)","*",$D$4),Trades!$AE$2:$AE$74,IF($G$4="(All)","*",$G$4)),"") | H27: =IFERROR(SUMIFS(Trades!$AD$2:$AD$74,Trades!$I$2:$I$74,$A$27,Trades!$AD$2:$AD$74,">0",Trades!$C$2:$C$74,IF($D$4="(All)","*",$D$4),Trades!$AE$2:$AE$74,IF($G$4="(All)","*",$G$4))/-SUMIFS(Trades!$AD$2:$AD$74,Trades!$I$2:$I$74,$A$27,Trades!$AD$2:$AD$74,"<0",Trades!$C$2:$C$74,IF($D$4="(All)","*",$D$4),Trades!$AE$2:$AE$74,IF($G$4="(All)","*",$G$4)),"") | I27: =IFERROR(AVERAGEIFS(Trades!$AH$2:$AH$74,Trades!$I$2:$I$74,$A$27,Trades!$C$2:$C$74,IF($D$4="(All)","*",$D$4),Trades!$AE$2:$AE$74,IF($G$4="(All)","*",$G$4)),"") | J27: =IFERROR(AVERAGEIFS(Trades!$AI$2:$AI$74,Trades!$I$2:$I$74,$A$27,Trades!$C$2:$C$74,IF($D$4="(All)","*",$D$4),Trades!$AE$2:$AE$74,IF($G$4="(All)","*",$G$4)),"") | K27: =IFERROR(AVERAGEIFS(Trades!$O$2:$O$74,Trades!$I$2:$I$74,$A$27,Trades!$C$2:$C$74,IF($D$4="(All)","*",$D$4),Trades!$AE$2:$AE$74,IF($G$4="(All)","*",$G$4)),"") | L27: =IFERROR(E27/SUMIFS(Trades!$AD$2:$AD$74,Trades!$C$2:$C$74,IF($D$4="(All)","*",$D$4),Trades!$AE$2:$AE$74,IF($G$4="(All)","*",$G$4))*100,"")
A28: 8 | B28: =COUNTIFS(Trades!$I$2:$I$74,$A$28,Trades!$C$2:$C$74,IF($D$4="(All)","*",$D$4),Trades!$AE$2:$AE$74,IF($G$4="(All)","*",$G$4)) | C28: =COUNTIFS(Trades!$AE$2:$AE$74,"Win",Trades!$I$2:$I$74,$A$28,Trades!$C$2:$C$74,IF($D$4="(All)","*",$D$4),Trades!$AE$2:$AE$74,IF($G$4="(All)","*",$G$4)) | D28: =IFERROR(C28/B28*100,"") | E28: =SUMIFS(Trades!$AD$2:$AD$74,Trades!$I$2:$I$74,$A$28,Trades!$C$2:$C$74,IF($D$4="(All)","*",$D$4),Trades!$AE$2:$AE$74,IF($G$4="(All)","*",$G$4)) | F28: =IFERROR(E28/B28,"") | G28: =IFERROR(AVERAGEIFS(Trades!$Z$2:$Z$74,Trades!$I$2:$I$74,$A$28,Trades!$C$2:$C$74,IF($D$4="(All)","*",$D$4),Trades!$AE$2:$AE$74,IF($G$4="(All)","*",$G$4)),"") | H28: =IFERROR(SUMIFS(Trades!$AD$2:$AD$74,Trades!$I$2:$I$74,$A$28,Trades!$AD$2:$AD$74,">0",Trades!$C$2:$C$74,IF($D$4="(All)","*",$D$4),Trades!$AE$2:$AE$74,IF($G$4="(All)","*",$G$4))/-SUMIFS(Trades!$AD$2:$AD$74,Trades!$I$2:$I$74,$A$28,Trades!$AD$2:$AD$74,"<0",Trades!$C$2:$C$74,IF($D$4="(All)","*",$D$4),Trades!$AE$2:$AE$74,IF($G$4="(All)","*",$G$4)),"") | I28: =IFERROR(AVERAGEIFS(Trades!$AH$2:$AH$74,Trades!$I$2:$I$74,$A$28,Trades!$C$2:$C$74,IF($D$4="(All)","*",$D$4),Trades!$AE$2:$AE$74,IF($G$4="(All)","*",$G$4)),"") | J28: =IFERROR(AVERAGEIFS(Trades!$AI$2:$AI$74,Trades!$I$2:$I$74,$A$28,Trades!$C$2:$C$74,IF($D$4="(All)","*",$D$4),Trades!$AE$2:$AE$74,IF($G$4="(All)","*",$G$4)),"") | K28: =IFERROR(AVERAGEIFS(Trades!$O$2:$O$74,Trades!$I$2:$I$74,$A$28,Trades!$C$2:$C$74,IF($D$4="(All)","*",$D$4),Trades!$AE$2:$AE$74,IF($G$4="(All)","*",$G$4)),"") | L28: =IFERROR(E28/SUMIFS(Trades!$AD$2:$AD$74,Trades!$C$2:$C$74,IF($D$4="(All)","*",$D$4),Trades!$AE$2:$AE$74,IF($G$4="(All)","*",$G$4))*100,"")
A29: 9 | B29: =COUNTIFS(Trades!$I$2:$I$74,$A$29,Trades!$C$2:$C$74,IF($D$4="(All)","*",$D$4),Trades!$AE$2:$AE$74,IF($G$4="(All)","*",$G$4)) | C29: =COUNTIFS(Trades!$AE$2:$AE$74,"Win",Trades!$I$2:$I$74,$A$29,Trades!$C$2:$C$74,IF($D$4="(All)","*",$D$4),Trades!$AE$2:$AE$74,IF($G$4="(All)","*",$G$4)) | D29: =IFERROR(C29/B29*100,"") | E29: =SUMIFS(Trades!$AD$2:$AD$74,Trades!$I$2:$I$74,$A$29,Trades!$C$2:$C$74,IF($D$4="(All)","*",$D$4),Trades!$AE$2:$AE$74,IF($G$4="(All)","*",$G$4)) | F29: =IFERROR(E29/B29,"") | G29: =IFERROR(AVERAGEIFS(Trades!$Z$2:$Z$74,Trades!$I$2:$I$74,$A$29,Trades!$C$2:$C$74,IF($D$4="(All)","*",$D$4),Trades!$AE$2:$AE$74,IF($G$4="(All)","*",$G$4)),"") | H29: =IFERROR(SUMIFS(Trades!$AD$2:$AD$74,Trades!$I$2:$I$74,$A$29,Trades!$AD$2:$AD$74,">0",Trades!$C$2:$C$74,IF($D$4="(All)","*",$D$4),Trades!$AE$2:$AE$74,IF($G$4="(All)","*",$G$4))/-SUMIFS(Trades!$AD$2:$AD$74,Trades!$I$2:$I$74,$A$29,Trades!$AD$2:$AD$74,"<0",Trades!$C$2:$C$74,IF($D$4="(All)","*",$D$4),Trades!$AE$2:$AE$74,IF($G$4="(All)","*",$G$4)),"") | I29: =IFERROR(AVERAGEIFS(Trades!$AH$2:$AH$74,Trades!$I$2:$I$74,$A$29,Trades!$C$2:$C$74,IF($D$4="(All)","*",$D$4),Trades!$AE$2:$AE$74,IF($G$4="(All)","*",$G$4)),"") | J29: =IFERROR(AVERAGEIFS(Trades!$AI$2:$AI$74,Trades!$I$2:$I$74,$A$29,Trades!$C$2:$C$74,IF($D$4="(All)","*",$D$4),Trades!$AE$2:$AE$74,IF($G$4="(All)","*",$G$4)),"") | K29: =IFERROR(AVERAGEIFS(Trades!$O$2:$O$74,Trades!$I$2:$I$74,$A$29,Trades!$C$2:$C$74,IF($D$4="(All)","*",$D$4),Trades!$AE$2:$AE$74,IF($G$4="(All)","*",$G$4)),"") | L29: =IFERROR(E29/SUMIFS(Trades!$AD$2:$AD$74,Trades!$C$2:$C$74,IF($D$4="(All)","*",$D$4),Trades!$AE$2:$AE$74,IF($G$4="(All)","*",$G$4))*100,"")
A30: 10 | B30: =COUNTIFS(Trades!$I$2:$I$74,$A$30,Trades!$C$2:$C$74,IF($D$4="(All)","*",$D$4),Trades!$AE$2:$AE$74,IF($G$4="(All)","*",$G$4)) | C30: =COUNTIFS(Trades!$AE$2:$AE$74,"Win",Trades!$I$2:$I$74,$A$30,Trades!$C$2:$C$74,IF($D$4="(All)","*",$D$4),Trades!$AE$2:$AE$74,IF($G$4="(All)","*",$G$4)) | D30: =IFERROR(C30/B30*100,"") | E30: =SUMIFS(Trades!$AD$2:$AD$74,Trades!$I$2:$I$74,$A$30,Trades!$C$2:$C$74,IF($D$4="(All)","*",$D$4),Trades!$AE$2:$AE$74,IF($G$4="(All)","*",$G$4)) | F30: =IFERROR(E30/B30,"") | G30: =IFERROR(AVERAGEIFS(Trades!$Z$2:$Z$74,Trades!$I$2:$I$74,$A$30,Trades!$C$2:$C$74,IF($D$4="(All)","*",$D$4),Trades!$AE$2:$AE$74,IF($G$4="(All)","*",$G$4)),"") | H30: =IFERROR(SUMIFS(Trades!$AD$2:$AD$74,Trades!$I$2:$I$74,$A$30,Trades!$AD$2:$AD$74,">0",Trades!$C$2:$C$74,IF($D$4="(All)","*",$D$4),Trades!$AE$2:$AE$74,IF($G$4="(All)","*",$G$4))/-SUMIFS(Trades!$AD$2:$AD$74,Trades!$I$2:$I$74,$A$30,Trades!$AD$2:$AD$74,"<0",Trades!$C$2:$C$74,IF($D$4="(All)","*",$D$4),Trades!$AE$2:$AE$74,IF($G$4="(All)","*",$G$4)),"") | I30: =IFERROR(AVERAGEIFS(Trades!$AH$2:$AH$74,Trades!$I$2:$I$74,$A$30,Trades!$C$2:$C$74,IF($D$4="(All)","*",$D$4),Trades!$AE$2:$AE$74,IF($G$4="(All)","*",$G$4)),"") | J30: =IFERROR(AVERAGEIFS(Trades!$AI$2:$AI$74,Trades!$I$2:$I$74,$A$30,Trades!$C$2:$C$74,IF($D$4="(All)","*",$D$4),Trades!$AE$2:$AE$74,IF($G$4="(All)","*",$G$4)),"") | K30: =IFERROR(AVERAGEIFS(Trades!$O$2:$O$74,Trades!$I$2:$I$74,$A$30,Trades!$C$2:$C$74,IF($D$4="(All)","*",$D$4),Trades!$AE$2:$AE$74,IF($G$4="(All)","*",$G$4)),"") | L30: =IFERROR(E30/SUMIFS(Trades!$AD$2:$AD$74,Trades!$C$2:$C$74,IF($D$4="(All)","*",$D$4),Trades!$AE$2:$AE$74,IF($G$4="(All)","*",$G$4))*100,"")
A31: 11 | B31: =COUNTIFS(Trades!$I$2:$I$74,$A$31,Trades!$C$2:$C$74,IF($D$4="(All)","*",$D$4),Trades!$AE$2:$AE$74,IF($G$4="(All)","*",$G$4)) | C31: =COUNTIFS(Trades!$AE$2:$AE$74,"Win",Trades!$I$2:$I$74,$A$31,Trades!$C$2:$C$74,IF($D$4="(All)","*",$D$4),Trades!$AE$2:$AE$74,IF($G$4="(All)","*",$G$4)) | D31: =IFERROR(C31/B31*100,"") | E31: =SUMIFS(Trades!$AD$2:$AD$74,Trades!$I$2:$I$74,$A$31,Trades!$C$2:$C$74,IF($D$4="(All)","*",$D$4),Trades!$AE$2:$AE$74,IF($G$4="(All)","*",$G$4)) | F31: =IFERROR(E31/B31,"") | G31: =IFERROR(AVERAGEIFS(Trades!$Z$2:$Z$74,Trades!$I$2:$I$74,$A$31,Trades!$C$2:$C$74,IF($D$4="(All)","*",$D$4),Trades!$AE$2:$AE$74,IF($G$4="(All)","*",$G$4)),"") | H31: =IFERROR(SUMIFS(Trades!$AD$2:$AD$74,Trades!$I$2:$I$74,$A$31,Trades!$AD$2:$AD$74,">0",Trades!$C$2:$C$74,IF($D$4="(All)","*",$D$4),Trades!$AE$2:$AE$74,IF($G$4="(All)","*",$G$4))/-SUMIFS(Trades!$AD$2:$AD$74,Trades!$I$2:$I$74,$A$31,Trades!$AD$2:$AD$74,"<0",Trades!$C$2:$C$74,IF($D$4="(All)","*",$D$4),Trades!$AE$2:$AE$74,IF($G$4="(All)","*",$G$4)),"") | I31: =IFERROR(AVERAGEIFS(Trades!$AH$2:$AH$74,Trades!$I$2:$I$74,$A$31,Trades!$C$2:$C$74,IF($D$4="(All)","*",$D$4),Trades!$AE$2:$AE$74,IF($G$4="(All)","*",$G$4)),"") | J31: =IFERROR(AVERAGEIFS(Trades!$AI$2:$AI$74,Trades!$I$2:$I$74,$A$31,Trades!$C$2:$C$74,IF($D$4="(All)","*",$D$4),Trades!$AE$2:$AE$74,IF($G$4="(All)","*",$G$4)),"") | K31: =IFERROR(AVERAGEIFS(Trades!$O$2:$O$74,Trades!$I$2:$I$74,$A$31,Trades!$C$2:$C$74,IF($D$4="(All)","*",$D$4),Trades!$AE$2:$AE$74,IF($G$4="(All)","*",$G$4)),"") | L31: =IFERROR(E31/SUMIFS(Trades!$AD$2:$AD$74,Trades!$C$2:$C$74,IF($D$4="(All)","*",$D$4),Trades!$AE$2:$AE$74,IF($G$4="(All)","*",$G$4))*100,"")
A32: 13 | B32: =COUNTIFS(Trades!$I$2:$I$74,$A$32,Trades!$C$2:$C$74,IF($D$4="(All)","*",$D$4),Trades!$AE$2:$AE$74,IF($G$4="(All)","*",$G$4)) | C32: =COUNTIFS(Trades!$AE$2:$AE$74,"Win",Trades!$I$2:$I$74,$A$32,Trades!$C$2:$C$74,IF($D$4="(All)","*",$D$4),Trades!$AE$2:$AE$74,IF($G$4="(All)","*",$G$4)) | D32: =IFERROR(C32/B32*100,"") | E32: =SUMIFS(Trades!$AD$2:$AD$74,Trades!$I$2:$I$74,$A$32,Trades!$C$2:$C$74,IF($D$4="(All)","*",$D$4),Trades!$AE$2:$AE$74,IF($G$4="(All)","*",$G$4)) | F32: =IFERROR(E32/B32,"") | G32: =IFERROR(AVERAGEIFS(Trades!$Z$2:$Z$74,Trades!$I$2:$I$74,$A$32,Trades!$C$2:$C$74,IF($D$4="(All)","*",$D$4),Trades!$AE$2:$AE$74,IF($G$4="(All)","*",$G$4)),"") | H32: =IFERROR(SUMIFS(Trades!$AD$2:$AD$74,Trades!$I$2:$I$74,$A$32,Trades!$AD$2:$AD$74,">0",Trades!$C$2:$C$74,IF($D$4="(All)","*",$D$4),Trades!$AE$2:$AE$74,IF($G$4="(All)","*",$G$4))/-SUMIFS(Trades!$AD$2:$AD$74,Trades!$I$2:$I$74,$A$32,Trades!$AD$2:$AD$74,"<0",Trades!$C$2:$C$74,IF($D$4="(All)","*",$D$4),Trades!$AE$2:$AE$74,IF($G$4="(All)","*",$G$4)),"") | I32: =IFERROR(AVERAGEIFS(Trades!$AH$2:$AH$74,Trades!$I$2:$I$74,$A$32,Trades!$C$2:$C$74,IF($D$4="(All)","*",$D$4),Trades!$AE$2:$AE$74,IF($G$4="(All)","*",$G$4)),"") | J32: =IFERROR(AVERAGEIFS(Trades!$AI$2:$AI$74,Trades!$I$2:$I$74,$A$32,Trades!$C$2:$C$74,IF($D$4="(All)","*",$D$4),Trades!$AE$2:$AE$74,IF($G$4="(All)","*",$G$4)),"") | K32: =IFERROR(AVERAGEIFS(Trades!$O$2:$O$74,Trades!$I$2:$I$74,$A$32,Trades!$C$2:$C$74,IF($D$4="(All)","*",$D$4),Trades!$AE$2:$AE$74,IF($G$4="(All)","*",$G$4)),"") | L32: =IFERROR(E32/SUMIFS(Trades!$AD$2:$AD$74,Trades!$C$2:$C$74,IF($D$4="(All)","*",$D$4),Trades!$AE$2:$AE$74,IF($G$4="(All)","*",$G$4))*100,"")
A33: 14 | B33: =COUNTIFS(Trades!$I$2:$I$74,$A$33,Trades!$C$2:$C$74,IF($D$4="(All)","*",$D$4),Trades!$AE$2:$AE$74,IF($G$4="(All)","*",$G$4)) | C33: =COUNTIFS(Trades!$AE$2:$AE$74,"Win",Trades!$I$2:$I$74,$A$33,Trades!$C$2:$C$74,IF($D$4="(All)","*",$D$4),Trades!$AE$2:$AE$74,IF($G$4="(All)","*",$G$4)) | D33: =IFERROR(C33/B33*100,"") | E33: =SUMIFS(Trades!$AD$2:$AD$74,Trades!$I$2:$I$74,$A$33,Trades!$C$2:$C$74,IF($D$4="(All)","*",$D$4),Trades!$AE$2:$AE$74,IF($G$4="(All)","*",$G$4)) | F33: =IFERROR(E33/B33,"") | G33: =IFERROR(AVERAGEIFS(Trades!$Z$2:$Z$74,Trades!$I$2:$I$74,$A$33,Trades!$C$2:$C$74,IF($D$4="(All)","*",$D$4),Trades!$AE$2:$AE$74,IF($G$4="(All)","*",$G$4)),"") | H33: =IFERROR(SUMIFS(Trades!$AD$2:$AD$74,Trades!$I$2:$I$74,$A$33,Trades!$AD$2:$AD$74,">0",Trades!$C$2:$C$74,IF($D$4="(All)","*",$D$4),Trades!$AE$2:$AE$74,IF($G$4="(All)","*",$G$4))/-SUMIFS(Trades!$AD$2:$AD$74,Trades!$I$2:$I$74,$A$33,Trades!$AD$2:$AD$74,"<0",Trades!$C$2:$C$74,IF($D$4="(All)","*",$D$4),Trades!$AE$2:$AE$74,IF($G$4="(All)","*",$G$4)),"") | I33: =IFERROR(AVERAGEIFS(Trades!$AH$2:$AH$74,Trades!$I$2:$I$74,$A$33,Trades!$C$2:$C$74,IF($D$4="(All)","*",$D$4),Trades!$AE$2:$AE$74,IF($G$4="(All)","*",$G$4)),"") | J33: =IFERROR(AVERAGEIFS(Trades!$AI$2:$AI$74,Trades!$I$2:$I$74,$A$33,Trades!$C$2:$C$74,IF($D$4="(All)","*",$D$4),Trades!$AE$2:$AE$74,IF($G$4="(All)","*",$G$4)),"") | K33: =IFERROR(AVERAGEIFS(Trades!$O$2:$O$74,Trades!$I$2:$I$74,$A$33,Trades!$C$2:$C$74,IF($D$4="(All)","*",$D$4),Trades!$AE$2:$AE$74,IF($G$4="(All)","*",$G$4)),"") | L33: =IFERROR(E33/SUMIFS(Trades!$AD$2:$AD$74,Trades!$C$2:$C$74,IF($D$4="(All)","*",$D$4),Trades!$AE$2:$AE$74,IF($G$4="(All)","*",$G$4))*100,"")
A34: 15 | B34: =COUNTIFS(Trades!$I$2:$I$74,$A$34,Trades!$C$2:$C$74,IF($D$4="(All)","*",$D$4),Trades!$AE$2:$AE$74,IF($G$4="(All)","*",$G$4)) | C34: =COUNTIFS(Trades!$AE$2:$AE$74,"Win",Trades!$I$2:$I$74,$A$34,Trades!$C$2:$C$74,IF($D$4="(All)","*",$D$4),Trades!$AE$2:$AE$74,IF($G$4="(All)","*",$G$4)) | D34: =IFERROR(C34/B34*100,"") | E34: =SUMIFS(Trades!$AD$2:$AD$74,Trades!$I$2:$I$74,$A$34,Trades!$C$2:$C$74,IF($D$4="(All)","*",$D$4),Trades!$AE$2:$AE$74,IF($G$4="(All)","*",$G$4)) | F34: =IFERROR(E34/B34,"") | G34: =IFERROR(AVERAGEIFS(Trades!$Z$2:$Z$74,Trades!$I$2:$I$74,$A$34,Trades!$C$2:$C$74,IF($D$4="(All)","*",$D$4),Trades!$AE$2:$AE$74,IF($G$4="(All)","*",$G$4)),"") | H34: =IFERROR(SUMIFS(Trades!$AD$2:$AD$74,Trades!$I$2:$I$74,$A$34,Trades!$AD$2:$AD$74,">0",Trades!$C$2:$C$74,IF($D$4="(All)","*",$D$4),Trades!$AE$2:$AE$74,IF($G$4="(All)","*",$G$4))/-SUMIFS(Trades!$AD$2:$AD$74,Trades!$I$2:$I$74,$A$34,Trades!$AD$2:$AD$74,"<0",Trades!$C$2:$C$74,IF($D$4="(All)","*",$D$4),Trades!$AE$2:$AE$74,IF($G$4="(All)","*",$G$4)),"") | I34: =IFERROR(AVERAGEIFS(Trades!$AH$2:$AH$74,Trades!$I$2:$I$74,$A$34,Trades!$C$2:$C$74,IF($D$4="(All)","*",$D$4),Trades!$AE$2:$AE$74,IF($G$4="(All)","*",$G$4)),"") | J34: =IFERROR(AVERAGEIFS(Trades!$AI$2:$AI$74,Trades!$I$2:$I$74,$A$34,Trades!$C$2:$C$74,IF($D$4="(All)","*",$D$4),Trades!$AE$2:$AE$74,IF($G$4="(All)","*",$G$4)),"") | K34: =IFERROR(AVERAGEIFS(Trades!$O$2:$O$74,Trades!$I$2:$I$74,$A$34,Trades!$C$2:$C$74,IF($D$4="(All)","*",$D$4),Trades!$AE$2:$AE$74,IF($G$4="(All)","*",$G$4)),"") | L34: =IFERROR(E34/SUMIFS(Trades!$AD$2:$AD$74,Trades!$C$2:$C$74,IF($D$4="(All)","*",$D$4),Trades!$AE$2:$AE$74,IF($G$4="(All)","*",$G$4))*100,"")
A35: 16 | B35: =COUNTIFS(Trades!$I$2:$I$74,$A$35,Trades!$C$2:$C$74,IF($D$4="(All)","*",$D$4),Trades!$AE$2:$AE$74,IF($G$4="(All)","*",$G$4)) | C35: =COUNTIFS(Trades!$AE$2:$AE$74,"Win",Trades!$I$2:$I$74,$A$35,Trades!$C$2:$C$74,IF($D$4="(All)","*",$D$4),Trades!$AE$2:$AE$74,IF($G$4="(All)","*",$G$4)) | D35: =IFERROR(C35/B35*100,"") | E35: =SUMIFS(Trades!$AD$2:$AD$74,Trades!$I$2:$I$74,$A$35,Trades!$C$2:$C$74,IF($D$4="(All)","*",$D$4),Trades!$AE$2:$AE$74,IF($G$4="(All)","*",$G$4)) | F35: =IFERROR(E35/B35,"") | G35: =IFERROR(AVERAGEIFS(Trades!$Z$2:$Z$74,Trades!$I$2:$I$74,$A$35,Trades!$C$2:$C$74,IF($D$4="(All)","*",$D$4),Trades!$AE$2:$AE$74,IF($G$4="(All)","*",$G$4)),"") | H35: =IFERROR(SUMIFS(Trades!$AD$2:$AD$74,Trades!$I$2:$I$74,$A$35,Trades!$AD$2:$AD$74,">0",Trades!$C$2:$C$74,IF($D$4="(All)","*",$D$4),Trades!$AE$2:$AE$74,IF($G$4="(All)","*",$G$4))/-SUMIFS(Trades!$AD$2:$AD$74,Trades!$I$2:$I$74,$A$35,Trades!$AD$2:$AD$74,"<0",Trades!$C$2:$C$74,IF($D$4="(All)","*",$D$4),Trades!$AE$2:$AE$74,IF($G$4="(All)","*",$G$4)),"") | I35: =IFERROR(AVERAGEIFS(Trades!$AH$2:$AH$74,Trades!$I$2:$I$74,$A$35,Trades!$C$2:$C$74,IF($D$4="(All)","*",$D$4),Trades!$AE$2:$AE$74,IF($G$4="(All)","*",$G$4)),"") | J35: =IFERROR(AVERAGEIFS(Trades!$AI$2:$AI$74,Trades!$I$2:$I$74,$A$35,Trades!$C$2:$C$74,IF($D$4="(All)","*",$D$4),Trades!$AE$2:$AE$74,IF($G$4="(All)","*",$G$4)),"") | K35: =IFERROR(AVERAGEIFS(Trades!$O$2:$O$74,Trades!$I$2:$I$74,$A$35,Trades!$C$2:$C$74,IF($D$4="(All)","*",$D$4),Trades!$AE$2:$AE$74,IF($G$4="(All)","*",$G$4)),"") | L35: =IFERROR(E35/SUMIFS(Trades!$AD$2:$AD$74,Trades!$C$2:$C$74,IF($D$4="(All)","*",$D$4),Trades!$AE$2:$AE$74,IF($G$4="(All)","*",$G$4))*100,"")
A36: 17 | B36: =COUNTIFS(Trades!$I$2:$I$74,$A$36,Trades!$C$2:$C$74,IF($D$4="(All)","*",$D$4),Trades!$AE$2:$AE$74,IF($G$4="(All)","*",$G$4)) | C36: =COUNTIFS(Trades!$AE$2:$AE$74,"Win",Trades!$I$2:$I$74,$A$36,Trades!$C$2:$C$74,IF($D$4="(All)","*",$D$4),Trades!$AE$2:$AE$74,IF($G$4="(All)","*",$G$4)) | D36: =IFERROR(C36/B36*100,"") | E36: =SUMIFS(Trades!$AD$2:$AD$74,Trades!$I$2:$I$74,$A$36,Trades!$C$2:$C$74,IF($D$4="(All)","*",$D$4),Trades!$AE$2:$AE$74,IF($G$4="(All)","*",$G$4)) | F36: =IFERROR(E36/B36,"") | G36: =IFERROR(AVERAGEIFS(Trades!$Z$2:$Z$74,Trades!$I$2:$I$74,$A$36,Trades!$C$2:$C$74,IF($D$4="(All)","*",$D$4),Trades!$AE$2:$AE$74,IF($G$4="(All)","*",$G$4)),"") | H36: =IFERROR(SUMIFS(Trades!$AD$2:$AD$74,Trades!$I$2:$I$74,$A$36,Trades!$AD$2:$AD$74,">0",Trades!$C$2:$C$74,IF($D$4="(All)","*",$D$4),Trades!$AE$2:$AE$74,IF($G$4="(All)","*",$G$4))/-SUMIFS(Trades!$AD$2:$AD$74,Trades!$I$2:$I$74,$A$36,Trades!$AD$2:$AD$74,"<0",Trades!$C$2:$C$74,IF($D$4="(All)","*",$D$4),Trades!$AE$2:$AE$74,IF($G$4="(All)","*",$G$4)),"") | I36: =IFERROR(AVERAGEIFS(Trades!$AH$2:$AH$74,Trades!$I$2:$I$74,$A$36,Trades!$C$2:$C$74,IF($D$4="(All)","*",$D$4),Trades!$AE$2:$AE$74,IF($G$4="(All)","*",$G$4)),"") | J36: =IFERROR(AVERAGEIFS(Trades!$AI$2:$AI$74,Trades!$I$2:$I$74,$A$36,Trades!$C$2:$C$74,IF($D$4="(All)","*",$D$4),Trades!$AE$2:$AE$74,IF($G$4="(All)","*",$G$4)),"") | K36: =IFERROR(AVERAGEIFS(Trades!$O$2:$O$74,Trades!$I$2:$I$74,$A$36,Trades!$C$2:$C$74,IF($D$4="(All)","*",$D$4),Trades!$AE$2:$AE$74,IF($G$4="(All)","*",$G$4)),"") | L36: =IFERROR(E36/SUMIFS(Trades!$AD$2:$AD$74,Trades!$C$2:$C$74,IF($D$4="(All)","*",$D$4),Trades!$AE$2:$AE$74,IF($G$4="(All)","*",$G$4))*100,"")
A37: 18 | B37: =COUNTIFS(Trades!$I$2:$I$74,$A$37,Trades!$C$2:$C$74,IF($D$4="(All)","*",$D$4),Trades!$AE$2:$AE$74,IF($G$4="(All)","*",$G$4)) | C37: =COUNTIFS(Trades!$AE$2:$AE$74,"Win",Trades!$I$2:$I$74,$A$37,Trades!$C$2:$C$74,IF($D$4="(All)","*",$D$4),Trades!$AE$2:$AE$74,IF($G$4="(All)","*",$G$4)) | D37: =IFERROR(C37/B37*100,"") | E37: =SUMIFS(Trades!$AD$2:$AD$74,Trades!$I$2:$I$74,$A$37,Trades!$C$2:$C$74,IF($D$4="(All)","*",$D$4),Trades!$AE$2:$AE$74,IF($G$4="(All)","*",$G$4)) | F37: =IFERROR(E37/B37,"") | G37: =IFERROR(AVERAGEIFS(Trades!$Z$2:$Z$74,Trades!$I$2:$I$74,$A$37,Trades!$C$2:$C$74,IF($D$4="(All)","*",$D$4),Trades!$AE$2:$AE$74,IF($G$4="(All)","*",$G$4)),"") | H37: =IFERROR(SUMIFS(Trades!$AD$2:$AD$74,Trades!$I$2:$I$74,$A$37,Trades!$AD$2:$AD$74,">0",Trades!$C$2:$C$74,IF($D$4="(All)","*",$D$4),Trades!$AE$2:$AE$74,IF($G$4="(All)","*",$G$4))/-SUMIFS(Trades!$AD$2:$AD$74,Trades!$I$2:$I$74,$A$37,Trades!$AD$2:$AD$74,"<0",Trades!$C$2:$C$74,IF($D$4="(All)","*",$D$4),Trades!$AE$2:$AE$74,IF($G$4="(All)","*",$G$4)),"") | I37: =IFERROR(AVERAGEIFS(Trades!$AH$2:$AH$74,Trades!$I$2:$I$74,$A$37,Trades!$C$2:$C$74,IF($D$4="(All)","*",$D$4),Trades!$AE$2:$AE$74,IF($G$4="(All)","*",$G$4)),"") | J37: =IFERROR(AVERAGEIFS(Trades!$AI$2:$AI$74,Trades!$I$2:$I$74,$A$37,Trades!$C$2:$C$74,IF($D$4="(All)","*",$D$4),Trades!$AE$2:$AE$74,IF($G$4="(All)","*",$G$4)),"") | K37: =IFERROR(AVERAGEIFS(Trades!$O$2:$O$74,Trades!$I$2:$I$74,$A$37,Trades!$C$2:$C$74,IF($D$4="(All)","*",$D$4),Trades!$AE$2:$AE$74,IF($G$4="(All)","*",$G$4)),"") | L37: =IFERROR(E37/SUMIFS(Trades!$AD$2:$AD$74,Trades!$C$2:$C$74,IF($D$4="(All)","*",$D$4),Trades!$AE$2:$AE$74,IF($G$4="(All)","*",$G$4))*100,"")
A38: 19 | B38: =COUNTIFS(Trades!$I$2:$I$74,$A$38,Trades!$C$2:$C$74,IF($D$4="(All)","*",$D$4),Trades!$AE$2:$AE$74,IF($G$4="(All)","*",$G$4)) | C38: =COUNTIFS(Trades!$AE$2:$AE$74,"Win",Trades!$I$2:$I$74,$A$38,Trades!$C$2:$C$74,IF($D$4="(All)","*",$D$4),Trades!$AE$2:$AE$74,IF($G$4="(All)","*",$G$4)) | D38: =IFERROR(C38/B38*100,"") | E38: =SUMIFS(Trades!$AD$2:$AD$74,Trades!$I$2:$I$74,$A$38,Trades!$C$2:$C$74,IF($D$4="(All)","*",$D$4),Trades!$AE$2:$AE$74,IF($G$4="(All)","*",$G$4)) | F38: =IFERROR(E38/B38,"") | G38: =IFERROR(AVERAGEIFS(Trades!$Z$2:$Z$74,Trades!$I$2:$I$74,$A$38,Trades!$C$2:$C$74,IF($D$4="(All)","*",$D$4),Trades!$AE$2:$AE$74,IF($G$4="(All)","*",$G$4)),"") | H38: =IFERROR(SUMIFS(Trades!$AD$2:$AD$74,Trades!$I$2:$I$74,$A$38,Trades!$AD$2:$AD$74,">0",Trades!$C$2:$C$74,IF($D$4="(All)","*",$D$4),Trades!$AE$2:$AE$74,IF($G$4="(All)","*",$G$4))/-SUMIFS(Trades!$AD$2:$AD$74,Trades!$I$2:$I$74,$A$38,Trades!$AD$2:$AD$74,"<0",Trades!$C$2:$C$74,IF($D$4="(All)","*",$D$4),Trades!$AE$2:$AE$74,IF($G$4="(All)","*",$G$4)),"") | I38: =IFERROR(AVERAGEIFS(Trades!$AH$2:$AH$74,Trades!$I$2:$I$74,$A$38,Trades!$C$2:$C$74,IF($D$4="(All)","*",$D$4),Trades!$AE$2:$AE$74,IF($G$4="(All)","*",$G$4)),"") | J38: =IFERROR(AVERAGEIFS(Trades!$AI$2:$AI$74,Trades!$I$2:$I$74,$A$38,Trades!$C$2:$C$74,IF($D$4="(All)","*",$D$4),Trades!$AE$2:$AE$74,IF($G$4="(All)","*",$G$4)),"") | K38: =IFERROR(AVERAGEIFS(Trades!$O$2:$O$74,Trades!$I$2:$I$74,$A$38,Trades!$C$2:$C$74,IF($D$4="(All)","*",$D$4),Trades!$AE$2:$AE$74,IF($G$4="(All)","*",$G$4)),"") | L38: =IFERROR(E38/SUMIFS(Trades!$AD$2:$AD$74,Trades!$C$2:$C$74,IF($D$4="(All)","*",$D$4),Trades!$AE$2:$AE$74,IF($G$4="(All)","*",$G$4))*100,"")
A39: 20 | B39: =COUNTIFS(Trades!$I$2:$I$74,$A$39,Trades!$C$2:$C$74,IF($D$4="(All)","*",$D$4),Trades!$AE$2:$AE$74,IF($G$4="(All)","*",$G$4)) | C39: =COUNTIFS(Trades!$AE$2:$AE$74,"Win",Trades!$I$2:$I$74,$A$39,Trades!$C$2:$C$74,IF($D$4="(All)","*",$D$4),Trades!$AE$2:$AE$74,IF($G$4="(All)","*",$G$4)) | D39: =IFERROR(C39/B39*100,"") | E39: =SUMIFS(Trades!$AD$2:$AD$74,Trades!$I$2:$I$74,$A$39,Trades!$C$2:$C$74,IF($D$4="(All)","*",$D$4),Trades!$AE$2:$AE$74,IF($G$4="(All)","*",$G$4)) | F39: =IFERROR(E39/B39,"") | G39: =IFERROR(AVERAGEIFS(Trades!$Z$2:$Z$74,Trades!$I$2:$I$74,$A$39,Trades!$C$2:$C$74,IF($D$4="(All)","*",$D$4),Trades!$AE$2:$AE$74,IF($G$4="(All)","*",$G$4)),"") | H39: =IFERROR(SUMIFS(Trades!$AD$2:$AD$74,Trades!$I$2:$I$74,$A$39,Trades!$AD$2:$AD$74,">0",Trades!$C$2:$C$74,IF($D$4="(All)","*",$D$4),Trades!$AE$2:$AE$74,IF($G$4="(All)","*",$G$4))/-SUMIFS(Trades!$AD$2:$AD$74,Trades!$I$2:$I$74,$A$39,Trades!$AD$2:$AD$74,"<0",Trades!$C$2:$C$74,IF($D$4="(All)","*",$D$4),Trades!$AE$2:$AE$74,IF($G$4="(All)","*",$G$4)),"") | I39: =IFERROR(AVERAGEIFS(Trades!$AH$2:$AH$74,Trades!$I$2:$I$74,$A$39,Trades!$C$2:$C$74,IF($D$4="(All)","*",$D$4),Trades!$AE$2:$AE$74,IF($G$4="(All)","*",$G$4)),"") | J39: =IFERROR(AVERAGEIFS(Trades!$AI$2:$AI$74,Trades!$I$2:$I$74,$A$39,Trades!$C$2:$C$74,IF($D$4="(All)","*",$D$4),Trades!$AE$2:$AE$74,IF($G$4="(All)","*",$G$4)),"") | K39: =IFERROR(AVERAGEIFS(Trades!$O$2:$O$74,Trades!$I$2:$I$74,$A$39,Trades!$C$2:$C$74,IF($D$4="(All)","*",$D$4),Trades!$AE$2:$AE$74,IF($G$4="(All)","*",$G$4)),"") | L39: =IFERROR(E39/SUMIFS(Trades!$AD$2:$AD$74,Trades!$C$2:$C$74,IF($D$4="(All)","*",$D$4),Trades!$AE$2:$AE$74,IF($G$4="(All)","*",$G$4))*100,"")
A40: 23 | B40: =COUNTIFS(Trades!$I$2:$I$74,$A$40,Trades!$C$2:$C$74,IF($D$4="(All)","*",$D$4),Trades!$AE$2:$AE$74,IF($G$4="(All)","*",$G$4)) | C40: =COUNTIFS(Trades!$AE$2:$AE$74,"Win",Trades!$I$2:$I$74,$A$40,Trades!$C$2:$C$74,IF($D$4="(All)","*",$D$4),Trades!$AE$2:$AE$74,IF($G$4="(All)","*",$G$4)) | D40: =IFERROR(C40/B40*100,"") | E40: =SUMIFS(Trades!$AD$2:$AD$74,Trades!$I$2:$I$74,$A$40,Trades!$C$2:$C$74,IF($D$4="(All)","*",$D$4),Trades!$AE$2:$AE$74,IF($G$4="(All)","*",$G$4)) | F40: =IFERROR(E40/B40,"") | G40: =IFERROR(AVERAGEIFS(Trades!$Z$2:$Z$74,Trades!$I$2:$I$74,$A$40,Trades!$C$2:$C$74,IF($D$4="(All)","*",$D$4),Trades!$AE$2:$AE$74,IF($G$4="(All)","*",$G$4)),"") | H40: =IFERROR(SUMIFS(Trades!$AD$2:$AD$74,Trades!$I$2:$I$74,$A$40,Trades!$AD$2:$AD$74,">0",Trades!$C$2:$C$74,IF($D$4="(All)","*",$D$4),Trades!$AE$2:$AE$74,IF($G$4="(All)","*",$G$4))/-SUMIFS(Trades!$AD$2:$AD$74,Trades!$I$2:$I$74,$A$40,Trades!$AD$2:$AD$74,"<0",Trades!$C$2:$C$74,IF($D$4="(All)","*",$D$4),Trades!$AE$2:$AE$74,IF($G$4="(All)","*",$G$4)),"") | I40: =IFERROR(AVERAGEIFS(Trades!$AH$2:$AH$74,Trades!$I$2:$I$74,$A$40,Trades!$C$2:$C$74,IF($D$4="(All)","*",$D$4),Trades!$AE$2:$AE$74,IF($G$4="(All)","*",$G$4)),"") | J40: =IFERROR(AVERAGEIFS(Trades!$AI$2:$AI$74,Trades!$I$2:$I$74,$A$40,Trades!$C$2:$C$74,IF($D$4="(All)","*",$D$4),Trades!$AE$2:$AE$74,IF($G$4="(All)","*",$G$4)),"") | K40: =IFERROR(AVERAGEIFS(Trades!$O$2:$O$74,Trades!$I$2:$I$74,$A$40,Trades!$C$2:$C$74,IF($D$4="(All)","*",$D$4),Trades!$AE$2:$AE$74,IF($G$4="(All)","*",$G$4)),"") | L40: =IFERROR(E40/SUMIFS(Trades!$AD$2:$AD$74,Trades!$C$2:$C$74,IF($D$4="(All)","*",$D$4),Trades!$AE$2:$AE$74,IF($G$4="(All)","*",$G$4))*100,"")
A41: All trades | B41: =COUNTIFS(Trades!$C$2:$C$74,IF($D$4="(All)","*",$D$4),Trades!$AE$2:$AE$74,IF($G$4="(All)","*",$G$4)) | C41: =COUNTIFS(Trades!$AE$2:$AE$74,"Win",Trades!$C$2:$C$74,IF($D$4="(All)","*",$D$4),Trades!$AE$2:$AE$74,IF($G$4="(All)","*",$G$4)) | D41: =IFERROR(C41/B41*100,"") | E41: =SUMIFS(Trades!$AD$2:$AD$74,Trades!$C$2:$C$74,IF($D$4="(All)","*",$D$4),Trades!$AE$2:$AE$74,IF($G$4="(All)","*",$G$4)) | F41: =IFERROR(E41/B41,"") | G41: =IFERROR(AVERAGEIFS(Trades!$Z$2:$Z$74,Trades!$C$2:$C$74,IF($D$4="(All)","*",$D$4),Trades!$AE$2:$AE$74,IF($G$4="(All)","*",$G$4)),"") | H41: =IFERROR(SUMIFS(Trades!$AD$2:$AD$74,Trades!$AD$2:$AD$74,">0",Trades!$C$2:$C$74,IF($D$4="(All)","*",$D$4),Trades!$AE$2:$AE$74,IF($G$4="(All)","*",$G$4))/-SUMIFS(Trades!$AD$2:$AD$74,Trades!$AD$2:$AD$74,"<0",Trades!$C$2:$C$74,IF($D$4="(All)","*",$D$4),Trades!$AE$2:$AE$74,IF($G$4="(All)","*",$G$4)),"") | I41: =IFERROR(AVERAGEIFS(Trades!$AH$2:$AH$74,Trades!$C$2:$C$74,IF($D$4="(All)","*",$D$4),Trades!$AE$2:$AE$74,IF($G$4="(All)","*",$G$4)),"") | J41: =IFERROR(AVERAGEIFS(Trades!$AI$2:$AI$74,Trades!$C$2:$C$74,IF($D$4="(All)","*",$D$4),Trades!$AE$2:$AE$74,IF($G$4="(All)","*",$G$4)),"") | K41: =IFERROR(AVERAGEIFS(Trades!$O$2:$O$74,Trades!$C$2:$C$74,IF($D$4="(All)","*",$D$4),Trades!$AE$2:$AE$74,IF($G$4="(All)","*",$G$4)),"") | L41: =IFERROR(E41/SUMIFS(Trades!$AD$2:$AD$74,Trades!$C$2:$C$74,IF($D$4="(All)","*",$D$4),Trades!$AE$2:$AE$74,IF($G$4="(All)","*",$G$4))*100,"")
A44: By month
A45: Month | B45: Trades | C45: Wins | D45: Win % | E45: Net | F45: Expectancy | G45: Avg R | H45: Profit factor | I45: Avg MFE | J45: Avg MAE | K45: Avg dur (min) | L45: Share of net
A46: 2026-07 | B46: =COUNTIFS(Trades!$L$2:$L$74,$A$46,Trades!$C$2:$C$74,IF($D$4="(All)","*",$D$4),Trades!$AE$2:$AE$74,IF($G$4="(All)","*",$G$4)) | C46: =COUNTIFS(Trades!$AE$2:$AE$74,"Win",Trades!$L$2:$L$74,$A$46,Trades!$C$2:$C$74,IF($D$4="(All)","*",$D$4),Trades!$AE$2:$AE$74,IF($G$4="(All)","*",$G$4)) | D46: =IFERROR(C46/B46*100,"") | E46: =SUMIFS(Trades!$AD$2:$AD$74,Trades!$L$2:$L$74,$A$46,Trades!$C$2:$C$74,IF($D$4="(All)","*",$D$4),Trades!$AE$2:$AE$74,IF($G$4="(All)","*",$G$4)) | F46: =IFERROR(E46/B46,"") | G46: =IFERROR(AVERAGEIFS(Trades!$Z$2:$Z$74,Trades!$L$2:$L$74,$A$46,Trades!$C$2:$C$74,IF($D$4="(All)","*",$D$4),Trades!$AE$2:$AE$74,IF($G$4="(All)","*",$G$4)),"") | H46: =IFERROR(SUMIFS(Trades!$AD$2:$AD$74,Trades!$L$2:$L$74,$A$46,Trades!$AD$2:$AD$74,">0",Trades!$C$2:$C$74,IF($D$4="(All)","*",$D$4),Trades!$AE$2:$AE$74,IF($G$4="(All)","*",$G$4))/-SUMIFS(Trades!$AD$2:$AD$74,Trades!$L$2:$L$74,$A$46,Trades!$AD$2:$AD$74,"<0",Trades!$C$2:$C$74,IF($D$4="(All)","*",$D$4),Trades!$AE$2:$AE$74,IF($G$4="(All)","*",$G$4)),"") | I46: =IFERROR(AVERAGEIFS(Trades!$AH$2:$AH$74,Trades!$L$2:$L$74,$A$46,Trades!$C$2:$C$74,IF($D$4="(All)","*",$D$4),Trades!$AE$2:$AE$74,IF($G$4="(All)","*",$G$4)),"") | J46: =IFERROR(AVERAGEIFS(Trades!$AI$2:$AI$74,Trades!$L$2:$L$74,$A$46,Trades!$C$2:$C$74,IF($D$4="(All)","*",$D$4),Trades!$AE$2:$AE$74,IF($G$4="(All)","*",$G$4)),"") | K46: =IFERROR(AVERAGEIFS(Trades!$O$2:$O$74,Trades!$L$2:$L$74,$A$46,Trades!$C$2:$C$74,IF($D$4="(All)","*",$D$4),Trades!$AE$2:$AE$74,IF($G$4="(All)","*",$G$4)),"") | L46: =IFERROR(E46/SUMIFS(Trades!$AD$2:$AD$74,Trades!$C$2:$C$74,IF($D$4="(All)","*",$D$4),Trades!$AE$2:$AE$74,IF($G$4="(All)","*",$G$4))*100,"")
A47: 2026-08 | B47: =COUNTIFS(Trades!$L$2:$L$74,$A$47,Trades!$C$2:$C$74,IF($D$4="(All)","*",$D$4),Trades!$AE$2:$AE$74,IF($G$4="(All)","*",$G$4)) | C47: =COUNTIFS(Trades!$AE$2:$AE$74,"Win",Trades!$L$2:$L$74,$A$47,Trades!$C$2:$C$74,IF($D$4="(All)","*",$D$4),Trades!$AE$2:$AE$74,IF($G$4="(All)","*",$G$4)) | D47: =IFERROR(C47/B47*100,"") | E47: =SUMIFS(Trades!$AD$2:$AD$74,Trades!$L$2:$L$74,$A$47,Trades!$C$2:$C$74,IF($D$4="(All)","*",$D$4),Trades!$AE$2:$AE$74,IF($G$4="(All)","*",$G$4)) | F47: =IFERROR(E47/B47,"") | G47: =IFERROR(AVERAGEIFS(Trades!$Z$2:$Z$74,Trades!$L$2:$L$74,$A$47,Trades!$C$2:$C$74,IF($D$4="(All)","*",$D$4),Trades!$AE$2:$AE$74,IF($G$4="(All)","*",$G$4)),"") | H47: =IFERROR(SUMIFS(Trades!$AD$2:$AD$74,Trades!$L$2:$L$74,$A$47,Trades!$AD$2:$AD$74,">0",Trades!$C$2:$C$74,IF($D$4="(All)","*",$D$4),Trades!$AE$2:$AE$74,IF($G$4="(All)","*",$G$4))/-SUMIFS(Trades!$AD$2:$AD$74,Trades!$L$2:$L$74,$A$47,Trades!$AD$2:$AD$74,"<0",Trades!$C$2:$C$74,IF($D$4="(All)","*",$D$4),Trades!$AE$2:$AE$74,IF($G$4="(All)","*",$G$4)),"") | I47: =IFERROR(AVERAGEIFS(Trades!$AH$2:$AH$74,Trades!$L$2:$L$74,$A$47,Trades!$C$2:$C$74,IF($D$4="(All)","*",$D$4),Trades!$AE$2:$AE$74,IF($G$4="(All)","*",$G$4)),"") | J47: =IFERROR(AVERAGEIFS(Trades!$AI$2:$AI$74,Trades!$L$2:$L$74,$A$47,Trades!$C$2:$C$74,IF($D$4="(All)","*",$D$4),Trades!$AE$2:$AE$74,IF($G$4="(All)","*",$G$4)),"") | K47: =IFERROR(AVERAGEIFS(Trades!$O$2:$O$74,Trades!$L$2:$L$74,$A$47,Trades!$C$2:$C$74,IF($D$4="(All)","*",$D$4),Trades!$AE$2:$AE$74,IF($G$4="(All)","*",$G$4)),"") | L47: =IFERROR(E47/SUMIFS(Trades!$AD$2:$AD$74,Trades!$C$2:$C$74,IF($D$4="(All)","*",$D$4),Trades!$AE$2:$AE$74,IF($G$4="(All)","*",$G$4))*100,"")
A48: All trades | B48: =COUNTIFS(Trades!$C$2:$C$74,IF($D$4="(All)","*",$D$4),Trades!$AE$2:$AE$74,IF($G$4="(All)","*",$G$4)) | C48: =COUNTIFS(Trades!$AE$2:$AE$74,"Win",Trades!$C$2:$C$74,IF($D$4="(All)","*",$D$4),Trades!$AE$2:$AE$74,IF($G$4="(All)","*",$G$4)) | D48: =IFERROR(C48/B48*100,"") | E48: =SUMIFS(Trades!$AD$2:$AD$74,Trades!$C$2:$C$74,IF($D$4="(All)","*",$D$4),Trades!$AE$2:$AE$74,IF($G$4="(All)","*",$G$4)) | F48: =IFERROR(E48/B48,"") | G48: =IFERROR(AVERAGEIFS(Trades!$Z$2:$Z$74,Trades!$C$2:$C$74,IF($D$4="(All)","*",$D$4),Trades!$AE$2:$AE$74,IF($G$4="(All)","*",$G$4)),"") | H48: =IFERROR(SUMIFS(Trades!$AD$2:$AD$74,Trades!$AD$2:$AD$74,">0",Trades!$C$2:$C$74,IF($D$4="(All)","*",$D$4),Trades!$AE$2:$AE$74,IF($G$4="(All)","*",$G$4))/-SUMIFS(Trades!$AD$2:$AD$74,Trades!$AD$2:$AD$74,"<0",Trades!$C$2:$C$74,IF($D$4="(All)","*",$D$4),Trades!$AE$2:$AE$74,IF($G$4="(All)","*",$G$4)),"") | I48: =IFERROR(AVERAGEIFS(Trades!$AH$2:$AH$74,Trades!$C$2:$C$74,IF($D$4="(All)","*",$D$4),Trades!$AE$2:$AE$74,IF($G$4="(All)","*",$G$4)),"") | J48: =IFERROR(AVERAGEIFS(Trades!$AI$2:$AI$74,Trades!$C$2:$C$74,IF($D$4="(All)","*",$D$4),Trades!$AE$2:$AE$74,IF($G$4="(All)","*",$G$4)),"") | K48: =IFERROR(AVERAGEIFS(Trades!$O$2:$O$74,Trades!$C$2:$C$74,IF($D$4="(All)","*",$D$4),Trades!$AE$2:$AE$74,IF($G$4="(All)","*",$G$4)),"") | L48: =IFERROR(E48/SUMIFS(Trades!$AD$2:$AD$74,Trades!$C$2:$C$74,IF($D$4="(All)","*",$D$4),Trades!$AE$2:$AE$74,IF($G$4="(All)","*",$G$4))*100,"")

Sheet Shape of results
A1: Distribution of outcomes
A2: Where the results sit, not just their average.
A4: Filters | C4: Symbol | D4: (All) | F4: Outcome | G4: (All) | I4: Change either dropdown - every grid below recalculates.
A6: By r band | E6: The distribution behind the expectancy figure.
A7: R band | B7: Trades | C7: Wins | D7: Win % | E7: Net | F7: Expectancy | G7: Avg R | H7: Profit factor | I7: Avg MFE | J7: Avg MAE | K7: Avg dur (min) | L7: Share of net
A8: A. <= -1.5R | B8: =COUNTIFS(Trades!$AA$2:$AA$74,$A$8,Trades!$C$2:$C$74,IF($D$4="(All)","*",$D$4),Trades!$AE$2:$AE$74,IF($G$4="(All)","*",$G$4)) | C8: =COUNTIFS(Trades!$AE$2:$AE$74,"Win",Trades!$AA$2:$AA$74,$A$8,Trades!$C$2:$C$74,IF($D$4="(All)","*",$D$4),Trades!$AE$2:$AE$74,IF($G$4="(All)","*",$G$4)) | D8: =IFERROR(C8/B8*100,"") | E8: =SUMIFS(Trades!$AD$2:$AD$74,Trades!$AA$2:$AA$74,$A$8,Trades!$C$2:$C$74,IF($D$4="(All)","*",$D$4),Trades!$AE$2:$AE$74,IF($G$4="(All)","*",$G$4)) | F8: =IFERROR(E8/B8,"") | G8: =IFERROR(AVERAGEIFS(Trades!$Z$2:$Z$74,Trades!$AA$2:$AA$74,$A$8,Trades!$C$2:$C$74,IF($D$4="(All)","*",$D$4),Trades!$AE$2:$AE$74,IF($G$4="(All)","*",$G$4)),"") | H8: =IFERROR(SUMIFS(Trades!$AD$2:$AD$74,Trades!$AA$2:$AA$74,$A$8,Trades!$AD$2:$AD$74,">0",Trades!$C$2:$C$74,IF($D$4="(All)","*",$D$4),Trades!$AE$2:$AE$74,IF($G$4="(All)","*",$G$4))/-SUMIFS(Trades!$AD$2:$AD$74,Trades!$AA$2:$AA$74,$A$8,Trades!$AD$2:$AD$74,"<0",Trades!$C$2:$C$74,IF($D$4="(All)","*",$D$4),Trades!$AE$2:$AE$74,IF($G$4="(All)","*",$G$4)),"") | I8: =IFERROR(AVERAGEIFS(Trades!$AH$2:$AH$74,Trades!$AA$2:$AA$74,$A$8,Trades!$C$2:$C$74,IF($D$4="(All)","*",$D$4),Trades!$AE$2:$AE$74,IF($G$4="(All)","*",$G$4)),"") | J8: =IFERROR(AVERAGEIFS(Trades!$AI$2:$AI$74,Trades!$AA$2:$AA$74,$A$8,Trades!$C$2:$C$74,IF($D$4="(All)","*",$D$4),Trades!$AE$2:$AE$74,IF($G$4="(All)","*",$G$4)),"") | K8: =IFERROR(AVERAGEIFS(Trades!$O$2:$O$74,Trades!$AA$2:$AA$74,$A$8,Trades!$C$2:$C$74,IF($D$4="(All)","*",$D$4),Trades!$AE$2:$AE$74,IF($G$4="(All)","*",$G$4)),"") | L8: =IFERROR(E8/SUMIFS(Trades!$AD$2:$AD$74,Trades!$C$2:$C$74,IF($D$4="(All)","*",$D$4),Trades!$AE$2:$AE$74,IF($G$4="(All)","*",$G$4))*100,"")
A9: B. -1.5R..-1R | B9: =COUNTIFS(Trades!$AA$2:$AA$74,$A$9,Trades!$C$2:$C$74,IF($D$4="(All)","*",$D$4),Trades!$AE$2:$AE$74,IF($G$4="(All)","*",$G$4)) | C9: =COUNTIFS(Trades!$AE$2:$AE$74,"Win",Trades!$AA$2:$AA$74,$A$9,Trades!$C$2:$C$74,IF($D$4="(All)","*",$D$4),Trades!$AE$2:$AE$74,IF($G$4="(All)","*",$G$4)) | D9: =IFERROR(C9/B9*100,"") | E9: =SUMIFS(Trades!$AD$2:$AD$74,Trades!$AA$2:$AA$74,$A$9,Trades!$C$2:$C$74,IF($D$4="(All)","*",$D$4),Trades!$AE$2:$AE$74,IF($G$4="(All)","*",$G$4)) | F9: =IFERROR(E9/B9,"") | G9: =IFERROR(AVERAGEIFS(Trades!$Z$2:$Z$74,Trades!$AA$2:$AA$74,$A$9,Trades!$C$2:$C$74,IF($D$4="(All)","*",$D$4),Trades!$AE$2:$AE$74,IF($G$4="(All)","*",$G$4)),"") | H9: =IFERROR(SUMIFS(Trades!$AD$2:$AD$74,Trades!$AA$2:$AA$74,$A$9,Trades!$AD$2:$AD$74,">0",Trades!$C$2:$C$74,IF($D$4="(All)","*",$D$4),Trades!$AE$2:$AE$74,IF($G$4="(All)","*",$G$4))/-SUMIFS(Trades!$AD$2:$AD$74,Trades!$AA$2:$AA$74,$A$9,Trades!$AD$2:$AD$74,"<0",Trades!$C$2:$C$74,IF($D$4="(All)","*",$D$4),Trades!$AE$2:$AE$74,IF($G$4="(All)","*",$G$4)),"") | I9: =IFERROR(AVERAGEIFS(Trades!$AH$2:$AH$74,Trades!$AA$2:$AA$74,$A$9,Trades!$C$2:$C$74,IF($D$4="(All)","*",$D$4),Trades!$AE$2:$AE$74,IF($G$4="(All)","*",$G$4)),"") | J9: =IFERROR(AVERAGEIFS(Trades!$AI$2:$AI$74,Trades!$AA$2:$AA$74,$A$9,Trades!$C$2:$C$74,IF($D$4="(All)","*",$D$4),Trades!$AE$2:$AE$74,IF($G$4="(All)","*",$G$4)),"") | K9: =IFERROR(AVERAGEIFS(Trades!$O$2:$O$74,Trades!$AA$2:$AA$74,$A$9,Trades!$C$2:$C$74,IF($D$4="(All)","*",$D$4),Trades!$AE$2:$AE$74,IF($G$4="(All)","*",$G$4)),"") | L9: =IFERROR(E9/SUMIFS(Trades!$AD$2:$AD$74,Trades!$C$2:$C$74,IF($D$4="(All)","*",$D$4),Trades!$AE$2:$AE$74,IF($G$4="(All)","*",$G$4))*100,"")
A10: C. -1R..-0.5R | B10: =COUNTIFS(Trades!$AA$2:$AA$74,$A$10,Trades!$C$2:$C$74,IF($D$4="(All)","*",$D$4),Trades!$AE$2:$AE$74,IF($G$4="(All)","*",$G$4)) | C10: =COUNTIFS(Trades!$AE$2:$AE$74,"Win",Trades!$AA$2:$AA$74,$A$10,Trades!$C$2:$C$74,IF($D$4="(All)","*",$D$4),Trades!$AE$2:$AE$74,IF($G$4="(All)","*",$G$4)) | D10: =IFERROR(C10/B10*100,"") | E10: =SUMIFS(Trades!$AD$2:$AD$74,Trades!$AA$2:$AA$74,$A$10,Trades!$C$2:$C$74,IF($D$4="(All)","*",$D$4),Trades!$AE$2:$AE$74,IF($G$4="(All)","*",$G$4)) | F10: =IFERROR(E10/B10,"") | G10: =IFERROR(AVERAGEIFS(Trades!$Z$2:$Z$74,Trades!$AA$2:$AA$74,$A$10,Trades!$C$2:$C$74,IF($D$4="(All)","*",$D$4),Trades!$AE$2:$AE$74,IF($G$4="(All)","*",$G$4)),"") | H10: =IFERROR(SUMIFS(Trades!$AD$2:$AD$74,Trades!$AA$2:$AA$74,$A$10,Trades!$AD$2:$AD$74,">0",Trades!$C$2:$C$74,IF($D$4="(All)","*",$D$4),Trades!$AE$2:$AE$74,IF($G$4="(All)","*",$G$4))/-SUMIFS(Trades!$AD$2:$AD$74,Trades!$AA$2:$AA$74,$A$10,Trades!$AD$2:$AD$74,"<0",Trades!$C$2:$C$74,IF($D$4="(All)","*",$D$4),Trades!$AE$2:$AE$74,IF($G$4="(All)","*",$G$4)),"") | I10: =IFERROR(AVERAGEIFS(Trades!$AH$2:$AH$74,Trades!$AA$2:$AA$74,$A$10,Trades!$C$2:$C$74,IF($D$4="(All)","*",$D$4),Trades!$AE$2:$AE$74,IF($G$4="(All)","*",$G$4)),"") | J10: =IFERROR(AVERAGEIFS(Trades!$AI$2:$AI$74,Trades!$AA$2:$AA$74,$A$10,Trades!$C$2:$C$74,IF($D$4="(All)","*",$D$4),Trades!$AE$2:$AE$74,IF($G$4="(All)","*",$G$4)),"") | K10: =IFERROR(AVERAGEIFS(Trades!$O$2:$O$74,Trades!$AA$2:$AA$74,$A$10,Trades!$C$2:$C$74,IF($D$4="(All)","*",$D$4),Trades!$AE$2:$AE$74,IF($G$4="(All)","*",$G$4)),"") | L10: =IFERROR(E10/SUMIFS(Trades!$AD$2:$AD$74,Trades!$C$2:$C$74,IF($D$4="(All)","*",$D$4),Trades!$AE$2:$AE$74,IF($G$4="(All)","*",$G$4))*100,"")
A11: D. -0.5R..0 | B11: =COUNTIFS(Trades!$AA$2:$AA$74,$A$11,Trades!$C$2:$C$74,IF($D$4="(All)","*",$D$4),Trades!$AE$2:$AE$74,IF($G$4="(All)","*",$G$4)) | C11: =COUNTIFS(Trades!$AE$2:$AE$74,"Win",Trades!$AA$2:$AA$74,$A$11,Trades!$C$2:$C$74,IF($D$4="(All)","*",$D$4),Trades!$AE$2:$AE$74,IF($G$4="(All)","*",$G$4)) | D11: =IFERROR(C11/B11*100,"") | E11: =SUMIFS(Trades!$AD$2:$AD$74,Trades!$AA$2:$AA$74,$A$11,Trades!$C$2:$C$74,IF($D$4="(All)","*",$D$4),Trades!$AE$2:$AE$74,IF($G$4="(All)","*",$G$4)) | F11: =IFERROR(E11/B11,"") | G11: =IFERROR(AVERAGEIFS(Trades!$Z$2:$Z$74,Trades!$AA$2:$AA$74,$A$11,Trades!$C$2:$C$74,IF($D$4="(All)","*",$D$4),Trades!$AE$2:$AE$74,IF($G$4="(All)","*",$G$4)),"") | H11: =IFERROR(SUMIFS(Trades!$AD$2:$AD$74,Trades!$AA$2:$AA$74,$A$11,Trades!$AD$2:$AD$74,">0",Trades!$C$2:$C$74,IF($D$4="(All)","*",$D$4),Trades!$AE$2:$AE$74,IF($G$4="(All)","*",$G$4))/-SUMIFS(Trades!$AD$2:$AD$74,Trades!$AA$2:$AA$74,$A$11,Trades!$AD$2:$AD$74,"<0",Trades!$C$2:$C$74,IF($D$4="(All)","*",$D$4),Trades!$AE$2:$AE$74,IF($G$4="(All)","*",$G$4)),"") | I11: =IFERROR(AVERAGEIFS(Trades!$AH$2:$AH$74,Trades!$AA$2:$AA$74,$A$11,Trades!$C$2:$C$74,IF($D$4="(All)","*",$D$4),Trades!$AE$2:$AE$74,IF($G$4="(All)","*",$G$4)),"") | J11: =IFERROR(AVERAGEIFS(Trades!$AI$2:$AI$74,Trades!$AA$2:$AA$74,$A$11,Trades!$C$2:$C$74,IF($D$4="(All)","*",$D$4),Trades!$AE$2:$AE$74,IF($G$4="(All)","*",$G$4)),"") | K11: =IFERROR(AVERAGEIFS(Trades!$O$2:$O$74,Trades!$AA$2:$AA$74,$A$11,Trades!$C$2:$C$74,IF($D$4="(All)","*",$D$4),Trades!$AE$2:$AE$74,IF($G$4="(All)","*",$G$4)),"") | L11: =IFERROR(E11/SUMIFS(Trades!$AD$2:$AD$74,Trades!$C$2:$C$74,IF($D$4="(All)","*",$D$4),Trades!$AE$2:$AE$74,IF($G$4="(All)","*",$G$4))*100,"")
A12: E. Breakeven | B12: =COUNTIFS(Trades!$AA$2:$AA$74,$A$12,Trades!$C$2:$C$74,IF($D$4="(All)","*",$D$4),Trades!$AE$2:$AE$74,IF($G$4="(All)","*",$G$4)) | C12: =COUNTIFS(Trades!$AE$2:$AE$74,"Win",Trades!$AA$2:$AA$74,$A$12,Trades!$C$2:$C$74,IF($D$4="(All)","*",$D$4),Trades!$AE$2:$AE$74,IF($G$4="(All)","*",$G$4)) | D12: =IFERROR(C12/B12*100,"") | E12: =SUMIFS(Trades!$AD$2:$AD$74,Trades!$AA$2:$AA$74,$A$12,Trades!$C$2:$C$74,IF($D$4="(All)","*",$D$4),Trades!$AE$2:$AE$74,IF($G$4="(All)","*",$G$4)) | F12: =IFERROR(E12/B12,"") | G12: =IFERROR(AVERAGEIFS(Trades!$Z$2:$Z$74,Trades!$AA$2:$AA$74,$A$12,Trades!$C$2:$C$74,IF($D$4="(All)","*",$D$4),Trades!$AE$2:$AE$74,IF($G$4="(All)","*",$G$4)),"") | H12: =IFERROR(SUMIFS(Trades!$AD$2:$AD$74,Trades!$AA$2:$AA$74,$A$12,Trades!$AD$2:$AD$74,">0",Trades!$C$2:$C$74,IF($D$4="(All)","*",$D$4),Trades!$AE$2:$AE$74,IF($G$4="(All)","*",$G$4))/-SUMIFS(Trades!$AD$2:$AD$74,Trades!$AA$2:$AA$74,$A$12,Trades!$AD$2:$AD$74,"<0",Trades!$C$2:$C$74,IF($D$4="(All)","*",$D$4),Trades!$AE$2:$AE$74,IF($G$4="(All)","*",$G$4)),"") | I12: =IFERROR(AVERAGEIFS(Trades!$AH$2:$AH$74,Trades!$AA$2:$AA$74,$A$12,Trades!$C$2:$C$74,IF($D$4="(All)","*",$D$4),Trades!$AE$2:$AE$74,IF($G$4="(All)","*",$G$4)),"") | J12: =IFERROR(AVERAGEIFS(Trades!$AI$2:$AI$74,Trades!$AA$2:$AA$74,$A$12,Trades!$C$2:$C$74,IF($D$4="(All)","*",$D$4),Trades!$AE$2:$AE$74,IF($G$4="(All)","*",$G$4)),"") | K12: =IFERROR(AVERAGEIFS(Trades!$O$2:$O$74,Trades!$AA$2:$AA$74,$A$12,Trades!$C$2:$C$74,IF($D$4="(All)","*",$D$4),Trades!$AE$2:$AE$74,IF($G$4="(All)","*",$G$4)),"") | L12: =IFERROR(E12/SUMIFS(Trades!$AD$2:$AD$74,Trades!$C$2:$C$74,IF($D$4="(All)","*",$D$4),Trades!$AE$2:$AE$74,IF($G$4="(All)","*",$G$4))*100,"")
A13: F. 0..0.5R | B13: =COUNTIFS(Trades!$AA$2:$AA$74,$A$13,Trades!$C$2:$C$74,IF($D$4="(All)","*",$D$4),Trades!$AE$2:$AE$74,IF($G$4="(All)","*",$G$4)) | C13: =COUNTIFS(Trades!$AE$2:$AE$74,"Win",Trades!$AA$2:$AA$74,$A$13,Trades!$C$2:$C$74,IF($D$4="(All)","*",$D$4),Trades!$AE$2:$AE$74,IF($G$4="(All)","*",$G$4)) | D13: =IFERROR(C13/B13*100,"") | E13: =SUMIFS(Trades!$AD$2:$AD$74,Trades!$AA$2:$AA$74,$A$13,Trades!$C$2:$C$74,IF($D$4="(All)","*",$D$4),Trades!$AE$2:$AE$74,IF($G$4="(All)","*",$G$4)) | F13: =IFERROR(E13/B13,"") | G13: =IFERROR(AVERAGEIFS(Trades!$Z$2:$Z$74,Trades!$AA$2:$AA$74,$A$13,Trades!$C$2:$C$74,IF($D$4="(All)","*",$D$4),Trades!$AE$2:$AE$74,IF($G$4="(All)","*",$G$4)),"") | H13: =IFERROR(SUMIFS(Trades!$AD$2:$AD$74,Trades!$AA$2:$AA$74,$A$13,Trades!$AD$2:$AD$74,">0",Trades!$C$2:$C$74,IF($D$4="(All)","*",$D$4),Trades!$AE$2:$AE$74,IF($G$4="(All)","*",$G$4))/-SUMIFS(Trades!$AD$2:$AD$74,Trades!$AA$2:$AA$74,$A$13,Trades!$AD$2:$AD$74,"<0",Trades!$C$2:$C$74,IF($D$4="(All)","*",$D$4),Trades!$AE$2:$AE$74,IF($G$4="(All)","*",$G$4)),"") | I13: =IFERROR(AVERAGEIFS(Trades!$AH$2:$AH$74,Trades!$AA$2:$AA$74,$A$13,Trades!$C$2:$C$74,IF($D$4="(All)","*",$D$4),Trades!$AE$2:$AE$74,IF($G$4="(All)","*",$G$4)),"") | J13: =IFERROR(AVERAGEIFS(Trades!$AI$2:$AI$74,Trades!$AA$2:$AA$74,$A$13,Trades!$C$2:$C$74,IF($D$4="(All)","*",$D$4),Trades!$AE$2:$AE$74,IF($G$4="(All)","*",$G$4)),"") | K13: =IFERROR(AVERAGEIFS(Trades!$O$2:$O$74,Trades!$AA$2:$AA$74,$A$13,Trades!$C$2:$C$74,IF($D$4="(All)","*",$D$4),Trades!$AE$2:$AE$74,IF($G$4="(All)","*",$G$4)),"") | L13: =IFERROR(E13/SUMIFS(Trades!$AD$2:$AD$74,Trades!$C$2:$C$74,IF($D$4="(All)","*",$D$4),Trades!$AE$2:$AE$74,IF($G$4="(All)","*",$G$4))*100,"")
A14: H. 1R..2R | B14: =COUNTIFS(Trades!$AA$2:$AA$74,$A$14,Trades!$C$2:$C$74,IF($D$4="(All)","*",$D$4),Trades!$AE$2:$AE$74,IF($G$4="(All)","*",$G$4)) | C14: =COUNTIFS(Trades!$AE$2:$AE$74,"Win",Trades!$AA$2:$AA$74,$A$14,Trades!$C$2:$C$74,IF($D$4="(All)","*",$D$4),Trades!$AE$2:$AE$74,IF($G$4="(All)","*",$G$4)) | D14: =IFERROR(C14/B14*100,"") | E14: =SUMIFS(Trades!$AD$2:$AD$74,Trades!$AA$2:$AA$74,$A$14,Trades!$C$2:$C$74,IF($D$4="(All)","*",$D$4),Trades!$AE$2:$AE$74,IF($G$4="(All)","*",$G$4)) | F14: =IFERROR(E14/B14,"") | G14: =IFERROR(AVERAGEIFS(Trades!$Z$2:$Z$74,Trades!$AA$2:$AA$74,$A$14,Trades!$C$2:$C$74,IF($D$4="(All)","*",$D$4),Trades!$AE$2:$AE$74,IF($G$4="(All)","*",$G$4)),"") | H14: =IFERROR(SUMIFS(Trades!$AD$2:$AD$74,Trades!$AA$2:$AA$74,$A$14,Trades!$AD$2:$AD$74,">0",Trades!$C$2:$C$74,IF($D$4="(All)","*",$D$4),Trades!$AE$2:$AE$74,IF($G$4="(All)","*",$G$4))/-SUMIFS(Trades!$AD$2:$AD$74,Trades!$AA$2:$AA$74,$A$14,Trades!$AD$2:$AD$74,"<0",Trades!$C$2:$C$74,IF($D$4="(All)","*",$D$4),Trades!$AE$2:$AE$74,IF($G$4="(All)","*",$G$4)),"") | I14: =IFERROR(AVERAGEIFS(Trades!$AH$2:$AH$74,Trades!$AA$2:$AA$74,$A$14,Trades!$C$2:$C$74,IF($D$4="(All)","*",$D$4),Trades!$AE$2:$AE$74,IF($G$4="(All)","*",$G$4)),"") | J14: =IFERROR(AVERAGEIFS(Trades!$AI$2:$AI$74,Trades!$AA$2:$AA$74,$A$14,Trades!$C$2:$C$74,IF($D$4="(All)","*",$D$4),Trades!$AE$2:$AE$74,IF($G$4="(All)","*",$G$4)),"") | K14: =IFERROR(AVERAGEIFS(Trades!$O$2:$O$74,Trades!$AA$2:$AA$74,$A$14,Trades!$C$2:$C$74,IF($D$4="(All)","*",$D$4),Trades!$AE$2:$AE$74,IF($G$4="(All)","*",$G$4)),"") | L14: =IFERROR(E14/SUMIFS(Trades!$AD$2:$AD$74,Trades!$C$2:$C$74,IF($D$4="(All)","*",$D$4),Trades!$AE$2:$AE$74,IF($G$4="(All)","*",$G$4))*100,"")
A15: I. 2R..3R | B15: =COUNTIFS(Trades!$AA$2:$AA$74,$A$15,Trades!$C$2:$C$74,IF($D$4="(All)","*",$D$4),Trades!$AE$2:$AE$74,IF($G$4="(All)","*",$G$4)) | C15: =COUNTIFS(Trades!$AE$2:$AE$74,"Win",Trades!$AA$2:$AA$74,$A$15,Trades!$C$2:$C$74,IF($D$4="(All)","*",$D$4),Trades!$AE$2:$AE$74,IF($G$4="(All)","*",$G$4)) | D15: =IFERROR(C15/B15*100,"") | E15: =SUMIFS(Trades!$AD$2:$AD$74,Trades!$AA$2:$AA$74,$A$15,Trades!$C$2:$C$74,IF($D$4="(All)","*",$D$4),Trades!$AE$2:$AE$74,IF($G$4="(All)","*",$G$4)) | F15: =IFERROR(E15/B15,"") | G15: =IFERROR(AVERAGEIFS(Trades!$Z$2:$Z$74,Trades!$AA$2:$AA$74,$A$15,Trades!$C$2:$C$74,IF($D$4="(All)","*",$D$4),Trades!$AE$2:$AE$74,IF($G$4="(All)","*",$G$4)),"") | H15: =IFERROR(SUMIFS(Trades!$AD$2:$AD$74,Trades!$AA$2:$AA$74,$A$15,Trades!$AD$2:$AD$74,">0",Trades!$C$2:$C$74,IF($D$4="(All)","*",$D$4),Trades!$AE$2:$AE$74,IF($G$4="(All)","*",$G$4))/-SUMIFS(Trades!$AD$2:$AD$74,Trades!$AA$2:$AA$74,$A$15,Trades!$AD$2:$AD$74,"<0",Trades!$C$2:$C$74,IF($D$4="(All)","*",$D$4),Trades!$AE$2:$AE$74,IF($G$4="(All)","*",$G$4)),"") | I15: =IFERROR(AVERAGEIFS(Trades!$AH$2:$AH$74,Trades!$AA$2:$AA$74,$A$15,Trades!$C$2:$C$74,IF($D$4="(All)","*",$D$4),Trades!$AE$2:$AE$74,IF($G$4="(All)","*",$G$4)),"") | J15: =IFERROR(AVERAGEIFS(Trades!$AI$2:$AI$74,Trades!$AA$2:$AA$74,$A$15,Trades!$C$2:$C$74,IF($D$4="(All)","*",$D$4),Trades!$AE$2:$AE$74,IF($G$4="(All)","*",$G$4)),"") | K15: =IFERROR(AVERAGEIFS(Trades!$O$2:$O$74,Trades!$AA$2:$AA$74,$A$15,Trades!$C$2:$C$74,IF($D$4="(All)","*",$D$4),Trades!$AE$2:$AE$74,IF($G$4="(All)","*",$G$4)),"") | L15: =IFERROR(E15/SUMIFS(Trades!$AD$2:$AD$74,Trades!$C$2:$C$74,IF($D$4="(All)","*",$D$4),Trades!$AE$2:$AE$74,IF($G$4="(All)","*",$G$4))*100,"")
A16: J. >= 3R | B16: =COUNTIFS(Trades!$AA$2:$AA$74,$A$16,Trades!$C$2:$C$74,IF($D$4="(All)","*",$D$4),Trades!$AE$2:$AE$74,IF($G$4="(All)","*",$G$4)) | C16: =COUNTIFS(Trades!$AE$2:$AE$74,"Win",Trades!$AA$2:$AA$74,$A$16,Trades!$C$2:$C$74,IF($D$4="(All)","*",$D$4),Trades!$AE$2:$AE$74,IF($G$4="(All)","*",$G$4)) | D16: =IFERROR(C16/B16*100,"") | E16: =SUMIFS(Trades!$AD$2:$AD$74,Trades!$AA$2:$AA$74,$A$16,Trades!$C$2:$C$74,IF($D$4="(All)","*",$D$4),Trades!$AE$2:$AE$74,IF($G$4="(All)","*",$G$4)) | F16: =IFERROR(E16/B16,"") | G16: =IFERROR(AVERAGEIFS(Trades!$Z$2:$Z$74,Trades!$AA$2:$AA$74,$A$16,Trades!$C$2:$C$74,IF($D$4="(All)","*",$D$4),Trades!$AE$2:$AE$74,IF($G$4="(All)","*",$G$4)),"") | H16: =IFERROR(SUMIFS(Trades!$AD$2:$AD$74,Trades!$AA$2:$AA$74,$A$16,Trades!$AD$2:$AD$74,">0",Trades!$C$2:$C$74,IF($D$4="(All)","*",$D$4),Trades!$AE$2:$AE$74,IF($G$4="(All)","*",$G$4))/-SUMIFS(Trades!$AD$2:$AD$74,Trades!$AA$2:$AA$74,$A$16,Trades!$AD$2:$AD$74,"<0",Trades!$C$2:$C$74,IF($D$4="(All)","*",$D$4),Trades!$AE$2:$AE$74,IF($G$4="(All)","*",$G$4)),"") | I16: =IFERROR(AVERAGEIFS(Trades!$AH$2:$AH$74,Trades!$AA$2:$AA$74,$A$16,Trades!$C$2:$C$74,IF($D$4="(All)","*",$D$4),Trades!$AE$2:$AE$74,IF($G$4="(All)","*",$G$4)),"") | J16: =IFERROR(AVERAGEIFS(Trades!$AI$2:$AI$74,Trades!$AA$2:$AA$74,$A$16,Trades!$C$2:$C$74,IF($D$4="(All)","*",$D$4),Trades!$AE$2:$AE$74,IF($G$4="(All)","*",$G$4)),"") | K16: =IFERROR(AVERAGEIFS(Trades!$O$2:$O$74,Trades!$AA$2:$AA$74,$A$16,Trades!$C$2:$C$74,IF($D$4="(All)","*",$D$4),Trades!$AE$2:$AE$74,IF($G$4="(All)","*",$G$4)),"") | L16: =IFERROR(E16/SUMIFS(Trades!$AD$2:$AD$74,Trades!$C$2:$C$74,IF($D$4="(All)","*",$D$4),Trades!$AE$2:$AE$74,IF($G$4="(All)","*",$G$4))*100,"")
A17: All trades | B17: =COUNTIFS(Trades!$C$2:$C$74,IF($D$4="(All)","*",$D$4),Trades!$AE$2:$AE$74,IF($G$4="(All)","*",$G$4)) | C17: =COUNTIFS(Trades!$AE$2:$AE$74,"Win",Trades!$C$2:$C$74,IF($D$4="(All)","*",$D$4),Trades!$AE$2:$AE$74,IF($G$4="(All)","*",$G$4)) | D17: =IFERROR(C17/B17*100,"") | E17: =SUMIFS(Trades!$AD$2:$AD$74,Trades!$C$2:$C$74,IF($D$4="(All)","*",$D$4),Trades!$AE$2:$AE$74,IF($G$4="(All)","*",$G$4)) | F17: =IFERROR(E17/B17,"") | G17: =IFERROR(AVERAGEIFS(Trades!$Z$2:$Z$74,Trades!$C$2:$C$74,IF($D$4="(All)","*",$D$4),Trades!$AE$2:$AE$74,IF($G$4="(All)","*",$G$4)),"") | H17: =IFERROR(SUMIFS(Trades!$AD$2:$AD$74,Trades!$AD$2:$AD$74,">0",Trades!$C$2:$C$74,IF($D$4="(All)","*",$D$4),Trades!$AE$2:$AE$74,IF($G$4="(All)","*",$G$4))/-SUMIFS(Trades!$AD$2:$AD$74,Trades!$AD$2:$AD$74,"<0",Trades!$C$2:$C$74,IF($D$4="(All)","*",$D$4),Trades!$AE$2:$AE$74,IF($G$4="(All)","*",$G$4)),"") | I17: =IFERROR(AVERAGEIFS(Trades!$AH$2:$AH$74,Trades!$C$2:$C$74,IF($D$4="(All)","*",$D$4),Trades!$AE$2:$AE$74,IF($G$4="(All)","*",$G$4)),"") | J17: =IFERROR(AVERAGEIFS(Trades!$AI$2:$AI$74,Trades!$C$2:$C$74,IF($D$4="(All)","*",$D$4),Trades!$AE$2:$AE$74,IF($G$4="(All)","*",$G$4)),"") | K17: =IFERROR(AVERAGEIFS(Trades!$O$2:$O$74,Trades!$C$2:$C$74,IF($D$4="(All)","*",$D$4),Trades!$AE$2:$AE$74,IF($G$4="(All)","*",$G$4)),"") | L17: =IFERROR(E17/SUMIFS(Trades!$AD$2:$AD$74,Trades!$C$2:$C$74,IF($D$4="(All)","*",$D$4),Trades!$AE$2:$AE$74,IF($G$4="(All)","*",$G$4))*100,"")
A20: By duration band | E20: Time in the market against money made.
A21: Duration band | B21: Trades | C21: Wins | D21: Win % | E21: Net | F21: Expectancy | G21: Avg R | H21: Profit factor | I21: Avg MFE | J21: Avg MAE | K21: Avg dur (min) | L21: Share of net
A22: A. < 1 min | B22: =COUNTIFS(Trades!$P$2:$P$74,$A$22,Trades!$C$2:$C$74,IF($D$4="(All)","*",$D$4),Trades!$AE$2:$AE$74,IF($G$4="(All)","*",$G$4)) | C22: =COUNTIFS(Trades!$AE$2:$AE$74,"Win",Trades!$P$2:$P$74,$A$22,Trades!$C$2:$C$74,IF($D$4="(All)","*",$D$4),Trades!$AE$2:$AE$74,IF($G$4="(All)","*",$G$4)) | D22: =IFERROR(C22/B22*100,"") | E22: =SUMIFS(Trades!$AD$2:$AD$74,Trades!$P$2:$P$74,$A$22,Trades!$C$2:$C$74,IF($D$4="(All)","*",$D$4),Trades!$AE$2:$AE$74,IF($G$4="(All)","*",$G$4)) | F22: =IFERROR(E22/B22,"") | G22: =IFERROR(AVERAGEIFS(Trades!$Z$2:$Z$74,Trades!$P$2:$P$74,$A$22,Trades!$C$2:$C$74,IF($D$4="(All)","*",$D$4),Trades!$AE$2:$AE$74,IF($G$4="(All)","*",$G$4)),"") | H22: =IFERROR(SUMIFS(Trades!$AD$2:$AD$74,Trades!$P$2:$P$74,$A$22,Trades!$AD$2:$AD$74,">0",Trades!$C$2:$C$74,IF($D$4="(All)","*",$D$4),Trades!$AE$2:$AE$74,IF($G$4="(All)","*",$G$4))/-SUMIFS(Trades!$AD$2:$AD$74,Trades!$P$2:$P$74,$A$22,Trades!$AD$2:$AD$74,"<0",Trades!$C$2:$C$74,IF($D$4="(All)","*",$D$4),Trades!$AE$2:$AE$74,IF($G$4="(All)","*",$G$4)),"") | I22: =IFERROR(AVERAGEIFS(Trades!$AH$2:$AH$74,Trades!$P$2:$P$74,$A$22,Trades!$C$2:$C$74,IF($D$4="(All)","*",$D$4),Trades!$AE$2:$AE$74,IF($G$4="(All)","*",$G$4)),"") | J22: =IFERROR(AVERAGEIFS(Trades!$AI$2:$AI$74,Trades!$P$2:$P$74,$A$22,Trades!$C$2:$C$74,IF($D$4="(All)","*",$D$4),Trades!$AE$2:$AE$74,IF($G$4="(All)","*",$G$4)),"") | K22: =IFERROR(AVERAGEIFS(Trades!$O$2:$O$74,Trades!$P$2:$P$74,$A$22,Trades!$C$2:$C$74,IF($D$4="(All)","*",$D$4),Trades!$AE$2:$AE$74,IF($G$4="(All)","*",$G$4)),"") | L22: =IFERROR(E22/SUMIFS(Trades!$AD$2:$AD$74,Trades!$C$2:$C$74,IF($D$4="(All)","*",$D$4),Trades!$AE$2:$AE$74,IF($G$4="(All)","*",$G$4))*100,"")
A23: B. 1-5 min | B23: =COUNTIFS(Trades!$P$2:$P$74,$A$23,Trades!$C$2:$C$74,IF($D$4="(All)","*",$D$4),Trades!$AE$2:$AE$74,IF($G$4="(All)","*",$G$4)) | C23: =COUNTIFS(Trades!$AE$2:$AE$74,"Win",Trades!$P$2:$P$74,$A$23,Trades!$C$2:$C$74,IF($D$4="(All)","*",$D$4),Trades!$AE$2:$AE$74,IF($G$4="(All)","*",$G$4)) | D23: =IFERROR(C23/B23*100,"") | E23: =SUMIFS(Trades!$AD$2:$AD$74,Trades!$P$2:$P$74,$A$23,Trades!$C$2:$C$74,IF($D$4="(All)","*",$D$4),Trades!$AE$2:$AE$74,IF($G$4="(All)","*",$G$4)) | F23: =IFERROR(E23/B23,"") | G23: =IFERROR(AVERAGEIFS(Trades!$Z$2:$Z$74,Trades!$P$2:$P$74,$A$23,Trades!$C$2:$C$74,IF($D$4="(All)","*",$D$4),Trades!$AE$2:$AE$74,IF($G$4="(All)","*",$G$4)),"") | H23: =IFERROR(SUMIFS(Trades!$AD$2:$AD$74,Trades!$P$2:$P$74,$A$23,Trades!$AD$2:$AD$74,">0",Trades!$C$2:$C$74,IF($D$4="(All)","*",$D$4),Trades!$AE$2:$AE$74,IF($G$4="(All)","*",$G$4))/-SUMIFS(Trades!$AD$2:$AD$74,Trades!$P$2:$P$74,$A$23,Trades!$AD$2:$AD$74,"<0",Trades!$C$2:$C$74,IF($D$4="(All)","*",$D$4),Trades!$AE$2:$AE$74,IF($G$4="(All)","*",$G$4)),"") | I23: =IFERROR(AVERAGEIFS(Trades!$AH$2:$AH$74,Trades!$P$2:$P$74,$A$23,Trades!$C$2:$C$74,IF($D$4="(All)","*",$D$4),Trades!$AE$2:$AE$74,IF($G$4="(All)","*",$G$4)),"") | J23: =IFERROR(AVERAGEIFS(Trades!$AI$2:$AI$74,Trades!$P$2:$P$74,$A$23,Trades!$C$2:$C$74,IF($D$4="(All)","*",$D$4),Trades!$AE$2:$AE$74,IF($G$4="(All)","*",$G$4)),"") | K23: =IFERROR(AVERAGEIFS(Trades!$O$2:$O$74,Trades!$P$2:$P$74,$A$23,Trades!$C$2:$C$74,IF($D$4="(All)","*",$D$4),Trades!$AE$2:$AE$74,IF($G$4="(All)","*",$G$4)),"") | L23: =IFERROR(E23/SUMIFS(Trades!$AD$2:$AD$74,Trades!$C$2:$C$74,IF($D$4="(All)","*",$D$4),Trades!$AE$2:$AE$74,IF($G$4="(All)","*",$G$4))*100,"")
A24: C. 5-15 min | B24: =COUNTIFS(Trades!$P$2:$P$74,$A$24,Trades!$C$2:$C$74,IF($D$4="(All)","*",$D$4),Trades!$AE$2:$AE$74,IF($G$4="(All)","*",$G$4)) | C24: =COUNTIFS(Trades!$AE$2:$AE$74,"Win",Trades!$P$2:$P$74,$A$24,Trades!$C$2:$C$74,IF($D$4="(All)","*",$D$4),Trades!$AE$2:$AE$74,IF($G$4="(All)","*",$G$4)) | D24: =IFERROR(C24/B24*100,"") | E24: =SUMIFS(Trades!$AD$2:$AD$74,Trades!$P$2:$P$74,$A$24,Trades!$C$2:$C$74,IF($D$4="(All)","*",$D$4),Trades!$AE$2:$AE$74,IF($G$4="(All)","*",$G$4)) | F24: =IFERROR(E24/B24,"") | G24: =IFERROR(AVERAGEIFS(Trades!$Z$2:$Z$74,Trades!$P$2:$P$74,$A$24,Trades!$C$2:$C$74,IF($D$4="(All)","*",$D$4),Trades!$AE$2:$AE$74,IF($G$4="(All)","*",$G$4)),"") | H24: =IFERROR(SUMIFS(Trades!$AD$2:$AD$74,Trades!$P$2:$P$74,$A$24,Trades!$AD$2:$AD$74,">0",Trades!$C$2:$C$74,IF($D$4="(All)","*",$D$4),Trades!$AE$2:$AE$74,IF($G$4="(All)","*",$G$4))/-SUMIFS(Trades!$AD$2:$AD$74,Trades!$P$2:$P$74,$A$24,Trades!$AD$2:$AD$74,"<0",Trades!$C$2:$C$74,IF($D$4="(All)","*",$D$4),Trades!$AE$2:$AE$74,IF($G$4="(All)","*",$G$4)),"") | I24: =IFERROR(AVERAGEIFS(Trades!$AH$2:$AH$74,Trades!$P$2:$P$74,$A$24,Trades!$C$2:$C$74,IF($D$4="(All)","*",$D$4),Trades!$AE$2:$AE$74,IF($G$4="(All)","*",$G$4)),"") | J24: =IFERROR(AVERAGEIFS(Trades!$AI$2:$AI$74,Trades!$P$2:$P$74,$A$24,Trades!$C$2:$C$74,IF($D$4="(All)","*",$D$4),Trades!$AE$2:$AE$74,IF($G$4="(All)","*",$G$4)),"") | K24: =IFERROR(AVERAGEIFS(Trades!$O$2:$O$74,Trades!$P$2:$P$74,$A$24,Trades!$C$2:$C$74,IF($D$4="(All)","*",$D$4),Trades!$AE$2:$AE$74,IF($G$4="(All)","*",$G$4)),"") | L24: =IFERROR(E24/SUMIFS(Trades!$AD$2:$AD$74,Trades!$C$2:$C$74,IF($D$4="(All)","*",$D$4),Trades!$AE$2:$AE$74,IF($G$4="(All)","*",$G$4))*100,"")
A25: D. 15-30 min | B25: =COUNTIFS(Trades!$P$2:$P$74,$A$25,Trades!$C$2:$C$74,IF($D$4="(All)","*",$D$4),Trades!$AE$2:$AE$74,IF($G$4="(All)","*",$G$4)) | C25: =COUNTIFS(Trades!$AE$2:$AE$74,"Win",Trades!$P$2:$P$74,$A$25,Trades!$C$2:$C$74,IF($D$4="(All)","*",$D$4),Trades!$AE$2:$AE$74,IF($G$4="(All)","*",$G$4)) | D25: =IFERROR(C25/B25*100,"") | E25: =SUMIFS(Trades!$AD$2:$AD$74,Trades!$P$2:$P$74,$A$25,Trades!$C$2:$C$74,IF($D$4="(All)","*",$D$4),Trades!$AE$2:$AE$74,IF($G$4="(All)","*",$G$4)) | F25: =IFERROR(E25/B25,"") | G25: =IFERROR(AVERAGEIFS(Trades!$Z$2:$Z$74,Trades!$P$2:$P$74,$A$25,Trades!$C$2:$C$74,IF($D$4="(All)","*",$D$4),Trades!$AE$2:$AE$74,IF($G$4="(All)","*",$G$4)),"") | H25: =IFERROR(SUMIFS(Trades!$AD$2:$AD$74,Trades!$P$2:$P$74,$A$25,Trades!$AD$2:$AD$74,">0",Trades!$C$2:$C$74,IF($D$4="(All)","*",$D$4),Trades!$AE$2:$AE$74,IF($G$4="(All)","*",$G$4))/-SUMIFS(Trades!$AD$2:$AD$74,Trades!$P$2:$P$74,$A$25,Trades!$AD$2:$AD$74,"<0",Trades!$C$2:$C$74,IF($D$4="(All)","*",$D$4),Trades!$AE$2:$AE$74,IF($G$4="(All)","*",$G$4)),"") | I25: =IFERROR(AVERAGEIFS(Trades!$AH$2:$AH$74,Trades!$P$2:$P$74,$A$25,Trades!$C$2:$C$74,IF($D$4="(All)","*",$D$4),Trades!$AE$2:$AE$74,IF($G$4="(All)","*",$G$4)),"") | J25: =IFERROR(AVERAGEIFS(Trades!$AI$2:$AI$74,Trades!$P$2:$P$74,$A$25,Trades!$C$2:$C$74,IF($D$4="(All)","*",$D$4),Trades!$AE$2:$AE$74,IF($G$4="(All)","*",$G$4)),"") | K25: =IFERROR(AVERAGEIFS(Trades!$O$2:$O$74,Trades!$P$2:$P$74,$A$25,Trades!$C$2:$C$74,IF($D$4="(All)","*",$D$4),Trades!$AE$2:$AE$74,IF($G$4="(All)","*",$G$4)),"") | L25: =IFERROR(E25/SUMIFS(Trades!$AD$2:$AD$74,Trades!$C$2:$C$74,IF($D$4="(All)","*",$D$4),Trades!$AE$2:$AE$74,IF($G$4="(All)","*",$G$4))*100,"")
A26: E. 30-60 min | B26: =COUNTIFS(Trades!$P$2:$P$74,$A$26,Trades!$C$2:$C$74,IF($D$4="(All)","*",$D$4),Trades!$AE$2:$AE$74,IF($G$4="(All)","*",$G$4)) | C26: =COUNTIFS(Trades!$AE$2:$AE$74,"Win",Trades!$P$2:$P$74,$A$26,Trades!$C$2:$C$74,IF($D$4="(All)","*",$D$4),Trades!$AE$2:$AE$74,IF($G$4="(All)","*",$G$4)) | D26: =IFERROR(C26/B26*100,"") | E26: =SUMIFS(Trades!$AD$2:$AD$74,Trades!$P$2:$P$74,$A$26,Trades!$C$2:$C$74,IF($D$4="(All)","*",$D$4),Trades!$AE$2:$AE$74,IF($G$4="(All)","*",$G$4)) | F26: =IFERROR(E26/B26,"") | G26: =IFERROR(AVERAGEIFS(Trades!$Z$2:$Z$74,Trades!$P$2:$P$74,$A$26,Trades!$C$2:$C$74,IF($D$4="(All)","*",$D$4),Trades!$AE$2:$AE$74,IF($G$4="(All)","*",$G$4)),"") | H26: =IFERROR(SUMIFS(Trades!$AD$2:$AD$74,Trades!$P$2:$P$74,$A$26,Trades!$AD$2:$AD$74,">0",Trades!$C$2:$C$74,IF($D$4="(All)","*",$D$4),Trades!$AE$2:$AE$74,IF($G$4="(All)","*",$G$4))/-SUMIFS(Trades!$AD$2:$AD$74,Trades!$P$2:$P$74,$A$26,Trades!$AD$2:$AD$74,"<0",Trades!$C$2:$C$74,IF($D$4="(All)","*",$D$4),Trades!$AE$2:$AE$74,IF($G$4="(All)","*",$G$4)),"") | I26: =IFERROR(AVERAGEIFS(Trades!$AH$2:$AH$74,Trades!$P$2:$P$74,$A$26,Trades!$C$2:$C$74,IF($D$4="(All)","*",$D$4),Trades!$AE$2:$AE$74,IF($G$4="(All)","*",$G$4)),"") | J26: =IFERROR(AVERAGEIFS(Trades!$AI$2:$AI$74,Trades!$P$2:$P$74,$A$26,Trades!$C$2:$C$74,IF($D$4="(All)","*",$D$4),Trades!$AE$2:$AE$74,IF($G$4="(All)","*",$G$4)),"") | K26: =IFERROR(AVERAGEIFS(Trades!$O$2:$O$74,Trades!$P$2:$P$74,$A$26,Trades!$C$2:$C$74,IF($D$4="(All)","*",$D$4),Trades!$AE$2:$AE$74,IF($G$4="(All)","*",$G$4)),"") | L26: =IFERROR(E26/SUMIFS(Trades!$AD$2:$AD$74,Trades!$C$2:$C$74,IF($D$4="(All)","*",$D$4),Trades!$AE$2:$AE$74,IF($G$4="(All)","*",$G$4))*100,"")
A27: F. 1-4 h | B27: =COUNTIFS(Trades!$P$2:$P$74,$A$27,Trades!$C$2:$C$74,IF($D$4="(All)","*",$D$4),Trades!$AE$2:$AE$74,IF($G$4="(All)","*",$G$4)) | C27: =COUNTIFS(Trades!$AE$2:$AE$74,"Win",Trades!$P$2:$P$74,$A$27,Trades!$C$2:$C$74,IF($D$4="(All)","*",$D$4),Trades!$AE$2:$AE$74,IF($G$4="(All)","*",$G$4)) | D27: =IFERROR(C27/B27*100,"") | E27: =SUMIFS(Trades!$AD$2:$AD$74,Trades!$P$2:$P$74,$A$27,Trades!$C$2:$C$74,IF($D$4="(All)","*",$D$4),Trades!$AE$2:$AE$74,IF($G$4="(All)","*",$G$4)) | F27: =IFERROR(E27/B27,"") | G27: =IFERROR(AVERAGEIFS(Trades!$Z$2:$Z$74,Trades!$P$2:$P$74,$A$27,Trades!$C$2:$C$74,IF($D$4="(All)","*",$D$4),Trades!$AE$2:$AE$74,IF($G$4="(All)","*",$G$4)),"") | H27: =IFERROR(SUMIFS(Trades!$AD$2:$AD$74,Trades!$P$2:$P$74,$A$27,Trades!$AD$2:$AD$74,">0",Trades!$C$2:$C$74,IF($D$4="(All)","*",$D$4),Trades!$AE$2:$AE$74,IF($G$4="(All)","*",$G$4))/-SUMIFS(Trades!$AD$2:$AD$74,Trades!$P$2:$P$74,$A$27,Trades!$AD$2:$AD$74,"<0",Trades!$C$2:$C$74,IF($D$4="(All)","*",$D$4),Trades!$AE$2:$AE$74,IF($G$4="(All)","*",$G$4)),"") | I27: =IFERROR(AVERAGEIFS(Trades!$AH$2:$AH$74,Trades!$P$2:$P$74,$A$27,Trades!$C$2:$C$74,IF($D$4="(All)","*",$D$4),Trades!$AE$2:$AE$74,IF($G$4="(All)","*",$G$4)),"") | J27: =IFERROR(AVERAGEIFS(Trades!$AI$2:$AI$74,Trades!$P$2:$P$74,$A$27,Trades!$C$2:$C$74,IF($D$4="(All)","*",$D$4),Trades!$AE$2:$AE$74,IF($G$4="(All)","*",$G$4)),"") | K27: =IFERROR(AVERAGEIFS(Trades!$O$2:$O$74,Trades!$P$2:$P$74,$A$27,Trades!$C$2:$C$74,IF($D$4="(All)","*",$D$4),Trades!$AE$2:$AE$74,IF($G$4="(All)","*",$G$4)),"") | L27: =IFERROR(E27/SUMIFS(Trades!$AD$2:$AD$74,Trades!$C$2:$C$74,IF($D$4="(All)","*",$D$4),Trades!$AE$2:$AE$74,IF($G$4="(All)","*",$G$4))*100,"")
A28: All trades | B28: =COUNTIFS(Trades!$C$2:$C$74,IF($D$4="(All)","*",$D$4),Trades!$AE$2:$AE$74,IF($G$4="(All)","*",$G$4)) | C28: =COUNTIFS(Trades!$AE$2:$AE$74,"Win",Trades!$C$2:$C$74,IF($D$4="(All)","*",$D$4),Trades!$AE$2:$AE$74,IF($G$4="(All)","*",$G$4)) | D28: =IFERROR(C28/B28*100,"") | E28: =SUMIFS(Trades!$AD$2:$AD$74,Trades!$C$2:$C$74,IF($D$4="(All)","*",$D$4),Trades!$AE$2:$AE$74,IF($G$4="(All)","*",$G$4)) | F28: =IFERROR(E28/B28,"") | G28: =IFERROR(AVERAGEIFS(Trades!$Z$2:$Z$74,Trades!$C$2:$C$74,IF($D$4="(All)","*",$D$4),Trades!$AE$2:$AE$74,IF($G$4="(All)","*",$G$4)),"") | H28: =IFERROR(SUMIFS(Trades!$AD$2:$AD$74,Trades!$AD$2:$AD$74,">0",Trades!$C$2:$C$74,IF($D$4="(All)","*",$D$4),Trades!$AE$2:$AE$74,IF($G$4="(All)","*",$G$4))/-SUMIFS(Trades!$AD$2:$AD$74,Trades!$AD$2:$AD$74,"<0",Trades!$C$2:$C$74,IF($D$4="(All)","*",$D$4),Trades!$AE$2:$AE$74,IF($G$4="(All)","*",$G$4)),"") | I28: =IFERROR(AVERAGEIFS(Trades!$AH$2:$AH$74,Trades!$C$2:$C$74,IF($D$4="(All)","*",$D$4),Trades!$AE$2:$AE$74,IF($G$4="(All)","*",$G$4)),"") | J28: =IFERROR(AVERAGEIFS(Trades!$AI$2:$AI$74,Trades!$C$2:$C$74,IF($D$4="(All)","*",$D$4),Trades!$AE$2:$AE$74,IF($G$4="(All)","*",$G$4)),"") | K28: =IFERROR(AVERAGEIFS(Trades!$O$2:$O$74,Trades!$C$2:$C$74,IF($D$4="(All)","*",$D$4),Trades!$AE$2:$AE$74,IF($G$4="(All)","*",$G$4)),"") | L28: =IFERROR(E28/SUMIFS(Trades!$AD$2:$AD$74,Trades!$C$2:$C$74,IF($D$4="(All)","*",$D$4),Trades!$AE$2:$AE$74,IF($G$4="(All)","*",$G$4))*100,"")
A31: By mfe first | E31: Did price go the trader's way before it went against? The 'No' row is trades that were wrong from the first tick.
A32: MFE first | B32: Trades | C32: Wins | D32: Win % | E32: Net | F32: Expectancy | G32: Avg R | H32: Profit factor | I32: Avg MFE | J32: Avg MAE | K32: Avg dur (min) | L32: Share of net
A33: No | B33: =COUNTIFS(Trades!$AV$2:$AV$74,$A$33,Trades!$C$2:$C$74,IF($D$4="(All)","*",$D$4),Trades!$AE$2:$AE$74,IF($G$4="(All)","*",$G$4)) | C33: =COUNTIFS(Trades!$AE$2:$AE$74,"Win",Trades!$AV$2:$AV$74,$A$33,Trades!$C$2:$C$74,IF($D$4="(All)","*",$D$4),Trades!$AE$2:$AE$74,IF($G$4="(All)","*",$G$4)) | D33: =IFERROR(C33/B33*100,"") | E33: =SUMIFS(Trades!$AD$2:$AD$74,Trades!$AV$2:$AV$74,$A$33,Trades!$C$2:$C$74,IF($D$4="(All)","*",$D$4),Trades!$AE$2:$AE$74,IF($G$4="(All)","*",$G$4)) | F33: =IFERROR(E33/B33,"") | G33: =IFERROR(AVERAGEIFS(Trades!$Z$2:$Z$74,Trades!$AV$2:$AV$74,$A$33,Trades!$C$2:$C$74,IF($D$4="(All)","*",$D$4),Trades!$AE$2:$AE$74,IF($G$4="(All)","*",$G$4)),"") | H33: =IFERROR(SUMIFS(Trades!$AD$2:$AD$74,Trades!$AV$2:$AV$74,$A$33,Trades!$AD$2:$AD$74,">0",Trades!$C$2:$C$74,IF($D$4="(All)","*",$D$4),Trades!$AE$2:$AE$74,IF($G$4="(All)","*",$G$4))/-SUMIFS(Trades!$AD$2:$AD$74,Trades!$AV$2:$AV$74,$A$33,Trades!$AD$2:$AD$74,"<0",Trades!$C$2:$C$74,IF($D$4="(All)","*",$D$4),Trades!$AE$2:$AE$74,IF($G$4="(All)","*",$G$4)),"") | I33: =IFERROR(AVERAGEIFS(Trades!$AH$2:$AH$74,Trades!$AV$2:$AV$74,$A$33,Trades!$C$2:$C$74,IF($D$4="(All)","*",$D$4),Trades!$AE$2:$AE$74,IF($G$4="(All)","*",$G$4)),"") | J33: =IFERROR(AVERAGEIFS(Trades!$AI$2:$AI$74,Trades!$AV$2:$AV$74,$A$33,Trades!$C$2:$C$74,IF($D$4="(All)","*",$D$4),Trades!$AE$2:$AE$74,IF($G$4="(All)","*",$G$4)),"") | K33: =IFERROR(AVERAGEIFS(Trades!$O$2:$O$74,Trades!$AV$2:$AV$74,$A$33,Trades!$C$2:$C$74,IF($D$4="(All)","*",$D$4),Trades!$AE$2:$AE$74,IF($G$4="(All)","*",$G$4)),"") | L33: =IFERROR(E33/SUMIFS(Trades!$AD$2:$AD$74,Trades!$C$2:$C$74,IF($D$4="(All)","*",$D$4),Trades!$AE$2:$AE$74,IF($G$4="(All)","*",$G$4))*100,"")
A34: Yes | B34: =COUNTIFS(Trades!$AV$2:$AV$74,$A$34,Trades!$C$2:$C$74,IF($D$4="(All)","*",$D$4),Trades!$AE$2:$AE$74,IF($G$4="(All)","*",$G$4)) | C34: =COUNTIFS(Trades!$AE$2:$AE$74,"Win",Trades!$AV$2:$AV$74,$A$34,Trades!$C$2:$C$74,IF($D$4="(All)","*",$D$4),Trades!$AE$2:$AE$74,IF($G$4="(All)","*",$G$4)) | D34: =IFERROR(C34/B34*100,"") | E34: =SUMIFS(Trades!$AD$2:$AD$74,Trades!$AV$2:$AV$74,$A$34,Trades!$C$2:$C$74,IF($D$4="(All)","*",$D$4),Trades!$AE$2:$AE$74,IF($G$4="(All)","*",$G$4)) | F34: =IFERROR(E34/B34,"") | G34: =IFERROR(AVERAGEIFS(Trades!$Z$2:$Z$74,Trades!$AV$2:$AV$74,$A$34,Trades!$C$2:$C$74,IF($D$4="(All)","*",$D$4),Trades!$AE$2:$AE$74,IF($G$4="(All)","*",$G$4)),"") | H34: =IFERROR(SUMIFS(Trades!$AD$2:$AD$74,Trades!$AV$2:$AV$74,$A$34,Trades!$AD$2:$AD$74,">0",Trades!$C$2:$C$74,IF($D$4="(All)","*",$D$4),Trades!$AE$2:$AE$74,IF($G$4="(All)","*",$G$4))/-SUMIFS(Trades!$AD$2:$AD$74,Trades!$AV$2:$AV$74,$A$34,Trades!$AD$2:$AD$74,"<0",Trades!$C$2:$C$74,IF($D$4="(All)","*",$D$4),Trades!$AE$2:$AE$74,IF($G$4="(All)","*",$G$4)),"") | I34: =IFERROR(AVERAGEIFS(Trades!$AH$2:$AH$74,Trades!$AV$2:$AV$74,$A$34,Trades!$C$2:$C$74,IF($D$4="(All)","*",$D$4),Trades!$AE$2:$AE$74,IF($G$4="(All)","*",$G$4)),"") | J34: =IFERROR(AVERAGEIFS(Trades!$AI$2:$AI$74,Trades!$AV$2:$AV$74,$A$34,Trades!$C$2:$C$74,IF($D$4="(All)","*",$D$4),Trades!$AE$2:$AE$74,IF($G$4="(All)","*",$G$4)),"") | K34: =IFERROR(AVERAGEIFS(Trades!$O$2:$O$74,Trades!$AV$2:$AV$74,$A$34,Trades!$C$2:$C$74,IF($D$4="(All)","*",$D$4),Trades!$AE$2:$AE$74,IF($G$4="(All)","*",$G$4)),"") | L34: =IFERROR(E34/SUMIFS(Trades!$AD$2:$AD$74,Trades!$C$2:$C$74,IF($D$4="(All)","*",$D$4),Trades!$AE$2:$AE$74,IF($G$4="(All)","*",$G$4))*100,"")
A35: All trades | B35: =COUNTIFS(Trades!$C$2:$C$74,IF($D$4="(All)","*",$D$4),Trades!$AE$2:$AE$74,IF($G$4="(All)","*",$G$4)) | C35: =COUNTIFS(Trades!$AE$2:$AE$74,"Win",Trades!$C$2:$C$74,IF($D$4="(All)","*",$D$4),Trades!$AE$2:$AE$74,IF($G$4="(All)","*",$G$4)) | D35: =IFERROR(C35/B35*100,"") | E35: =SUMIFS(Trades!$AD$2:$AD$74,Trades!$C$2:$C$74,IF($D$4="(All)","*",$D$4),Trades!$AE$2:$AE$74,IF($G$4="(All)","*",$G$4)) | F35: =IFERROR(E35/B35,"") | G35: =IFERROR(AVERAGEIFS(Trades!$Z$2:$Z$74,Trades!$C$2:$C$74,IF($D$4="(All)","*",$D$4),Trades!$AE$2:$AE$74,IF($G$4="(All)","*",$G$4)),"") | H35: =IFERROR(SUMIFS(Trades!$AD$2:$AD$74,Trades!$AD$2:$AD$74,">0",Trades!$C$2:$C$74,IF($D$4="(All)","*",$D$4),Trades!$AE$2:$AE$74,IF($G$4="(All)","*",$G$4))/-SUMIFS(Trades!$AD$2:$AD$74,Trades!$AD$2:$AD$74,"<0",Trades!$C$2:$C$74,IF($D$4="(All)","*",$D$4),Trades!$AE$2:$AE$74,IF($G$4="(All)","*",$G$4)),"") | I35: =IFERROR(AVERAGEIFS(Trades!$AH$2:$AH$74,Trades!$C$2:$C$74,IF($D$4="(All)","*",$D$4),Trades!$AE$2:$AE$74,IF($G$4="(All)","*",$G$4)),"") | J35: =IFERROR(AVERAGEIFS(Trades!$AI$2:$AI$74,Trades!$C$2:$C$74,IF($D$4="(All)","*",$D$4),Trades!$AE$2:$AE$74,IF($G$4="(All)","*",$G$4)),"") | K35: =IFERROR(AVERAGEIFS(Trades!$O$2:$O$74,Trades!$C$2:$C$74,IF($D$4="(All)","*",$D$4),Trades!$AE$2:$AE$74,IF($G$4="(All)","*",$G$4)),"") | L35: =IFERROR(E35/SUMIFS(Trades!$AD$2:$AD$74,Trades!$C$2:$C$74,IF($D$4="(All)","*",$D$4),Trades!$AE$2:$AE$74,IF($G$4="(All)","*",$G$4))*100,"")

Sheet Excursions
A1: Excursions — MAE, MFE and what happened in between
A2: Maximum adverse and favourable excursion measured tick by tick where the history allowed it, from M1 bars otherwise. The source is recorded per trade on the Trades sheet.
A4: Headline
A5: Average MFE | D5: 8.68 | F5: How much the average trade was up at its best point.
A6: Average MAE | D6: -5.76 | F6: How far the average trade went against the entry before resolving.
A7: Average MAE on winners | D7: -3.55 | F7: Heat a winning trade takes. If this is far inside the average risk, the stops are wider than the trades need.
A8: Average MFE on losers | D8: 4.23 | F8: Money that was on the table in trades that finished red.
A9: Median heat | D9: 101.5 | F9: MAE as a share of the risk taken. Above 100% means the trade went further against the entry than the stop it was risking.
A10: 90th percentile heat | D10: 167 | F10: One trade in ten runs at least this hot.
A11: Capture on winners | D11: 0.933 | F11: Money kept divided by money offered, across all winners. 1.00 would be exiting every winner at its exact high.
A12: Median winner capture | D12: 0.988 | F12: The typical winner, unweighted by size.
A13: Total giveback | D13: 501.56 | F13: Sum of the gap between each trade's best point and where it closed.
A14: Losers that were up 0.5R or more | D14: 25 | F14: 51.0% of all losing trades. The threshold exists on purpose: measured on ticks almost every trade shows a fractionally positive MFE, and counting those would turn noise into a finding.
A15: Trades with excursion data | D15: 73 | F15: out of 73 closed trades.
A18: Efficiency (Sweeney) | F18: Share of the trade's own high-to-low range that the entry, the exit and the trade as a whole captured. 1.00 is perfect, 0.50 is a coin flip against the range that was available.
A19: Entry efficiency | D19: =IFERROR(AVERAGE(Trades!$AS$2:$AS$74),"") | F19: Average across all closed trades, from column AS of the Trades sheet.
A20: Exit efficiency | D20: =IFERROR(AVERAGE(Trades!$AT$2:$AT$74),"") | F20: Average across all closed trades, from column AT of the Trades sheet.
A21: Total efficiency | D21: =IFERROR(AVERAGE(Trades!$AU$2:$AU$74),"") | F21: Average across all closed trades, from column AU of the Trades sheet.
A24: Filters | C24: Symbol | D24: (All) | F24: Outcome | G24: (All) | I24: Change either dropdown - every grid below recalculates.
A26: Excursion by exit reason | E26: Compare Avg MFE against Avg MAE row by row: a reason whose MFE dwarfs its net is an exit problem, not an entry problem.
A27: Exit reason | B27: Trades | C27: Wins | D27: Win % | E27: Net | F27: Expectancy | G27: Avg R | H27: Profit factor | I27: Avg MFE | J27: Avg MAE | K27: Avg dur (min) | L27: Share of net
A28: Expert | B28: =COUNTIFS(Trades!$AF$2:$AF$74,$A$28,Trades!$C$2:$C$74,IF($D$24="(All)","*",$D$24),Trades!$AE$2:$AE$74,IF($G$24="(All)","*",$G$24)) | C28: =COUNTIFS(Trades!$AE$2:$AE$74,"Win",Trades!$AF$2:$AF$74,$A$28,Trades!$C$2:$C$74,IF($D$24="(All)","*",$D$24),Trades!$AE$2:$AE$74,IF($G$24="(All)","*",$G$24)) | D28: =IFERROR(C28/B28*100,"") | E28: =SUMIFS(Trades!$AD$2:$AD$74,Trades!$AF$2:$AF$74,$A$28,Trades!$C$2:$C$74,IF($D$24="(All)","*",$D$24),Trades!$AE$2:$AE$74,IF($G$24="(All)","*",$G$24)) | F28: =IFERROR(E28/B28,"") | G28: =IFERROR(AVERAGEIFS(Trades!$Z$2:$Z$74,Trades!$AF$2:$AF$74,$A$28,Trades!$C$2:$C$74,IF($D$24="(All)","*",$D$24),Trades!$AE$2:$AE$74,IF($G$24="(All)","*",$G$24)),"") | H28: =IFERROR(SUMIFS(Trades!$AD$2:$AD$74,Trades!$AF$2:$AF$74,$A$28,Trades!$AD$2:$AD$74,">0",Trades!$C$2:$C$74,IF($D$24="(All)","*",$D$24),Trades!$AE$2:$AE$74,IF($G$24="(All)","*",$G$24))/-SUMIFS(Trades!$AD$2:$AD$74,Trades!$AF$2:$AF$74,$A$28,Trades!$AD$2:$AD$74,"<0",Trades!$C$2:$C$74,IF($D$24="(All)","*",$D$24),Trades!$AE$2:$AE$74,IF($G$24="(All)","*",$G$24)),"") | I28: =IFERROR(AVERAGEIFS(Trades!$AH$2:$AH$74,Trades!$AF$2:$AF$74,$A$28,Trades!$C$2:$C$74,IF($D$24="(All)","*",$D$24),Trades!$AE$2:$AE$74,IF($G$24="(All)","*",$G$24)),"") | J28: =IFERROR(AVERAGEIFS(Trades!$AI$2:$AI$74,Trades!$AF$2:$AF$74,$A$28,Trades!$C$2:$C$74,IF($D$24="(All)","*",$D$24),Trades!$AE$2:$AE$74,IF($G$24="(All)","*",$G$24)),"") | K28: =IFERROR(AVERAGEIFS(Trades!$O$2:$O$74,Trades!$AF$2:$AF$74,$A$28,Trades!$C$2:$C$74,IF($D$24="(All)","*",$D$24),Trades!$AE$2:$AE$74,IF($G$24="(All)","*",$G$24)),"") | L28: =IFERROR(E28/SUMIFS(Trades!$AD$2:$AD$74,Trades!$C$2:$C$74,IF($D$24="(All)","*",$D$24),Trades!$AE$2:$AE$74,IF($G$24="(All)","*",$G$24))*100,"")
A29: Stop Loss | B29: =COUNTIFS(Trades!$AF$2:$AF$74,$A$29,Trades!$C$2:$C$74,IF($D$24="(All)","*",$D$24),Trades!$AE$2:$AE$74,IF($G$24="(All)","*",$G$24)) | C29: =COUNTIFS(Trades!$AE$2:$AE$74,"Win",Trades!$AF$2:$AF$74,$A$29,Trades!$C$2:$C$74,IF($D$24="(All)","*",$D$24),Trades!$AE$2:$AE$74,IF($G$24="(All)","*",$G$24)) | D29: =IFERROR(C29/B29*100,"") | E29: =SUMIFS(Trades!$AD$2:$AD$74,Trades!$AF$2:$AF$74,$A$29,Trades!$C$2:$C$74,IF($D$24="(All)","*",$D$24),Trades!$AE$2:$AE$74,IF($G$24="(All)","*",$G$24)) | F29: =IFERROR(E29/B29,"") | G29: =IFERROR(AVERAGEIFS(Trades!$Z$2:$Z$74,Trades!$AF$2:$AF$74,$A$29,Trades!$C$2:$C$74,IF($D$24="(All)","*",$D$24),Trades!$AE$2:$AE$74,IF($G$24="(All)","*",$G$24)),"") | H29: =IFERROR(SUMIFS(Trades!$AD$2:$AD$74,Trades!$AF$2:$AF$74,$A$29,Trades!$AD$2:$AD$74,">0",Trades!$C$2:$C$74,IF($D$24="(All)","*",$D$24),Trades!$AE$2:$AE$74,IF($G$24="(All)","*",$G$24))/-SUMIFS(Trades!$AD$2:$AD$74,Trades!$AF$2:$AF$74,$A$29,Trades!$AD$2:$AD$74,"<0",Trades!$C$2:$C$74,IF($D$24="(All)","*",$D$24),Trades!$AE$2:$AE$74,IF($G$24="(All)","*",$G$24)),"") | I29: =IFERROR(AVERAGEIFS(Trades!$AH$2:$AH$74,Trades!$AF$2:$AF$74,$A$29,Trades!$C$2:$C$74,IF($D$24="(All)","*",$D$24),Trades!$AE$2:$AE$74,IF($G$24="(All)","*",$G$24)),"") | J29: =IFERROR(AVERAGEIFS(Trades!$AI$2:$AI$74,Trades!$AF$2:$AF$74,$A$29,Trades!$C$2:$C$74,IF($D$24="(All)","*",$D$24),Trades!$AE$2:$AE$74,IF($G$24="(All)","*",$G$24)),"") | K29: =IFERROR(AVERAGEIFS(Trades!$O$2:$O$74,Trades!$AF$2:$AF$74,$A$29,Trades!$C$2:$C$74,IF($D$24="(All)","*",$D$24),Trades!$AE$2:$AE$74,IF($G$24="(All)","*",$G$24)),"") | L29: =IFERROR(E29/SUMIFS(Trades!$AD$2:$AD$74,Trades!$C$2:$C$74,IF($D$24="(All)","*",$D$24),Trades!$AE$2:$AE$74,IF($G$24="(All)","*",$G$24))*100,"")
A30: Take Profit | B30: =COUNTIFS(Trades!$AF$2:$AF$74,$A$30,Trades!$C$2:$C$74,IF($D$24="(All)","*",$D$24),Trades!$AE$2:$AE$74,IF($G$24="(All)","*",$G$24)) | C30: =COUNTIFS(Trades!$AE$2:$AE$74,"Win",Trades!$AF$2:$AF$74,$A$30,Trades!$C$2:$C$74,IF($D$24="(All)","*",$D$24),Trades!$AE$2:$AE$74,IF($G$24="(All)","*",$G$24)) | D30: =IFERROR(C30/B30*100,"") | E30: =SUMIFS(Trades!$AD$2:$AD$74,Trades!$AF$2:$AF$74,$A$30,Trades!$C$2:$C$74,IF($D$24="(All)","*",$D$24),Trades!$AE$2:$AE$74,IF($G$24="(All)","*",$G$24)) | F30: =IFERROR(E30/B30,"") | G30: =IFERROR(AVERAGEIFS(Trades!$Z$2:$Z$74,Trades!$AF$2:$AF$74,$A$30,Trades!$C$2:$C$74,IF($D$24="(All)","*",$D$24),Trades!$AE$2:$AE$74,IF($G$24="(All)","*",$G$24)),"") | H30: =IFERROR(SUMIFS(Trades!$AD$2:$AD$74,Trades!$AF$2:$AF$74,$A$30,Trades!$AD$2:$AD$74,">0",Trades!$C$2:$C$74,IF($D$24="(All)","*",$D$24),Trades!$AE$2:$AE$74,IF($G$24="(All)","*",$G$24))/-SUMIFS(Trades!$AD$2:$AD$74,Trades!$AF$2:$AF$74,$A$30,Trades!$AD$2:$AD$74,"<0",Trades!$C$2:$C$74,IF($D$24="(All)","*",$D$24),Trades!$AE$2:$AE$74,IF($G$24="(All)","*",$G$24)),"") | I30: =IFERROR(AVERAGEIFS(Trades!$AH$2:$AH$74,Trades!$AF$2:$AF$74,$A$30,Trades!$C$2:$C$74,IF($D$24="(All)","*",$D$24),Trades!$AE$2:$AE$74,IF($G$24="(All)","*",$G$24)),"") | J30: =IFERROR(AVERAGEIFS(Trades!$AI$2:$AI$74,Trades!$AF$2:$AF$74,$A$30,Trades!$C$2:$C$74,IF($D$24="(All)","*",$D$24),Trades!$AE$2:$AE$74,IF($G$24="(All)","*",$G$24)),"") | K30: =IFERROR(AVERAGEIFS(Trades!$O$2:$O$74,Trades!$AF$2:$AF$74,$A$30,Trades!$C$2:$C$74,IF($D$24="(All)","*",$D$24),Trades!$AE$2:$AE$74,IF($G$24="(All)","*",$G$24)),"") | L30: =IFERROR(E30/SUMIFS(Trades!$AD$2:$AD$74,Trades!$C$2:$C$74,IF($D$24="(All)","*",$D$24),Trades!$AE$2:$AE$74,IF($G$24="(All)","*",$G$24))*100,"")
A31: All trades | B31: =COUNTIFS(Trades!$C$2:$C$74,IF($D$24="(All)","*",$D$24),Trades!$AE$2:$AE$74,IF($G$24="(All)","*",$G$24)) | C31: =COUNTIFS(Trades!$AE$2:$AE$74,"Win",Trades!$C$2:$C$74,IF($D$24="(All)","*",$D$24),Trades!$AE$2:$AE$74,IF($G$24="(All)","*",$G$24)) | D31: =IFERROR(C31/B31*100,"") | E31: =SUMIFS(Trades!$AD$2:$AD$74,Trades!$C$2:$C$74,IF($D$24="(All)","*",$D$24),Trades!$AE$2:$AE$74,IF($G$24="(All)","*",$G$24)) | F31: =IFERROR(E31/B31,"") | G31: =IFERROR(AVERAGEIFS(Trades!$Z$2:$Z$74,Trades!$C$2:$C$74,IF($D$24="(All)","*",$D$24),Trades!$AE$2:$AE$74,IF($G$24="(All)","*",$G$24)),"") | H31: =IFERROR(SUMIFS(Trades!$AD$2:$AD$74,Trades!$AD$2:$AD$74,">0",Trades!$C$2:$C$74,IF($D$24="(All)","*",$D$24),Trades!$AE$2:$AE$74,IF($G$24="(All)","*",$G$24))/-SUMIFS(Trades!$AD$2:$AD$74,Trades!$AD$2:$AD$74,"<0",Trades!$C$2:$C$74,IF($D$24="(All)","*",$D$24),Trades!$AE$2:$AE$74,IF($G$24="(All)","*",$G$24)),"") | I31: =IFERROR(AVERAGEIFS(Trades!$AH$2:$AH$74,Trades!$C$2:$C$74,IF($D$24="(All)","*",$D$24),Trades!$AE$2:$AE$74,IF($G$24="(All)","*",$G$24)),"") | J31: =IFERROR(AVERAGEIFS(Trades!$AI$2:$AI$74,Trades!$C$2:$C$74,IF($D$24="(All)","*",$D$24),Trades!$AE$2:$AE$74,IF($G$24="(All)","*",$G$24)),"") | K31: =IFERROR(AVERAGEIFS(Trades!$O$2:$O$74,Trades!$C$2:$C$74,IF($D$24="(All)","*",$D$24),Trades!$AE$2:$AE$74,IF($G$24="(All)","*",$G$24)),"") | L31: =IFERROR(E31/SUMIFS(Trades!$AD$2:$AD$74,Trades!$C$2:$C$74,IF($D$24="(All)","*",$D$24),Trades!$AE$2:$AE$74,IF($G$24="(All)","*",$G$24))*100,"")

Sheet Risk
A1: Risk and sequence
A2: Sizing consistency, drawdown depth, and what streaks did to the balance. Sequence matters: the same trades in a different order produce a different drawdown.
A4: Sizing
A5: Average risk | D5: 5.92 | F5: Money at stake per trade, from entry to the initial stop.
A6: Median risk | D6: 5.15 | F6: Half the trades risked less than this.
A7: Risk consistency | D7: 0.408 | F7: Standard deviation divided by the mean. Under 0.30 is disciplined sizing; above 0.60 means the size is being chosen by feel, and one oversized loss can undo a good month.
A8: Average risk % of balance | D8: 0.59 | F8: Against the balance standing before each trade.
A9: Largest risk % of balance | D9: 1.272 | F9: The single most exposed trade in the record.
A10: Average planned RR | D10: 1.52 | F10: Reward-to-risk as set at entry, where both a stop and a target existed.
A11: Realised R per trade | D11: 0.225 | F11: Compare with planned RR above: a wide gap is trades not being held to their own plan.
A14: Drawdown
A15: Maximum drawdown | D15: -84.51 | F15: 8.2% below the equity peak.
A16: Recovery factor | D16: 1.193 | F16: Net profit divided by that drawdown. Under 1.0 means the account has not yet made back more than its worst decline.
A17: Longest drawdown | D17: 29 | F17: Trades spent below the previous equity peak - the number that actually tests patience.
A18: Worst losing run | D18: -54.4 | F18: 6 consecutive losses.
A19: Best winning run | D19: 80.08 | F19: 3 consecutive wins.
A20: Current streak | D20: 3 | F20: Positive is wins, negative is losses, as of the last closed trade.
A21: Standard deviation per trade | D21: 13.72 | F21: The spread the expectancy is drawn from. A large value next to a small expectancy is why the equity curve feels rough.
A22: Largest win | D22: 50.23 | F22: Check this against average win: if one trade carries the account, the record is thinner than the net suggests.
A23: Largest loss | D23: -16.43 | F23: Against average risk, this shows whether stops held.
A26: Filters | C26: Symbol | D26: (All) | F26: Outcome | G26: (All) | I26: Change either dropdown - every grid below recalculates.
A28: By stop management | E28: Whether moving the stop after entry paid for itself. 'Tightened' with a worse net than 'Unchanged' means stops are being moved too early.
A29: SL moved | B29: Trades | C29: Wins | D29: Win % | E29: Net | F29: Expectancy | G29: Avg R | H29: Profit factor | I29: Avg MFE | J29: Avg MAE | K29: Avg dur (min) | L29: Share of net
A30: Breakeven | B30: =COUNTIFS(Trades!$V$2:$V$74,$A$30,Trades!$C$2:$C$74,IF($D$26="(All)","*",$D$26),Trades!$AE$2:$AE$74,IF($G$26="(All)","*",$G$26)) | C30: =COUNTIFS(Trades!$AE$2:$AE$74,"Win",Trades!$V$2:$V$74,$A$30,Trades!$C$2:$C$74,IF($D$26="(All)","*",$D$26),Trades!$AE$2:$AE$74,IF($G$26="(All)","*",$G$26)) | D30: =IFERROR(C30/B30*100,"") | E30: =SUMIFS(Trades!$AD$2:$AD$74,Trades!$V$2:$V$74,$A$30,Trades!$C$2:$C$74,IF($D$26="(All)","*",$D$26),Trades!$AE$2:$AE$74,IF($G$26="(All)","*",$G$26)) | F30: =IFERROR(E30/B30,"") | G30: =IFERROR(AVERAGEIFS(Trades!$Z$2:$Z$74,Trades!$V$2:$V$74,$A$30,Trades!$C$2:$C$74,IF($D$26="(All)","*",$D$26),Trades!$AE$2:$AE$74,IF($G$26="(All)","*",$G$26)),"") | H30: =IFERROR(SUMIFS(Trades!$AD$2:$AD$74,Trades!$V$2:$V$74,$A$30,Trades!$AD$2:$AD$74,">0",Trades!$C$2:$C$74,IF($D$26="(All)","*",$D$26),Trades!$AE$2:$AE$74,IF($G$26="(All)","*",$G$26))/-SUMIFS(Trades!$AD$2:$AD$74,Trades!$V$2:$V$74,$A$30,Trades!$AD$2:$AD$74,"<0",Trades!$C$2:$C$74,IF($D$26="(All)","*",$D$26),Trades!$AE$2:$AE$74,IF($G$26="(All)","*",$G$26)),"") | I30: =IFERROR(AVERAGEIFS(Trades!$AH$2:$AH$74,Trades!$V$2:$V$74,$A$30,Trades!$C$2:$C$74,IF($D$26="(All)","*",$D$26),Trades!$AE$2:$AE$74,IF($G$26="(All)","*",$G$26)),"") | J30: =IFERROR(AVERAGEIFS(Trades!$AI$2:$AI$74,Trades!$V$2:$V$74,$A$30,Trades!$C$2:$C$74,IF($D$26="(All)","*",$D$26),Trades!$AE$2:$AE$74,IF($G$26="(All)","*",$G$26)),"") | K30: =IFERROR(AVERAGEIFS(Trades!$O$2:$O$74,Trades!$V$2:$V$74,$A$30,Trades!$C$2:$C$74,IF($D$26="(All)","*",$D$26),Trades!$AE$2:$AE$74,IF($G$26="(All)","*",$G$26)),"") | L30: =IFERROR(E30/SUMIFS(Trades!$AD$2:$AD$74,Trades!$C$2:$C$74,IF($D$26="(All)","*",$D$26),Trades!$AE$2:$AE$74,IF($G$26="(All)","*",$G$26))*100,"")
A31: Tightened | B31: =COUNTIFS(Trades!$V$2:$V$74,$A$31,Trades!$C$2:$C$74,IF($D$26="(All)","*",$D$26),Trades!$AE$2:$AE$74,IF($G$26="(All)","*",$G$26)) | C31: =COUNTIFS(Trades!$AE$2:$AE$74,"Win",Trades!$V$2:$V$74,$A$31,Trades!$C$2:$C$74,IF($D$26="(All)","*",$D$26),Trades!$AE$2:$AE$74,IF($G$26="(All)","*",$G$26)) | D31: =IFERROR(C31/B31*100,"") | E31: =SUMIFS(Trades!$AD$2:$AD$74,Trades!$V$2:$V$74,$A$31,Trades!$C$2:$C$74,IF($D$26="(All)","*",$D$26),Trades!$AE$2:$AE$74,IF($G$26="(All)","*",$G$26)) | F31: =IFERROR(E31/B31,"") | G31: =IFERROR(AVERAGEIFS(Trades!$Z$2:$Z$74,Trades!$V$2:$V$74,$A$31,Trades!$C$2:$C$74,IF($D$26="(All)","*",$D$26),Trades!$AE$2:$AE$74,IF($G$26="(All)","*",$G$26)),"") | H31: =IFERROR(SUMIFS(Trades!$AD$2:$AD$74,Trades!$V$2:$V$74,$A$31,Trades!$AD$2:$AD$74,">0",Trades!$C$2:$C$74,IF($D$26="(All)","*",$D$26),Trades!$AE$2:$AE$74,IF($G$26="(All)","*",$G$26))/-SUMIFS(Trades!$AD$2:$AD$74,Trades!$V$2:$V$74,$A$31,Trades!$AD$2:$AD$74,"<0",Trades!$C$2:$C$74,IF($D$26="(All)","*",$D$26),Trades!$AE$2:$AE$74,IF($G$26="(All)","*",$G$26)),"") | I31: =IFERROR(AVERAGEIFS(Trades!$AH$2:$AH$74,Trades!$V$2:$V$74,$A$31,Trades!$C$2:$C$74,IF($D$26="(All)","*",$D$26),Trades!$AE$2:$AE$74,IF($G$26="(All)","*",$G$26)),"") | J31: =IFERROR(AVERAGEIFS(Trades!$AI$2:$AI$74,Trades!$V$2:$V$74,$A$31,Trades!$C$2:$C$74,IF($D$26="(All)","*",$D$26),Trades!$AE$2:$AE$74,IF($G$26="(All)","*",$G$26)),"") | K31: =IFERROR(AVERAGEIFS(Trades!$O$2:$O$74,Trades!$V$2:$V$74,$A$31,Trades!$C$2:$C$74,IF($D$26="(All)","*",$D$26),Trades!$AE$2:$AE$74,IF($G$26="(All)","*",$G$26)),"") | L31: =IFERROR(E31/SUMIFS(Trades!$AD$2:$AD$74,Trades!$C$2:$C$74,IF($D$26="(All)","*",$D$26),Trades!$AE$2:$AE$74,IF($G$26="(All)","*",$G$26))*100,"")
A32: Unchanged | B32: =COUNTIFS(Trades!$V$2:$V$74,$A$32,Trades!$C$2:$C$74,IF($D$26="(All)","*",$D$26),Trades!$AE$2:$AE$74,IF($G$26="(All)","*",$G$26)) | C32: =COUNTIFS(Trades!$AE$2:$AE$74,"Win",Trades!$V$2:$V$74,$A$32,Trades!$C$2:$C$74,IF($D$26="(All)","*",$D$26),Trades!$AE$2:$AE$74,IF($G$26="(All)","*",$G$26)) | D32: =IFERROR(C32/B32*100,"") | E32: =SUMIFS(Trades!$AD$2:$AD$74,Trades!$V$2:$V$74,$A$32,Trades!$C$2:$C$74,IF($D$26="(All)","*",$D$26),Trades!$AE$2:$AE$74,IF($G$26="(All)","*",$G$26)) | F32: =IFERROR(E32/B32,"") | G32: =IFERROR(AVERAGEIFS(Trades!$Z$2:$Z$74,Trades!$V$2:$V$74,$A$32,Trades!$C$2:$C$74,IF($D$26="(All)","*",$D$26),Trades!$AE$2:$AE$74,IF($G$26="(All)","*",$G$26)),"") | H32: =IFERROR(SUMIFS(Trades!$AD$2:$AD$74,Trades!$V$2:$V$74,$A$32,Trades!$AD$2:$AD$74,">0",Trades!$C$2:$C$74,IF($D$26="(All)","*",$D$26),Trades!$AE$2:$AE$74,IF($G$26="(All)","*",$G$26))/-SUMIFS(Trades!$AD$2:$AD$74,Trades!$V$2:$V$74,$A$32,Trades!$AD$2:$AD$74,"<0",Trades!$C$2:$C$74,IF($D$26="(All)","*",$D$26),Trades!$AE$2:$AE$74,IF($G$26="(All)","*",$G$26)),"") | I32: =IFERROR(AVERAGEIFS(Trades!$AH$2:$AH$74,Trades!$V$2:$V$74,$A$32,Trades!$C$2:$C$74,IF($D$26="(All)","*",$D$26),Trades!$AE$2:$AE$74,IF($G$26="(All)","*",$G$26)),"") | J32: =IFERROR(AVERAGEIFS(Trades!$AI$2:$AI$74,Trades!$V$2:$V$74,$A$32,Trades!$C$2:$C$74,IF($D$26="(All)","*",$D$26),Trades!$AE$2:$AE$74,IF($G$26="(All)","*",$G$26)),"") | K32: =IFERROR(AVERAGEIFS(Trades!$O$2:$O$74,Trades!$V$2:$V$74,$A$32,Trades!$C$2:$C$74,IF($D$26="(All)","*",$D$26),Trades!$AE$2:$AE$74,IF($G$26="(All)","*",$G$26)),"") | L32: =IFERROR(E32/SUMIFS(Trades!$AD$2:$AD$74,Trades!$C$2:$C$74,IF($D$26="(All)","*",$D$26),Trades!$AE$2:$AE$74,IF($G$26="(All)","*",$G$26))*100,"")
A33: Widened | B33: =COUNTIFS(Trades!$V$2:$V$74,$A$33,Trades!$C$2:$C$74,IF($D$26="(All)","*",$D$26),Trades!$AE$2:$AE$74,IF($G$26="(All)","*",$G$26)) | C33: =COUNTIFS(Trades!$AE$2:$AE$74,"Win",Trades!$V$2:$V$74,$A$33,Trades!$C$2:$C$74,IF($D$26="(All)","*",$D$26),Trades!$AE$2:$AE$74,IF($G$26="(All)","*",$G$26)) | D33: =IFERROR(C33/B33*100,"") | E33: =SUMIFS(Trades!$AD$2:$AD$74,Trades!$V$2:$V$74,$A$33,Trades!$C$2:$C$74,IF($D$26="(All)","*",$D$26),Trades!$AE$2:$AE$74,IF($G$26="(All)","*",$G$26)) | F33: =IFERROR(E33/B33,"") | G33: =IFERROR(AVERAGEIFS(Trades!$Z$2:$Z$74,Trades!$V$2:$V$74,$A$33,Trades!$C$2:$C$74,IF($D$26="(All)","*",$D$26),Trades!$AE$2:$AE$74,IF($G$26="(All)","*",$G$26)),"") | H33: =IFERROR(SUMIFS(Trades!$AD$2:$AD$74,Trades!$V$2:$V$74,$A$33,Trades!$AD$2:$AD$74,">0",Trades!$C$2:$C$74,IF($D$26="(All)","*",$D$26),Trades!$AE$2:$AE$74,IF($G$26="(All)","*",$G$26))/-SUMIFS(Trades!$AD$2:$AD$74,Trades!$V$2:$V$74,$A$33,Trades!$AD$2:$AD$74,"<0",Trades!$C$2:$C$74,IF($D$26="(All)","*",$D$26),Trades!$AE$2:$AE$74,IF($G$26="(All)","*",$G$26)),"") | I33: =IFERROR(AVERAGEIFS(Trades!$AH$2:$AH$74,Trades!$V$2:$V$74,$A$33,Trades!$C$2:$C$74,IF($D$26="(All)","*",$D$26),Trades!$AE$2:$AE$74,IF($G$26="(All)","*",$G$26)),"") | J33: =IFERROR(AVERAGEIFS(Trades!$AI$2:$AI$74,Trades!$V$2:$V$74,$A$33,Trades!$C$2:$C$74,IF($D$26="(All)","*",$D$26),Trades!$AE$2:$AE$74,IF($G$26="(All)","*",$G$26)),"") | K33: =IFERROR(AVERAGEIFS(Trades!$O$2:$O$74,Trades!$V$2:$V$74,$A$33,Trades!$C$2:$C$74,IF($D$26="(All)","*",$D$26),Trades!$AE$2:$AE$74,IF($G$26="(All)","*",$G$26)),"") | L33: =IFERROR(E33/SUMIFS(Trades!$AD$2:$AD$74,Trades!$C$2:$C$74,IF($D$26="(All)","*",$D$26),Trades!$AE$2:$AE$74,IF($G$26="(All)","*",$G$26))*100,"")
A34: All trades | B34: =COUNTIFS(Trades!$C$2:$C$74,IF($D$26="(All)","*",$D$26),Trades!$AE$2:$AE$74,IF($G$26="(All)","*",$G$26)) | C34: =COUNTIFS(Trades!$AE$2:$AE$74,"Win",Trades!$C$2:$C$74,IF($D$26="(All)","*",$D$26),Trades!$AE$2:$AE$74,IF($G$26="(All)","*",$G$26)) | D34: =IFERROR(C34/B34*100,"") | E34: =SUMIFS(Trades!$AD$2:$AD$74,Trades!$C$2:$C$74,IF($D$26="(All)","*",$D$26),Trades!$AE$2:$AE$74,IF($G$26="(All)","*",$G$26)) | F34: =IFERROR(E34/B34,"") | G34: =IFERROR(AVERAGEIFS(Trades!$Z$2:$Z$74,Trades!$C$2:$C$74,IF($D$26="(All)","*",$D$26),Trades!$AE$2:$AE$74,IF($G$26="(All)","*",$G$26)),"") | H34: =IFERROR(SUMIFS(Trades!$AD$2:$AD$74,Trades!$AD$2:$AD$74,">0",Trades!$C$2:$C$74,IF($D$26="(All)","*",$D$26),Trades!$AE$2:$AE$74,IF($G$26="(All)","*",$G$26))/-SUMIFS(Trades!$AD$2:$AD$74,Trades!$AD$2:$AD$74,"<0",Trades!$C$2:$C$74,IF($D$26="(All)","*",$D$26),Trades!$AE$2:$AE$74,IF($G$26="(All)","*",$G$26)),"") | I34: =IFERROR(AVERAGEIFS(Trades!$AH$2:$AH$74,Trades!$C$2:$C$74,IF($D$26="(All)","*",$D$26),Trades!$AE$2:$AE$74,IF($G$26="(All)","*",$G$26)),"") | J34: =IFERROR(AVERAGEIFS(Trades!$AI$2:$AI$74,Trades!$C$2:$C$74,IF($D$26="(All)","*",$D$26),Trades!$AE$2:$AE$74,IF($G$26="(All)","*",$G$26)),"") | K34: =IFERROR(AVERAGEIFS(Trades!$O$2:$O$74,Trades!$C$2:$C$74,IF($D$26="(All)","*",$D$26),Trades!$AE$2:$AE$74,IF($G$26="(All)","*",$G$26)),"") | L34: =IFERROR(E34/SUMIFS(Trades!$AD$2:$AD$74,Trades!$C$2:$C$74,IF($D$26="(All)","*",$D$26),Trades!$AE$2:$AE$74,IF($G$26="(All)","*",$G$26))*100,"")
A37: By position in the streak | E37: Streak counts the trade itself: -1 is the first loss after a win, -2 the second in a row. If the net worsens as the streak deepens, the losing runs are being made worse by the trading, not just by the market.
A38: Streak | B38: Trades | C38: Wins | D38: Win % | E38: Net | F38: Expectancy | G38: Avg R | H38: Profit factor | I38: Avg MFE | J38: Avg MAE | K38: Avg dur (min) | L38: Share of net
A39: -6 | B39: =COUNTIFS(Trades!$BB$2:$BB$74,$A$39,Trades!$C$2:$C$74,IF($D$26="(All)","*",$D$26),Trades!$AE$2:$AE$74,IF($G$26="(All)","*",$G$26)) | C39: =COUNTIFS(Trades!$AE$2:$AE$74,"Win",Trades!$BB$2:$BB$74,$A$39,Trades!$C$2:$C$74,IF($D$26="(All)","*",$D$26),Trades!$AE$2:$AE$74,IF($G$26="(All)","*",$G$26)) | D39: =IFERROR(C39/B39*100,"") | E39: =SUMIFS(Trades!$AD$2:$AD$74,Trades!$BB$2:$BB$74,$A$39,Trades!$C$2:$C$74,IF($D$26="(All)","*",$D$26),Trades!$AE$2:$AE$74,IF($G$26="(All)","*",$G$26)) | F39: =IFERROR(E39/B39,"") | G39: =IFERROR(AVERAGEIFS(Trades!$Z$2:$Z$74,Trades!$BB$2:$BB$74,$A$39,Trades!$C$2:$C$74,IF($D$26="(All)","*",$D$26),Trades!$AE$2:$AE$74,IF($G$26="(All)","*",$G$26)),"") | H39: =IFERROR(SUMIFS(Trades!$AD$2:$AD$74,Trades!$BB$2:$BB$74,$A$39,Trades!$AD$2:$AD$74,">0",Trades!$C$2:$C$74,IF($D$26="(All)","*",$D$26),Trades!$AE$2:$AE$74,IF($G$26="(All)","*",$G$26))/-SUMIFS(Trades!$AD$2:$AD$74,Trades!$BB$2:$BB$74,$A$39,Trades!$AD$2:$AD$74,"<0",Trades!$C$2:$C$74,IF($D$26="(All)","*",$D$26),Trades!$AE$2:$AE$74,IF($G$26="(All)","*",$G$26)),"") | I39: =IFERROR(AVERAGEIFS(Trades!$AH$2:$AH$74,Trades!$BB$2:$BB$74,$A$39,Trades!$C$2:$C$74,IF($D$26="(All)","*",$D$26),Trades!$AE$2:$AE$74,IF($G$26="(All)","*",$G$26)),"") | J39: =IFERROR(AVERAGEIFS(Trades!$AI$2:$AI$74,Trades!$BB$2:$BB$74,$A$39,Trades!$C$2:$C$74,IF($D$26="(All)","*",$D$26),Trades!$AE$2:$AE$74,IF($G$26="(All)","*",$G$26)),"") | K39: =IFERROR(AVERAGEIFS(Trades!$O$2:$O$74,Trades!$BB$2:$BB$74,$A$39,Trades!$C$2:$C$74,IF($D$26="(All)","*",$D$26),Trades!$AE$2:$AE$74,IF($G$26="(All)","*",$G$26)),"") | L39: =IFERROR(E39/SUMIFS(Trades!$AD$2:$AD$74,Trades!$C$2:$C$74,IF($D$26="(All)","*",$D$26),Trades!$AE$2:$AE$74,IF($G$26="(All)","*",$G$26))*100,"")
A40: -5 | B40: =COUNTIFS(Trades!$BB$2:$BB$74,$A$40,Trades!$C$2:$C$74,IF($D$26="(All)","*",$D$26),Trades!$AE$2:$AE$74,IF($G$26="(All)","*",$G$26)) | C40: =COUNTIFS(Trades!$AE$2:$AE$74,"Win",Trades!$BB$2:$BB$74,$A$40,Trades!$C$2:$C$74,IF($D$26="(All)","*",$D$26),Trades!$AE$2:$AE$74,IF($G$26="(All)","*",$G$26)) | D40: =IFERROR(C40/B40*100,"") | E40: =SUMIFS(Trades!$AD$2:$AD$74,Trades!$BB$2:$BB$74,$A$40,Trades!$C$2:$C$74,IF($D$26="(All)","*",$D$26),Trades!$AE$2:$AE$74,IF($G$26="(All)","*",$G$26)) | F40: =IFERROR(E40/B40,"") | G40: =IFERROR(AVERAGEIFS(Trades!$Z$2:$Z$74,Trades!$BB$2:$BB$74,$A$40,Trades!$C$2:$C$74,IF($D$26="(All)","*",$D$26),Trades!$AE$2:$AE$74,IF($G$26="(All)","*",$G$26)),"") | H40: =IFERROR(SUMIFS(Trades!$AD$2:$AD$74,Trades!$BB$2:$BB$74,$A$40,Trades!$AD$2:$AD$74,">0",Trades!$C$2:$C$74,IF($D$26="(All)","*",$D$26),Trades!$AE$2:$AE$74,IF($G$26="(All)","*",$G$26))/-SUMIFS(Trades!$AD$2:$AD$74,Trades!$BB$2:$BB$74,$A$40,Trades!$AD$2:$AD$74,"<0",Trades!$C$2:$C$74,IF($D$26="(All)","*",$D$26),Trades!$AE$2:$AE$74,IF($G$26="(All)","*",$G$26)),"") | I40: =IFERROR(AVERAGEIFS(Trades!$AH$2:$AH$74,Trades!$BB$2:$BB$74,$A$40,Trades!$C$2:$C$74,IF($D$26="(All)","*",$D$26),Trades!$AE$2:$AE$74,IF($G$26="(All)","*",$G$26)),"") | J40: =IFERROR(AVERAGEIFS(Trades!$AI$2:$AI$74,Trades!$BB$2:$BB$74,$A$40,Trades!$C$2:$C$74,IF($D$26="(All)","*",$D$26),Trades!$AE$2:$AE$74,IF($G$26="(All)","*",$G$26)),"") | K40: =IFERROR(AVERAGEIFS(Trades!$O$2:$O$74,Trades!$BB$2:$BB$74,$A$40,Trades!$C$2:$C$74,IF($D$26="(All)","*",$D$26),Trades!$AE$2:$AE$74,IF($G$26="(All)","*",$G$26)),"") | L40: =IFERROR(E40/SUMIFS(Trades!$AD$2:$AD$74,Trades!$C$2:$C$74,IF($D$26="(All)","*",$D$26),Trades!$AE$2:$AE$74,IF($G$26="(All)","*",$G$26))*100,"")
